Workbook
Name ClsRecords: RSCLASS!$B$17
Name EqpRecords: RSMEQP!$C$17
Name MNUMRTTY: RSMEQP!$C$19
Name nClDryClasses: RSCLASS!$H$58
Name nClDryTypes: RSMEQP!$I$896
Name nClWashClasses: RSCLASS!$D$58
Name nClWashTypes: RSMEQP!$E$896
Name nCookClasses: RSCLASS!$G$58
Name nCookTypes: RSMEQP!$H$896
Name nCoolClasses: RSCLASS!$C$58
Name nCoolTypes: RSMEQP!$D$896
Name nDishClasses: RSCLASS!$E$58
Name nDishTypes: RSMEQP!$F$896
Name nFrezClasses: RSCLASS!$J$58
Name nFrezTypes: RSMEQP!$K$896
Name nHeatClasses: RSCLASS!$B$58
Name nHeatTypes: RSMEQP!$C$896
Name nRefrClasses: RSCLASS!$I$58
Name nRefrTypes: RSMEQP!$J$896
Name nShellTypes: RSMSHL!$B$14
Name nWatHtClasses: RSCLASS!$F$58
Name nWatHtTypes: RSMEQP!$G$896
Name RSHLDOLLARYR: RSMSHL!$B$16
Name RTEKDOLLARYR: RSMEQP!$C$18
Name ShlRecords: RSMSHL!$B$15
Name xlCLSHBASE: RSMSHL!$O$25:$O$2214
Name xlCLSHEFF: RSMSHL!$M$25:$M$2214
Name xlCWMEF: RSMEQP!$K$25:$K$889
Name xlHTSHBASE: RSMSHL!$N$25:$N$2214
Name xlHTSHEFF: RSMSHL!$L$25:$L$2214
Name xlHVACPNTR: RSMEQP!$I$25:$I$889
Name xlHVCLEQCL: RSMSHL!$F$25:$F$2214
Name xlHVCLEQTY: RSMSHL!$G$25:$G$2214
Name xlHVCOOLFACTOR: RSMSHL!$K$25:$K$2214
Name xlHVFYEAR: RSMSHL!$H$25:$H$2214
Name xlHVHEATFACTOR: RSMSHL!$J$25:$J$2214
Name xlHVHTEQCL: RSMSHL!$D$25:$D$2214
Name xlHVHTEQTY: RSMSHL!$E$25:$E$2214
Name xlHVLYEAR: RSMSHL!$I$25:$I$2214
Name xlHVPACKG: RSMSHL!$S$25:$S$2214
Name xlHVPGNAME: RSMSHL!$T$25:$T$2214
Name xlLOADADJ: RSMEQP!$L$25:$L$889
Name xlRSBTYPE: RSMSHL!$C$25:$C$2214
Name xlRSCENDIV: RSMSHL!$B$25:$B$2214
Name xlRTALPHA: RSCLASS!$N$22:$N$51
Name xlRTBASEFF: RSCLASS!$J$22:$J$51
Name xlRTCENDIV: RSMEQP!$H$25:$H$889
Name xlRTCLENDU: RSCLASS!$C$22:$C$51
Name xlRTCLEQCL: RSCLASS!$D$22:$D$51
Name xlRTCLNAME: RSCLASS!$U$22:$U$51
Name xlRTCLPNTR: RSCLASS!$F$22:$F$51
Name xlRTCLREPL: RSCLASS!$G$22:$G$51
Name xlRTCLTYPT: RSCLASS!$E$22:$E$51
Name xlRTCOSTP1: RSMEQP!$W$25:$W$889
Name xlRTCOSTP2: RSMEQP!$X$25:$X$889
Name xlRTCOSTP3: RSMEQP!$Y$25:$Y$889
Name xlRTECBIAS: RSMEQP!$AC$25:$AC$889
Name xlRTECBTA1: RSMEQP!$Z$25:$Z$889
Name xlRTECBTA2: RSMEQP!$AA$25:$AA$889
Name xlRTECBTA3: RSMEQP!$AB$25:$AB$889

Sheet READ_ME
B2: FILE NAME | C2: Residential Menus for Equipment, Shells, and Subsidies (RSMESS)
B3: USED BY | C3: RTEKREAD subroutine of the National Energy Modeling System (NEMS) Residential Demand Module (RDM)
B4: DEFINITION | C4: Residential sector menu for equipment and shell selection
B6: Tab | C6: Content | D6: Source | E6: Comment | F6: Last Modified
B7: RSCLASS | C7: Residential major end-use equipment class inputs | D7: See tab for sources | E7: Formerly contained in RSCLASS.txt input file | F7: =RSCLASS!$C$3 -> 45484
B8: RSMEQP | C8: Residential major end-use equipment technology menu | D8: See tab for sources | E8: Formerly contained in RSMEQP.txt input file Correct vintage year rows must be present to pull in all applicable values. | F8: =RSMEQP!$D$3 -> 45597
B9: RSMSHL | C9: Residential shell package inputs | D9: See tab for sources | E9: Formerly contained in RSMSHL.txt input file; subsidies are looked up automatically, but correct vintage year rows must be present to pull in all applicable values | F9: =RSMSHL!$C$3 -> 45601
B10: TaxCred&Subs | C10: Equipment and whole-building subsidy lookup tables for federal tax credits, non-federal energy efficiency subsidies, and CPP energy efficiency subsidies | D10: See tab for sources | E10: Updated non-federal energy efficiency rebates based on 2022 data. | F10: ='TaxCred&Subs'!$C$2 -> 45575

Sheet RSCLASS
B2: FILE NAME | C2: RSCLASS
B3: DATE MODIFIED | C3: 45484
B4: DEFINITION | C4: Residential technology equipment class descriptions (pointers and flags for major end-use equipment types)
B5: UNITS | C5: None
B6: DIMENSION | C6: Housing type, Census division, equipment type
B7: SPECIAL CONSTRAINTS | C7: Varies
B8: ORGANIZATION OF DATA | C8: Number classes 1, 2 , 3, ... must match RSM(EQP and SHL) class numbers
C9: Do not change equipment class names (RTCLNAME); RTCLENDU mapping shown in Table 1 and RTFUEL mapping shown in Table 2 of RDM documentation
C10: RTxxxxxx are RESD variable names (also named ranges in Excel); total available number of RSCLASS rows controlled by MNUMRTCL in RTEK includes file
C11: File must be sorted by column one (RTCLENDU) then column two (RTCLEQCL)
B12: SOURCES | C12: Guidehouse and Leidos, EIA - Technology Forecast Updates – Residential and Commercial Building Technologies – Reference Case, March, 2023 (https://www.eia.gov/analysis/studies/buildings/equipcosts/)
C13: Weibull parameters sourced from various DOE rulemaking technical support documents accessed through https://www.energy.gov/eere/buildings/standards-and-test-procedures
B14: COMMENT | C14: Updated base efficiencies and equipment life parameters based on latest technology report and DOE TSDs
B17: =COUNTA(xlRTCLENDU) -> 30 | C17: Number of class records (ClsRecords)
L18: scale (α) | M18: shape (β) | N18: delay (θ) | O18: <- Descriptions from DOE Technical Support Documents
L19: Equipment Life Parameters
B20: End Use/ Class Lookup | C20: End Use | D20: Equipment Class | E20: Type Pointer | F20: Equipment Class Pointer | G20: Replacement Equipment Class | H20: Fuel | I20: Furnace Fan Flag | J20: Base Efficiency | K20: Efficiency Metric | L20: Weibull λ | M20: Weibull K | N20: Alpha | O20: Minimum Equipment Life (Years) | P20: Maximum Equipment Life (Years) | Q20: New Beta | R20: Switching Factor | S20: Replacement Beta | T20: Bias | U20: Equipment Class Name
B21: - | C21: xlRTCLENDU | D21: xlRTCLEQCL | E21: xlRTCLTYPT | F21: xlRTCLPNTR | G21: xlRTCLREPL | H21: xlRTFUEL | I21: xlRTFFAN | J21: xlRTBASEFF | K21: - | L21: xlRTLAMBDA | M21: xlRTK | N21: xlRTALPHA | O21: - | P21: - | Q21: xlRTFCBETA | R21: xlRTSWFACT | S21: xlRTSWBETA | T21: xlRTSWBIAS | U21: xlRTCLNAME | V21: <- RSCLASS variable names
B22: =C22&D22 -> 11 | C22: 1 | D22: 1 | E22: {=MIN(IF(($C22=xlRTTYENDU)*($D22=xlRTTYEQCL),xlRTEQTYPE))} -> 1 | F22: 2 | G22: 3 | H22: 4 | I22: 0 | J22: 0.98 | K22: AFUE | L22: 23.9 | M22: 3.7 | N22: 1 | O22: 15 | P22: 30 | Q22: -0.00108 | R22: 0.2 | S22: -0.00172 | T22: -0.47 | U22: ELEC_RAD
B23: =C23&D23 -> 12 | C23: 1 | D23: 2 | E23: {=MIN(IF(($C23=xlRTTYENDU)*($D23=xlRTTYEQCL),xlRTEQTYPE))} -> 2 | F23: 2 | G23: 0 | H23: 4 | I23: 0 | J23: 2.3153576 | K23: COP | L23: 15.88 | M23: 2 | N23: 1 | O23: 15.3 | P23: 15.3 | Q23: -0.00108 | R23: 0.2 | S23: -0.00172 | T23: -0.1 | U23: ELEC_HP
B24: =C24&D24 -> 13 | C24: 1 | D24: 3 | E24: {=MIN(IF(($C24=xlRTTYENDU)*($D24=xlRTTYEQCL),xlRTEQTYPE))} -> 6 | F24: 1 | G24: 0 | H24: 3 | I24: 1 | J24: 0.8 | K24: AFUE | L24: 22.6 | M24: 3.7 | N24: 1 | O24: 16.1 | P24: 24.7 | Q24: -0.00108 | R24: 0 | S24: -0.00172 | T24: 0 | U24: NG_FA
B25: =C25&D25 -> 14 | C25: 1 | D25: 4 | E25: {=MIN(IF(($C25=xlRTTYENDU)*($D25=xlRTTYEQCL),xlRTEQTYPE))} -> 10 | F25: 1 | G25: 0 | H25: 3 | I25: 1 | J25: 0.82 | K25: AFUE | L25: 28.87 | M25: 2.39 | N25: 1 | O25: 20 | P25: 30 | Q25: -0.00108 | R25: 0 | S25: -0.00172 | T25: 0 | U25: NG_RAD
B26: =C26&D26 -> 15 | C26: 1 | D26: 5 | E26: {=MIN(IF(($C26=xlRTTYENDU)*($D26=xlRTTYEQCL),xlRTEQTYPE))} -> 14 | F26: 2 | G26: 0 | H26: 1 | I26: 0 | J26: 0.83 | K26: AFUE | L26: 23.9 | M26: 3.7 | N26: 1 | O26: 19.7 | P26: 33.1 | Q26: -0.00108 | R26: 0.2 | S26: -0.00172 | T26: -0.27 | U26: KERO_FA
B27: =C27&D27 -> 16 | C27: 1 | D27: 6 | E27: {=MIN(IF(($C27=xlRTTYENDU)*($D27=xlRTTYEQCL),xlRTEQTYPE))} -> 18 | F27: 4 | G27: 3 | H27: 2 | I27: 1 | J27: 0.8 | K27: AFUE | L27: 22.6 | M27: 3.7 | N27: 1 | O27: 16.1 | P27: 24.7 | Q27: -0.00108 | R27: 0.2 | S27: -0.00172 | T27: -0.03 | U27: LPG_FA
B28: =C28&D28 -> 17 | C28: 1 | D28: 7 | E28: {=MIN(IF(($C28=xlRTTYENDU)*($D28=xlRTTYEQCL),xlRTEQTYPE))} -> 22 | F28: 3 | G28: 3 | H28: 1 | I28: 1 | J28: 0.83 | K28: AFUE | L28: 23.9 | M28: 3.7 | N28: 1 | O28: 19.7 | P28: 33.1 | Q28: -0.00108 | R28: 0.2 | S28: -0.00172 | T28: -0.03 | U28: DIST_FA
B29: =C29&D29 -> 18 | C29: 1 | D29: 8 | E29: {=MIN(IF(($C29=xlRTTYENDU)*($D29=xlRTTYEQCL),xlRTEQTYPE))} -> 26 | F29: 3 | G29: 0 | H29: 1 | I29: 1 | J29: 0.84 | K29: AFUE | L29: 26.77 | M29: 2.39 | N29: 1 | O29: 18 | P29: 28 | Q29: -0.00108 | R29: 0.2 | S29: -0.00172 | T29: -0.03 | U29: DIST_RAD
B30: =C30&D30 -> 19 | C30: 1 | D30: 9 | E30: {=MIN(IF(($C30=xlRTTYENDU)*($D30=xlRTTYEQCL),xlRTEQTYPE))} -> 29 | F30: 2 | G30: 3 | H30: 6 | I30: 1 | J30: 0.63 | K30: HHV | L30: 20.23 | M30: 4.11 | N30: 1 | O30: 12 | P30: 25 | Q30: -0.00108 | R30: 0.3 | S30: -0.00172 | T30: -0.27 | U30: WOOD_HT
B31: =C31&D31 -> 110 | C31: 1 | D31: 10 | E31: {=MIN(IF(($C31=xlRTTYENDU)*($D31=xlRTTYEQCL),xlRTEQTYPE))} -> 31 | F31: 2 | G31: 0 | H31: 4 | I31: 0 | J31: 3.1 | K31: COP | L31: 17.04 | M31: 1.64 | N31: 1 | O31: 8 | P31: 20.8 | Q31: -0.00108 | R31: 0 | S31: -0.00172 | T31: -0.1 | U31: GEO_HP
B32: =C32&D32 -> 111 | C32: 1 | D32: 11 | E32: {=MIN(IF(($C32=xlRTTYENDU)*($D32=xlRTTYEQCL),xlRTEQTYPE))} -> 35 | F32: 1 | G32: 0 | H32: 3 | I32: 1 | J32: 1.3 | K32: COP | L32: 15.8 | M32: 7.21 | N32: 0.5 | O32: 12 | P32: 18 | Q32: -0.00108 | R32: 0 | S32: -0.00172 | T32: -0.1 | U32: NG_HP
B33: =C33&D33 -> 21 | C33: 2 | D33: 1 | E33: {=MIN(IF(($C33=xlRTTYENDU)*($D33=xlRTTYEQCL),xlRTEQTYPE))} -> 1 | F33: 0 | G33: 0 | H33: 4 | I33: 0 | J33: 3.1946073 | K33: COP | L33: 9.36 | M33: 2.49 | N33: 1 | O33: 6 | P33: 13 | Q33: 0 | R33: 0.1 | S33: -0.00172 | T33: 0 | U33: ROOM_AIR
... B51: =C51&D51 -> 91 | C51: 9 | D51: 1 | E51: {=MIN(IF(($C51=xlRTTYENDU)*($D51=xlRTTYEQCL),xlRTEQTYPE))} -> 1 | F51: 0 | G51: 0 | H51: 4 | I51: 0 | J51: 483.36048 | K51: kWh/yr | L51: 21.96 | M51: 1.83 | N51: 1 | O51: 21 | P51: 21 | Q51: 0 | R51: 0 | S51: -0.00172 | T51: 0 | U51: FREZ
B52: ^^ Insert new rows above, and extend named ranges if rows are inserted immediately above grey boxes ^^
B54: Used to modify technology parameters in resd.f (labeled !EqpParam)
B55: 1 | C55: 2 | D55: 3 | E55: 4 | F55: 5 | G55: 6 | H55: 7 | I55: 8 | J55: 9
B56: Space Heating | C56: Space Cooling | D56: ClothesWashing | E56: Dishwashing | F56: Water Heating | G56: Cooking | H56: Clothes Drying | I56: Refrigeration | J56: Standalone Freezing
B57: nHeatClasses | C57: nCoolClasses | D57: nClWashClasses | E57: nDishClasses | F57: nWatHtClasses | G57: nCookClasses | H57: nClDryClasses | I57: nRefrClasses | J57: nFrezClasses
B58: {=MAX(IF((xlRTCLENDU=B$55),xlRTCLEQCL,0))} -> 11 | C58: {=MAX(IF((xlRTCLENDU=C$55),xlRTCLEQCL,0))} -> 5 | D58: {=MAX(IF((xlRTCLENDU=D$55),xlRTCLEQCL,0))} -> 1 | E58: {=MAX(IF((xlRTCLENDU=E$55),xlRTCLEQCL,0))} -> 1 | F58: {=MAX(IF((xlRTCLENDU=F$55),xlRTCLEQCL,0))} -> 5 | G58: {=MAX(IF((xlRTCLENDU=G$55),xlRTCLEQCL,0))} -> 3 | H58: {=MAX(IF((xlRTCLENDU=H$55),xlRTCLEQCL,0))} -> 2 | I58: {=MAX(IF((xlRTCLENDU=I$55),xlRTCLEQCL,0))} -> 1 | J58: {=MAX(IF((xlRTCLENDU=J$55),xlRTCLEQCL,0))} -> 1

Sheet RSMEQP
C2: FILE NAME | D2: RSMEQP | L2: Changed value from prior version
C3: DATE MODIFIED | D3: 45597 | L3: New value
C4: DEFINITION | D4: Major end-use equipment technology menu | L4: Verify value
C5: UNITS | D5: Various= see RDM documentation for efficiency units
C6: DIMENSION | D6: End use, equipment class, Census division, end-use technology, vintage
C7: SPECIAL CONSTRAINTS | D7: Must be sorted by column one then column two
D8: End use (xlRTTYENDU) and class number (xlRTTYEQCL) must match xlRTCLENDU and xlRTCLEQCL in RSCLASS.txt input file, respectively
D9: Do not add equipment classes (xlRTTYEQCL)= do not change equipment class names (xlRTTYNAME)
D10: Each xlRTEQTYPE must range the full 2021-2050 projection period and begin with the same RTCLTYPT as in RSCLASS.txt
D11: Set xlRTCENDIV=11 if the entire data row applies to all census divisions; will not apply to ENERGY STAR or higher equipment that receives census division-level non-federal energy efficiency subsidies
C12: ORGANIZATION OF DATA | D12: xlRTxxxxxx labels are RDM variable names (also named ranges in Excel)
C13: SOURCES | D13: Guidehouse and Leidos, EIA - Technology Forecast Updates – Residential and Commercial Building Technologies – Reference Case, March, 2023 (https://www.eia.gov/analysis/studies/buildings/equipcosts/)
C14: COMMENT | D14: Revise base year for 2020 RECS; update equipment costs and characteristics using 2023 technology report; remove instances of Typical equipment that have same performance and cost characteristics as Current Standard or ENERGY STAR; incorporate revised federal minimum efficiency standards and ENERGY STAR specifications
C17: =COUNTA(xlRTTYENDU) -> 865 | D17: Number of technology records (EqpRecords)
C18: 2022 | D18: Equipment cost dollar year (RTEKDOLLARYR)
C19: =EqpRecords+COUNTIF(xlRTCENDIV,11)*8 -> 2097 | D19: Minimum array size parameter (MNUMRTTY)
V21: Cost Trend Function | Z21: Efficiency Choice Model Logit Parameters
C22: End Use | D22: Equipment Class | E22: Equipment Type | F22: First Year | G22: Last Year | H22: Census Division | I22: HVAC Pointer | J22: Type Pointer | K22: Clothes Washer Integrated Modified Energy Factor | L22: Hot Water Load Adjustment | M22: Efficiency | N22: Replacement Cost | O22: New Construction Cost | P22: Federal Replacement Subsidy | Q22: Federal New Construction Subsidy | R22: Non-Federal Replacement Subsidy | S22: Non-Federal New Construction Subsidy | T22: EE Replacement Subsidy | U22: EE New Construction Subsidy | V22: Maturity | W22: Cost Decline Initial Year | X22: Shape Parameter | Y22: Cost Decline | Z22: Beta_1 | AA22: Beta_2 | AB22: Beta_3 | AC22: Bias | AD22: Tech Name
C23: xlRTCLENDU | D23: xlRTCLEQCL | AE23: <- RSCLASS variable names
B24: xlI | C24: xlRTTYENDU | D24: xlRTTYEQCL | E24: xlRTEQTYPE | F24: xlRTINITYR | G24: xlRTLASTYR | H24: xlRTCENDIV | I24: xlHVACPNTR | J24: xlRTTYPNTR | K24: xlCWMEF | L24: xlLOADADJ | M24: xlRTEQEFF | N24: xlRTEQCOST | O24: xlRTRECOST | P24: xlRTEQSUB | Q24: xlRTRESUB | R24: xlRTEQSUBN | S24: xlRTRESUBN | T24: xlRTEQSUB111D | U24: xlRTRESUB111D | V24: xlRTMATURE | W24: xlRTCOSTP1 | X24: xlRTCOSTP2 | Y24: xlRTCOSTP3 | Z24: xlRTECBTA1 | AA24: xlRTECBTA2 | AB24: xlRTECBTA3 | AC24: xlRTECBIAS | AD24: xlRTTYNAME | AE24: <- RSMEQP variable names
B25: 1 | C25: 1 | D25: 1 | E25: 1 | F25: 2020 | G25: 2050 | H25: 11 | I25: 1 | J25: 0 | K25: 0 | L25: 0 | M25: 1 | N25: 1480 | O25: 950 | P25: {=ROUND(IF($F25<='TaxCred&Subs'!$C$49,(IF($C25=2,IF($M25>=IFERROR(INDEX('TaxCred&Subs'!$L$12:$L$47,MATCH(1,($C25&$D25='TaxCred&Subs'!$E$12:$E$47)*($F25='TaxCred&Subs'!$C$12:$C$47),0) ),9999),IFERROR(INDEX('TaxCred&Subs'!$N$12:$N$47,MATCH(1,($C25&$D25='TaxCred&Subs'!$E$12:$E$47)*($F25='TaxCred&Subs'!$C$12:$C$47),0) ),0),0),(IF($M25>=IFERROR(INDEX('TaxCred&Subs'!$H$12:$H$47,MATCH(1,($C25&$D25='TaxCred&Subs'!$D$12:$D$47)*($F25='TaxCred&Subs'!$C$12:$C$47),0) ),9999),IFERROR(INDEX('TaxCred&Subs'!$N$12:$N$47,MATCH(1,($C25&$D25='TaxCred&Subs'!$D$12:$D$47)*($F25='TaxCred&Subs'!$C$12:$C$47),0) ),0),0)))),0)+IF(AND($C25=2,VALUE(RIGHT($AD25,1))>2),(N25-R25)*(IFERROR(INDEX('TaxCred&Subs'!$J$66:$J$99,MATCH(1,($C25&$D25='TaxCred&Subs'!$E$66:$E$99)*($F25='TaxCred&Subs'!$C$66:$C$99),0)),0)),IF(AND($C25=1,VALUE(RIGHT($AD25,1))>2),(N25-R25)*(IFERROR(INDEX('TaxCred&Subs'!$J$66:$J$99,MATCH(1,($C25&$D25='TaxCred&Subs'!$D$66:$D$99)*($F25='TaxCred&Subs'!$C$66:$C$99),0)),0)),IF($C25>2,(N25-R25)*(IFERROR(INDEX('TaxCred&Subs'!$J$66:$J$99,MATCH(1,($C25&$D25='TaxCred&Subs'!$D$66:$D$99)*($F25='TaxCred&Subs'!$C$66:$C$99),0)),0)),0))),0)} -> 0 | Q25: {=ROUND(IF(AND($C25=2,VALUE(RIGHT($AD25,1))>2),(O25-S25)*(IFERROR(INDEX('TaxCred&Subs'!$J$66:$J$99,MATCH(1,($C25&$D25='TaxCred&Subs'!$E$66:$E$99)*($F25='TaxCred&Subs'!$C$66:$C$99),0)),0)),IF(AND($C25=1,VALUE(RIGHT($AD25,1))>2),(O25-S25)*(IFERROR(INDEX('TaxCred&Subs'!$J$66:$J$99,MATCH(1,($C25&$D25='TaxCred&Subs'!$D$66:$D$99)*($F25='TaxCred&Subs'!$C$66:$C$99),0)),0)),IF($C25>2,(O25-S25)*(IFERROR(INDEX('TaxCred&Subs'!$J$66:$J$99,MATCH(1,($C25&$D25='TaxCred&Subs'!$D$66:$D$99)*($F25='TaxCred&Subs'!$C$66:$C$99),0)),0)),0))),0)} -> 0 | R25: {=ROUND(IF(IFERROR(VALUE(RIGHT($AD25,1)),0)>2,IF($C25=8,N25*IFERROR(INDEX('TaxCred&Subs'!$K$139:$S$151,MATCH($C25&$D25&LEFT($AD25,7),'TaxCred&Subs'!$E$139:$E$151,0),MATCH($H25,'TaxCred&Subs'!$K$137:$S$137,0)),0),IF($C25=2,N25*IFERROR(INDEX('TaxCred&Subs'!$K$139:$S$151,MATCH($C25&$D25,'TaxCred&Subs'!$D$139:$D$151,0),MATCH($H25,'TaxCred&Subs'!$K$137:$S$137,0)),0),N25*IFERROR(INDEX('TaxCred&Subs'!$K$139:$S$151,MATCH($C25&$D25,'TaxCred&Subs'!$C$139:$C$151,0),MATCH($H25,'TaxCred&Subs'!$K$137:$S$137,0)),0))),0),0)} -> 0 | S25: {=ROUND(IF(IFERROR(VALUE(RIGHT($AD25,1)),0)>2,IF($C25=8,O25*IFERROR(INDEX('TaxCred&Subs'!$K$139:$S$151,MATCH($C25&$D25&LEFT($AD25,7),'TaxCred&Subs'!$E$139:$E$151,0),MATCH($H25,'TaxCred&Subs'!$K$137:$S$137,0)),0),IF($C25=2,O25*IFERROR(INDEX('TaxCred&Subs'!$K$139:$S$151,MATCH($C25&$D25,'TaxCred&Subs'!$D$139:$D$151,0),MATCH($H25,'TaxCred&Subs'!$K$137:$S$137,0)),0),O25*IFERROR(INDEX('TaxCred&Subs'!$K$139:$S$151,MATCH($C25&$D25,'TaxCred&Subs'!$C$139:$C$151,0),MATCH($H25,'TaxCred&Subs'!$K$137:$S$137,0)),0))),0),0)} -> 0 | T25: =IF($H25=9,IF(R25>0,(N25-P25)*0.15,0),0) -> 0 | U25: =IF($H25=9,IF(S25>0,(O25-Q25)*0.15,0),0) -> 0 | V25: MATURE | W25: 2020 | X25: 1 | Y25: 0 | Z25: -0.005353783 | AA25: -0.082365893 | AB25: 0 | AC25: 0 | AD25: ELEC_RAD2
B26: =B25+1 -> 2 | C26: 1 | D26: 2 | E26: 2 | F26: 2020 | G26: 2022 | H26: 11 | I26: 2 | J26: 0 | K26: 0 | L26: 0 | M26: 2.4032825 | N26: 3365 | O26: 3970 | P26: {=ROUND(IF($F26<='TaxCred&Subs'!$C$49,(IF($C26=2,IF($M26>=IFERROR(INDEX('TaxCred&Subs'!$L$12:$L$47,MATCH(1,($C26&$D26='TaxCred&Subs'!$E$12:$E$47)*($F26='TaxCred&Subs'!$C$12:$C$47),0) ),9999),IFERROR(INDEX('TaxCred&Subs'!$N$12:$N$47,MATCH(1,($C26&$D26='TaxCred&Subs'!$E$12:$E$47)*($F26='TaxCred&Subs'!$C$12:$C$47),0) ),0),0),(IF($M26>=IFERROR(INDEX('TaxCred&Subs'!$H$12:$H$47,MATCH(1,($C26&$D26='TaxCred&Subs'!$D$12:$D$47)*($F26='TaxCred&Subs'!$C$12:$C$47),0) ),9999),IFERROR(INDEX('TaxCred&Subs'!$N$12:$N$47,MATCH(1,($C26&$D26='TaxCred&Subs'!$D$12:$D$47)*($F26='TaxCred&Subs'!$C$12:$C$47),0) ),0),0)))),0)+IF(AND($C26=2,VALUE(RIGHT($AD26,1))>2),(N26-R26)*(IFERROR(INDEX('TaxCred&Subs'!$J$66:$J$99,MATCH(1,($C26&$D26='TaxCred&Subs'!$E$66:$E$99)*($F26='TaxCred&Subs'!$C$66:$C$99),0)),0)),IF(AND($C26=1,VALUE(RIGHT($AD26,1))>2),(N26-R26)*(IFERROR(INDEX('TaxCred&Subs'!$J$66:$J$99,MATCH(1,($C26&$D26='TaxCred&Subs'!$D$66:$D$99)*($F26='TaxCred&Subs'!$C$66:$C$99),0)),0)),IF($C26>2,(N26-R26)*(IFERROR(INDEX('TaxCred&Subs'!$J$66:$J$99,MATCH(1,($C26&$D26='TaxCred&Subs'!$D$66:$D$99)*($F26='TaxCred&Subs'!$C$66:$C$99),0)),0)),0))),0)} -> 0 | Q26: {=ROUND(IF(AND($C26=2,VALUE(RIGHT($AD26,1))>2),(O26-S26)*(IFERROR(INDEX('TaxCred&Subs'!$J$66:$J$99,MATCH(1,($C26&$D26='TaxCred&Subs'!$E$66:$E$99)*($F26='TaxCred&Subs'!$C$66:$C$99),0)),0)),IF(AND($C26=1,VALUE(RIGHT($AD26,1))>2),(O26-S26)*(IFERROR(INDEX('TaxCred&Subs'!$J$66:$J$99,MATCH(1,($C26&$D26='TaxCred&Subs'!$D$66:$D$99)*($F26='TaxCred&Subs'!$C$66:$C$99),0)),0)),IF($C26>2,(O26-S26)*(IFERROR(INDEX('TaxCred&Subs'!$J$66:$J$99,MATCH(1,($C26&$D26='TaxCred&Subs'!$D$66:$D$99)*($F26='TaxCred&Subs'!$C$66:$C$99),0)),0)),0))),0)} -> 0 | R26: {=ROUND(IF(IFERROR(VALUE(RIGHT($AD26,1)),0)>2,IF($C26=8,N26*IFERROR(INDEX('TaxCred&Subs'!$K$139:$S$151,MATCH($C26&$D26&LEFT($AD26,7),'TaxCred&Subs'!$E$139:$E$151,0),MATCH($H26,'TaxCred&Subs'!$K$137:$S$137,0)),0),IF($C26=2,N26*IFERROR(INDEX('TaxCred&Subs'!$K$139:$S$151,MATCH($C26&$D26,'TaxCred&Subs'!$D$139:$D$151,0),MATCH($H26,'TaxCred&Subs'!$K$137:$S$137,0)),0),N26*IFERROR(INDEX('TaxCred&Subs'!$K$139:$S$151,MATCH($C26&$D26,'TaxCred&Subs'!$C$139:$C$151,0),MATCH($H26,'TaxCred&Subs'!$K$137:$S$137,0)),0))),0),0)} -> 0 | S26: {=ROUND(IF(IFERROR(VALUE(RIGHT($AD26,1)),0)>2,IF($C26=8,O26*IFERROR(INDEX('TaxCred&Subs'!$K$139:$S$151,MATCH($C26&$D26&LEFT($AD26,7),'TaxCred&Subs'!$E$139:$E$151,0),MATCH($H26,'TaxCred&Subs'!$K$137:$S$137,0)),0),IF($C26=2,O26*IFERROR(INDEX('TaxCred&Subs'!$K$139:$S$151,MATCH($C26&$D26,'TaxCred&Subs'!$D$139:$D$151,0),MATCH($H26,'TaxCred&Subs'!$K$137:$S$137,0)),0),O26*IFERROR(INDEX('TaxCred&Subs'!$K$139:$S$151,MATCH($C26&$D26,'TaxCred&Subs'!$C$139:$C$151,0),MATCH($H26,'TaxCred&Subs'!$K$137:$S$137,0)),0))),0),0)} -> 0 | T26: =IF($H26=9,IF(R26>0,(N26-P26)*0.15,0),0) -> 0 | U26: =IF($H26=9,IF(S26>0,(O26-Q26)*0.15,0),0) -> 0 | V26: MATURE | W26: 2020 | X26: 1 | Y26: 0 | Z26: -0.00016872968 | AA26: -0.0025958412 | AB26: 0 | AC26: 0 | AD26: ELEC_HP1
B27: =B26+1 -> 3 | C27: 1 | D27: 2 | E27: 2 | F27: 2023 | G27: 2050 | H27: 11 | I27: 2 | J27: 0 | K27: 0 | L27: 0 | M27: 2.5791325 | N27: 3405 | O27: 4110 | P27: {=ROUND(IF($F27<='TaxCred&Subs'!$C$49,(IF($C27=2,IF($M27>=IFERROR(INDEX('TaxCred&Subs'!$L$12:$L$47,MATCH(1,($C27&$D27='TaxCred&Subs'!$E$12:$E$47)*($F27='TaxCred&Subs'!$C$12:$C$47),0) ),9999),IFERROR(INDEX('TaxCred&Subs'!$N$12:$N$47,MATCH(1,($C27&$D27='TaxCred&Subs'!$E$12:$E$47)*($F27='TaxCred&Subs'!$C$12:$C$47),0) ),0),0),(IF($M27>=IFERROR(INDEX('TaxCred&Subs'!$H$12:$H$47,MATCH(1,($C27&$D27='TaxCred&Subs'!$D$12:$D$47)*($F27='TaxCred&Subs'!$C$12:$C$47),0) ),9999),IFERROR(INDEX('TaxCred&Subs'!$N$12:$N$47,MATCH(1,($C27&$D27='TaxCred&Subs'!$D$12:$D$47)*($F27='TaxCred&Subs'!$C$12:$C$47),0) ),0),0)))),0)+IF(AND($C27=2,VALUE(RIGHT($AD27,1))>2),(N27-R27)*(IFERROR(INDEX('TaxCred&Subs'!$J$66:$J$99,MATCH(1,($C27&$D27='TaxCred&Subs'!$E$66:$E$99)*($F27='TaxCred&Subs'!$C$66:$C$99),0)),0)),IF(AND($C27=1,VALUE(RIGHT($AD27,1))>2),(N27-R27)*(IFERROR(INDEX('TaxCred&Subs'!$J$66:$J$99,MATCH(1,($C27&$D27='TaxCred&Subs'!$D$66:$D$99)*($F27='TaxCred&Subs'!$C$66:$C$99),0)),0)),IF($C27>2,(N27-R27)*(IFERROR(INDEX('TaxCred&Subs'!$J$66:$J$99,MATCH(1,($C27&$D27='TaxCred&Subs'!$D$66:$D$99)*($F27='TaxCred&Subs'!$C$66:$C$99),0)),0)),0))),0)} -> 0 | Q27: {=ROUND(IF(AND($C27=2,VALUE(RIGHT($AD27,1))>2),(O27-S27)*(IFERROR(INDEX('TaxCred&Subs'!$J$66:$J$99,MATCH(1,($C27&$D27='TaxCred&Subs'!$E$66:$E$99)*($F27='TaxCred&Subs'!$C$66:$C$99),0)),0)),IF(AND($C27=1,VALUE(RIGHT($AD27,1))>2),(O27-S27)*(IFERROR(INDEX('TaxCred&Subs'!$J$66:$J$99,MATCH(1,($C27&$D27='TaxCred&Subs'!$D$66:$D$99)*($F27='TaxCred&Subs'!$C$66:$C$99),0)),0)),IF($C27>2,(O27-S27)*(IFERROR(INDEX('TaxCred&Subs'!$J$66:$J$99,MATCH(1,($C27&$D27='TaxCred&Subs'!$D$66:$D$99)*($F27='TaxCred&Subs'!$C$66:$C$99),0)),0)),0))),0)} -> 0 | R27: {=ROUND(IF(IFERROR(VALUE(RIGHT($AD27,1)),0)>2,IF($C27=8,N27*IFERROR(INDEX('TaxCred&Subs'!$K$139:$S$151,MATCH($C27&$D27&LEFT($AD27,7),'TaxCred&Subs'!$E$139:$E$151,0),MATCH($H27,'TaxCred&Subs'!$K$137:$S$137,0)),0),IF($C27=2,N27*IFERROR(INDEX('TaxCred&Subs'!$K$139:$S$151,MATCH($C27&$D27,'TaxCred&Subs'!$D$139:$D$151,0),MATCH($H27,'TaxCred&Subs'!$K$137:$S$137,0)),0),N27*IFERROR(INDEX('TaxCred&Subs'!$K$139:$S$151,MATCH($C27&$D27,'TaxCred&Subs'!$C$139:$C$151,0),MATCH($H27,'TaxCred&Subs'!$K$137:$S$137,0)),0))),0),0)} -> 0 | S27: {=ROUND(IF(IFERROR(VALUE(RIGHT($AD27,1)),0)>2,IF($C27=8,O27*IFERROR(INDEX('TaxCred&Subs'!$K$139:$S$151,MATCH($C27&$D27&LEFT($AD27,7),'TaxCred&Subs'!$E$139:$E$151,0),MATCH($H27,'TaxCred&Subs'!$K$137:$S$137,0)),0),IF($C27=2,O27*IFERROR(INDEX('TaxCred&Subs'!$K$139:$S$151,MATCH($C27&$D27,'TaxCred&Subs'!$D$139:$D$151,0),MATCH($H27,'TaxCred&Subs'!$K$137:$S$137,0)),0),O27*IFERROR(INDEX('TaxCred&Subs'!$K$139:$S$151,MATCH($C27&$D27,'TaxCred&Subs'!$C$139:$C$151,0),MATCH($H27,'TaxCred&Subs'!$K$137:$S$137,0)),0))),0),0)} -> 0 | T27: =IF($H27=9,IF(R27>0,(N27-P27)*0.15,0),0) -> 0 | U27: =IF($H27=9,IF(S27>0,(O27-Q27)*0.15,0),0) -> 0 | V27: MATURE | W27: 2020 | X27: 1 | Y27: 0 | Z27: -0.00016872968 | AA27: -0.0025958412 | AB27: 0 | AC27: 0 | AD27: ELEC_HP1
B28: =B27+1 -> 4 | C28: 1 | D28: 2 | E28: 3 | F28: 2020 | G28: 2021 | H28: 11 | I28: 3 | J28: 0 | K28: 0 | L28: 0 | M28: 2.5205158 | N28: 2135 | O28: 4270 | P28: {=ROUND(IF($F28<='TaxCred&Subs'!$C$49,(IF($C28=2,IF($M28>=IFERROR(INDEX('TaxCred&Subs'!$L$12:$L$47,MATCH(1,($C28&$D28='TaxCred&Subs'!$E$12:$E$47)*($F28='TaxCred&Subs'!$C$12:$C$47),0) ),9999),IFERROR(INDEX('TaxCred&Subs'!$N$12:$N$47,MATCH(1,($C28&$D28='TaxCred&Subs'!$E$12:$E$47)*($F28='TaxCred&Subs'!$C$12:$C$47),0) ),0),0),(IF($M28>=IFERROR(INDEX('TaxCred&Subs'!$H$12:$H$47,MATCH(1,($C28&$D28='TaxCred&Subs'!$D$12:$D$47)*($F28='TaxCred&Subs'!$C$12:$C$47),0) ),9999),IFERROR(INDEX('TaxCred&Subs'!$N$12:$N$47,MATCH(1,($C28&$D28='TaxCred&Subs'!$D$12:$D$47)*($F28='TaxCred&Subs'!$C$12:$C$47),0) ),0),0)))),0)+IF(AND($C28=2,VALUE(RIGHT($AD28,1))>2),(N28-R28)*(IFERROR(INDEX('TaxCred&Subs'!$J$66:$J$99,MATCH(1,($C28&$D28='TaxCred&Subs'!$E$66:$E$99)*($F28='TaxCred&Subs'!$C$66:$C$99),0)),0)),IF(AND($C28=1,VALUE(RIGHT($AD28,1))>2),(N28-R28)*(IFERROR(INDEX('TaxCred&Subs'!$J$66:$J$99,MATCH(1,($C28&$D28='TaxCred&Subs'!$D$66:$D$99)*($F28='TaxCred&Subs'!$C$66:$C$99),0)),0)),IF($C28>2,(N28-R28)*(IFERROR(INDEX('TaxCred&Subs'!$J$66:$J$99,MATCH(1,($C28&$D28='TaxCred&Subs'!$D$66:$D$99)*($F28='TaxCred&Subs'!$C$66:$C$99),0)),0)),0))),0)} -> 150 | Q28: {=ROUND(IF(AND($C28=2,VALUE(RIGHT($AD28,1))>2),(O28-S28)*(IFERROR(INDEX('TaxCred&Subs'!$J$66:$J$99,MATCH(1,($C28&$D28='TaxCred&Subs'!$E$66:$E$99)*($F28='TaxCred&Subs'!$C$66:$C$99),0)),0)),IF(AND($C28=1,VALUE(RIGHT($AD28,1))>2),(O28-S28)*(IFERROR(INDEX('TaxCred&Subs'!$J$66:$J$99,MATCH(1,($C28&$D28='TaxCred&Subs'!$D$66:$D$99)*($F28='TaxCred&Subs'!$C$66:$C$99),0)),0)),IF($C28>2,(O28-S28)*(IFERROR(INDEX('TaxCred&Subs'!$J$66:$J$99,MATCH(1,($C28&$D28='TaxCred&Subs'!$D$66:$D$99)*($F28='TaxCred&Subs'!$C$66:$C$99),0)),0)),0))),0)} -> 0 | R28: {=ROUND(IF(IFERROR(VALUE(RIGHT($AD28,1)),0)>2,IF($C28=8,N28*IFERROR(INDEX('TaxCred&Subs'!$K$139:$S$151,MATCH($C28&$D28&LEFT($AD28,7),'TaxCred&Subs'!$E$139:$E$151,0),MATCH($H28,'TaxCred&Subs'!$K$137:$S$137,0)),0),IF($C28=2,N28*IFERROR(INDEX('TaxCred&Subs'!$K$139:$S$151,MATCH($C28&$D28,'TaxCred&Subs'!$D$139:$D$151,0),MATCH($H28,'TaxCred&Subs'!$K$137:$S$137,0)),0),N28*IFERROR(INDEX('TaxCred&Subs'!$K$139:$S$151,MATCH($C28&$D28,'TaxCred&Subs'!$C$139:$C$151,0),MATCH($H28,'TaxCred&Subs'!$K$137:$S$137,0)),0))),0),0)} -> 0 | S28: {=ROUND(IF(IFERROR(VALUE(RIGHT($AD28,1)),0)>2,IF($C28=8,O28*IFERROR(INDEX('TaxCred&Subs'!$K$139:$S$151,MATCH($C28&$D28&LEFT($AD28,7),'TaxCred&Subs'!$E$139:$E$151,0),MATCH($H28,'TaxCred&Subs'!$K$137:$S$137,0)),0),IF($C28=2,O28*IFERROR(INDEX('TaxCred&Subs'!$K$139:$S$151,MATCH($C28&$D28,'TaxCred&Subs'!$D$139:$D$151,0),MATCH($H28,'TaxCred&Subs'!$K$137:$S$137,0)),0),O28*IFERROR(INDEX('TaxCred&Subs'!$K$139:$S$151,MATCH($C28&$D28,'TaxCred&Subs'!$C$139:$C$151,0),MATCH($H28,'TaxCred&Subs'!$K$137:$S$137,0)),0))),0),0)} -> 0 | T28: =IF($H28=9,IF(R28>0,(N28-P28)*0.15,0),0) -> 0 | U28: =IF($H28=9,IF(S28>0,(O28-Q28)*0.15,0),0) -> 0 | V28: MATURE | W28: 2020 | X28: 1 | Y28: 0 | Z28: -0.00016872968 | AA28: -0.0025958412 | AB28: 0 | AC28: 0 | AD28: ELEC_HP2
B29: =B28+1 -> 5 | C29: 1 | D29: 2 | E29: 3 | F29: 2022 | G29: 2022 | H29: 11 | I29: 3 | J29: 0 | K29: 0 | L29: 0 | M29: 2.5205158 | N29: 2135 | O29: 4270 | P29: {=ROUND(IF($F29<='TaxCred&Subs'!$C$49,(IF($C29=2,IF($M29>=IFERROR(INDEX('TaxCred&Subs'!$L$12:$L$47,MATCH(1,($C29&$D29='TaxCred&Subs'!$E$12:$E$47)*($F29='TaxCred&Subs'!$C$12:$C$47),0) ),9999),IFERROR(INDEX('TaxCred&Subs'!$N$12:$N$47,MATCH(1,($C29&$D29='TaxCred&Subs'!$E$12:$E$47)*($F29='TaxCred&Subs'!$C$12:$C$47),0) ),0),0),(IF($M29>=IFERROR(INDEX('TaxCred&Subs'!$H$12:$H$47,MATCH(1,($C29&$D29='TaxCred&Subs'!$D$12:$D$47)*($F29='TaxCred&Subs'!$C$12:$C$47),0) ),9999),IFERROR(INDEX('TaxCred&Subs'!$N$12:$N$47,MATCH(1,($C29&$D29='TaxCred&Subs'!$D$12:$D$47)*($F29='TaxCred&Subs'!$C$12:$C$47),0) ),0),0)))),0)+IF(AND($C29=2,VALUE(RIGHT($AD29,1))>2),(N29-R29)*(IFERROR(INDEX('TaxCred&Subs'!$J$66:$J$99,MATCH(1,($C29&$D29='TaxCred&Subs'!$E$66:$E$99)*($F29='TaxCred&Subs'!$C$66:$C$99),0)),0)),IF(AND($C29=1,VALUE(RIGHT($AD29,1))>2),(N29-R29)*(IFERROR(INDEX('TaxCred&Subs'!$J$66:$J$99,MATCH(1,($C29&$D29='TaxCred&Subs'!$D$66:$D$99)*($F29='TaxCred&Subs'!$C$66:$C$99),0)),0)),IF($C29>2,(N29-R29)*(IFERROR(INDEX('TaxCred&Subs'!$J$66:$J$99,MATCH(1,($C29&$D29='TaxCred&Subs'!$D$66:$D$99)*($F29='TaxCred&Subs'!$C$66:$C$99),0)),0)),0))),0)} -> 1000 | Q29: {=ROUND(IF(AND($C29=2,VALUE(RIGHT($AD29,1))>2),(O29-S29)*(IFERROR(INDEX('TaxCred&Subs'!$J$66:$J$99,MATCH(1,($C29&$D29='TaxCred&Subs'!$E$66:$E$99)*($F29='TaxCred&Subs'!$C$66:$C$99),0)),0)),IF(AND($C29=1,VALUE(RIGHT($AD29,1))>2),(O29-S29)*(IFERROR(INDEX('TaxCred&Subs'!$J$66:$J$99,MATCH(1,($C29&$D29='TaxCred&Subs'!$D$66:$D$99)*($F29='TaxCred&Subs'!$C$66:$C$99),0)),0)),IF($C29>2,(O29-S29)*(IFERROR(INDEX('TaxCred&Subs'!$J$66:$J$99,MATCH(1,($C29&$D29='TaxCred&Subs'!$D$66:$D$99)*($F29='TaxCred&Subs'!$C$66:$C$99),0)),0)),0))),0)} -> 0 | R29: {=ROUND(IF(IFERROR(VALUE(RIGHT($AD29,1)),0)>2,IF($C29=8,N29*IFERROR(INDEX('TaxCred&Subs'!$K$139:$S$151,MATCH($C29&$D29&LEFT($AD29,7),'TaxCred&Subs'!$E$139:$E$151,0),MATCH($H29,'TaxCred&Subs'!$K$137:$S$137,0)),0),IF($C29=2,N29*IFERROR(INDEX('TaxCred&Subs'!$K$139:$S$151,MATCH($C29&$D29,'TaxCred&Subs'!$D$139:$D$151,0),MATCH($H29,'TaxCred&Subs'!$K$137:$S$137,0)),0),N29*IFERROR(INDEX('TaxCred&Subs'!$K$139:$S$151,MATCH($C29&$D29,'TaxCred&Subs'!$C$139:$C$151,0),MATCH($H29,'TaxCred&Subs'!$K$137:$S$137,0)),0))),0),0)} -> 0 | S29: {=ROUND(IF(IFERROR(VALUE(RIGHT($AD29,1)),0)>2,IF($C29=8,O29*IFERROR(INDEX('TaxCred&Subs'!$K$139:$S$151,MATCH($C29&$D29&LEFT($AD29,7),'TaxCred&Subs'!$E$139:$E$151,0),MATCH($H29,'TaxCred&Subs'!$K$137:$S$137,0)),0),IF($C29=2,O29*IFERROR(INDEX('TaxCred&Subs'!$K$139:$S$151,MATCH($C29&$D29,'TaxCred&Subs'!$D$139:$D$151,0),MATCH($H29,'TaxCred&Subs'!$K$137:$S$137,0)),0),O29*IFERROR(INDEX('TaxCred&Subs'!$K$139:$S$151,MATCH($C29&$D29,'TaxCred&Subs'!$C$139:$C$151,0),MATCH($H29,'TaxCred&Subs'!$K$137:$S$137,0)),0))),0),0)} -> 0 | T29: =IF($H29=9,IF(R29>0,(N29-P29)*0.15,0),0) -> 0 | U29: =IF($H29=9,IF(S29>0,(O29-Q29)*0.15,0),0) -> 0 | V29: MATURE | W29: 2020 | X29: 1 | Y29: 0 | Z29: -0.00016872968 | AA29: -0.0025958412 | AB29: 0 | AC29: 0 | AD29: ELEC_HP2
B30: =B29+1 -> 6 | C30: 1 | D30: 2 | E30: 3 | F30: 2023 | G30: 2032 | H30: 11 | I30: 3 | J30: 0 | K30: 0 | L30: 0 | M30: 2.6963658 | N30: 3470 | O30: 4380 | P30: {=ROUND(IF($F30<='TaxCred&Subs'!$C$49,(IF($C30=2,IF($M30>=IFERROR(INDEX('TaxCred&Subs'!$L$12:$L$47,MATCH(1,($C30&$D30='TaxCred&Subs'!$E$12:$E$47)*($F30='TaxCred&Subs'!$C$12:$C$47),0) ),9999),IFERROR(INDEX('TaxCred&Subs'!$N$12:$N$47,MATCH(1,($C30&$D30='TaxCred&Subs'!$E$12:$E$47)*($F30='TaxCred&Subs'!$C$12:$C$47),0) ),0),0),(IF($M30>=IFERROR(INDEX('TaxCred&Subs'!$H$12:$H$47,MATCH(1,($C30&$D30='TaxCred&Subs'!$D$12:$D$47)*($F30='TaxCred&Subs'!$C$12:$C$47),0) ),9999),IFERROR(INDEX('TaxCred&Subs'!$N$12:$N$47,MATCH(1,($C30&$D30='TaxCred&Subs'!$D$12:$D$47)*($F30='TaxCred&Subs'!$C$12:$C$47),0) ),0),0)))),0)+IF(AND($C30=2,VALUE(RIGHT($AD30,1))>2),(N30-R30)*(IFERROR(INDEX('TaxCred&Subs'!$J$66:$J$99,MATCH(1,($C30&$D30='TaxCred&Subs'!$E$66:$E$99)*($F30='TaxCred&Subs'!$C$66:$C$99),0)),0)),IF(AND($C30=1,VALUE(RIGHT($AD30,1))>2),(N30-R30)*(IFERROR(INDEX('TaxCred&Subs'!$J$66:$J$99,MATCH(1,($C30&$D30='TaxCred&Subs'!$D$66:$D$99)*($F30='TaxCred&Subs'!$C$66:$C$99),0)),0)),IF($C30>2,(N30-R30)*(IFERROR(INDEX('TaxCred&Subs'!$J$66:$J$99,MATCH(1,($C30&$D30='TaxCred&Subs'!$D$66:$D$99)*($F30='TaxCred&Subs'!$C$66:$C$99),0)),0)),0))),0)} -> 1000 | Q30: {=ROUND(IF(AND($C30=2,VALUE(RIGHT($AD30,1))>2),(O30-S30)*(IFERROR(INDEX('TaxCred&Subs'!$J$66:$J$99,MATCH(1,($C30&$D30='TaxCred&Subs'!$E$66:$E$99)*($F30='TaxCred&Subs'!$C$66:$C$99),0)),0)),IF(AND($C30=1,VALUE(RIGHT($AD30,1))>2),(O30-S30)*(IFERROR(INDEX('TaxCred&Subs'!$J$66:$J$99,MATCH(1,($C30&$D30='TaxCred&Subs'!$D$66:$D$99)*($F30='TaxCred&Subs'!$C$66:$C$99),0)),0)),IF($C30>2,(O30-S30)*(IFERROR(INDEX('TaxCred&Subs'!$J$66:$J$99,MATCH(1,($C30&$D30='TaxCred&Subs'!$D$66:$D$99)*($F30='TaxCred&Subs'!$C$66:$C$99),0)),0)),0))),0)} -> 0 | R30: {=ROUND(IF(IFERROR(VALUE(RIGHT($AD30,1)),0)>2,IF($C30=8,N30*IFERROR(INDEX('TaxCred&Subs'!$K$139:$S$151,MATCH($C30&$D30&LEFT($AD30,7),'TaxCred&Subs'!$E$139:$E$151,0),MATCH($H30,'TaxCred&Subs'!$K$137:$S$137,0)),0),IF($C30=2,N30*IFERROR(INDEX('TaxCred&Subs'!$K$139:$S$151,MATCH($C30&$D30,'TaxCred&Subs'!$D$139:$D$151,0),MATCH($H30,'TaxCred&Subs'!$K$137:$S$137,0)),0),N30*IFERROR(INDEX('TaxCred&Subs'!$K$139:$S$151,MATCH($C30&$D30,'TaxCred&Subs'!$C$139:$C$151,0),MATCH($H30,'TaxCred&Subs'!$K$137:$S$137,0)),0))),0),0)} -> 0 | S30: {=ROUND(IF(IFERROR(VALUE(RIGHT($AD30,1)),0)>2,IF($C30=8,O30*IFERROR(INDEX('TaxCred&Subs'!$K$139:$S$151,MATCH($C30&$D30&LEFT($AD30,7),'TaxCred&Subs'!$E$139:$E$151,0),MATCH($H30,'TaxCred&Subs'!$K$137:$S$137,0)),0),IF($C30=2,O30*IFERROR(INDEX('TaxCred&Subs'!$K$139:$S$151,MATCH($C30&$D30,'TaxCred&Subs'!$D$139:$D$151,0),MATCH($H30,'TaxCred&Subs'!$K$137:$S$137,0)),0),O30*IFERROR(INDEX('TaxCred&Subs'!$K$139:$S$151,MATCH($C30&$D30,'TaxCred&Subs'!$C$139:$C$151,0),MATCH($H30,'TaxCred&Subs'!$K$137:$S$137,0)),0))),0),0)} -> 0 | T30: =IF($H30=9,IF(R30>0,(N30-P30)*0.15,0),0) -> 0 | U30: =IF($H30=9,IF(S30>0,(O30-Q30)*0.15,0),0) -> 0 | V30: MATURE | W30: 2020 | X30: 1 | Y30: 0 | Z30: -0.00016872968 | AA30: -0.0025958412 | AB30: 0 | AC30: 0 | AD30: ELEC_HP2
B31: =B30+1 -> 7 | C31: 1 | D31: 2 | E31: 3 | F31: 2033 | G31: 2039 | H31: 11 | I31: 3 | J31: 0 | K31: 0 | L31: 0 | M31: 2.6963658 | N31: 3470 | O31: 4380 | P31: {=ROUND(IF($F31<='TaxCred&Subs'!$C$49,(IF($C31=2,IF($M31>=IFERROR(INDEX('TaxCred&Subs'!$L$12:$L$47,MATCH(1,($C31&$D31='TaxCred&Subs'!$E$12:$E$47)*($F31='TaxCred&Subs'!$C$12:$C$47),0) ),9999),IFERROR(INDEX('TaxCred&Subs'!$N$12:$N$47,MATCH(1,($C31&$D31='TaxCred&Subs'!$E$12:$E$47)*($F31='TaxCred&Subs'!$C$12:$C$47),0) ),0),0),(IF($M31>=IFERROR(INDEX('TaxCred&Subs'!$H$12:$H$47,MATCH(1,($C31&$D31='TaxCred&Subs'!$D$12:$D$47)*($F31='TaxCred&Subs'!$C$12:$C$47),0) ),9999),IFERROR(INDEX('TaxCred&Subs'!$N$12:$N$47,MATCH(1,($C31&$D31='TaxCred&Subs'!$D$12:$D$47)*($F31='TaxCred&Subs'!$C$12:$C$47),0) ),0),0)))),0)+IF(AND($C31=2,VALUE(RIGHT($AD31,1))>2),(N31-R31)*(IFERROR(INDEX('TaxCred&Subs'!$J$66:$J$99,MATCH(1,($C31&$D31='TaxCred&Subs'!$E$66:$E$99)*($F31='TaxCred&Subs'!$C$66:$C$99),0)),0)),IF(AND($C31=1,VALUE(RIGHT($AD31,1))>2),(N31-R31)*(IFERROR(INDEX('TaxCred&Subs'!$J$66:$J$99,MATCH(1,($C31&$D31='TaxCred&Subs'!$D$66:$D$99)*($F31='TaxCred&Subs'!$C$66:$C$99),0)),0)),IF($C31>2,(N31-R31)*(IFERROR(INDEX('TaxCred&Subs'!$J$66:$J$99,MATCH(1,($C31&$D31='TaxCred&Subs'!$D$66:$D$99)*($F31='TaxCred&Subs'!$C$66:$C$99),0)),0)),0))),0)} -> 0 | Q31: {=ROUND(IF(AND($C31=2,VALUE(RIGHT($AD31,1))>2),(O31-S31)*(IFERROR(INDEX('TaxCred&Subs'!$J$66:$J$99,MATCH(1,($C31&$D31='TaxCred&Subs'!$E$66:$E$99)*($F31='TaxCred&Subs'!$C$66:$C$99),0)),0)),IF(AND($C31=1,VALUE(RIGHT($AD31,1))>2),(O31-S31)*(IFERROR(INDEX('TaxCred&Subs'!$J$66:$J$99,MATCH(1,($C31&$D31='TaxCred&Subs'!$D$66:$D$99)*($F31='TaxCred&Subs'!$C$66:$C$99),0)),0)),IF($C31>2,(O31-S31)*(IFERROR(INDEX('TaxCred&Subs'!$J$66:$J$99,MATCH(1,($C31&$D31='TaxCred&Subs'!$D$66:$D$99)*($F31='TaxCred&Subs'!$C$66:$C$99),0)),0)),0))),0)} -> 0 | R31: {=ROUND(IF(IFERROR(VALUE(RIGHT($AD31,1)),0)>2,IF($C31=8,N31*IFERROR(INDEX('TaxCred&Subs'!$K$139:$S$151,MATCH($C31&$D31&LEFT($AD31,7),'TaxCred&Subs'!$E$139:$E$151,0),MATCH($H31,'TaxCred&Subs'!$K$137:$S$137,0)),0),IF($C31=2,N31*IFERROR(INDEX('TaxCred&Subs'!$K$139:$S$151,MATCH($C31&$D31,'TaxCred&Subs'!$D$139:$D$151,0),MATCH($H31,'TaxCred&Subs'!$K$137:$S$137,0)),0),N31*IFERROR(INDEX('TaxCred&Subs'!$K$139:$S$151,MATCH($C31&$D31,'TaxCred&Subs'!$C$139:$C$151,0),MATCH($H31,'TaxCred&Subs'!$K$137:$S$137,0)),0))),0),0)} -> 0 | S31: {=ROUND(IF(IFERROR(VALUE(RIGHT($AD31,1)),0)>2,IF($C31=8,O31*IFERROR(INDEX('TaxCred&Subs'!$K$139:$S$151,MATCH($C31&$D31&LEFT($AD31,7),'TaxCred&Subs'!$E$139:$E$151,0),MATCH($H31,'TaxCred&Subs'!$K$137:$S$137,0)),0),IF($C31=2,O31*IFERROR(INDEX('TaxCred&Subs'!$K$139:$S$151,MATCH($C31&$D31,'TaxCred&Subs'!$D$139:$D$151,0),MATCH($H31,'TaxCred&Subs'!$K$137:$S$137,0)),0),O31*IFERROR(INDEX('TaxCred&Subs'!$K$139:$S$151,MATCH($C31&$D31,'TaxCred&Subs'!$C$139:$C$151,0),MATCH($H31,'TaxCred&Subs'!$K$137:$S$137,0)),0))),0),0)} -> 0 | T31: =IF($H31=9,IF(R31>0,(N31-P31)*0.15,0),0) -> 0 | U31: =IF($H31=9,IF(S31>0,(O31-Q31)*0.15,0),0) -> 0 | V31: MATURE | W31: 2020 | X31: 1 | Y31: 0 | Z31: -0.00016872968 | AA31: -0.0025958412 | AB31: 0 | AC31: 0 | AD31: ELEC_HP2
B32: =B31+1 -> 8 | C32: 1 | D32: 2 | E32: 3 | F32: 2040 | G32: 2050 | H32: 11 | I32: 3 | J32: 0 | K32: 0 | L32: 0 | M32: 2.7256741 | N32: 3620 | O32: 5000 | P32: {=ROUND(IF($F32<='TaxCred&Subs'!$C$49,(IF($C32=2,IF($M32>=IFERROR(INDEX('TaxCred&Subs'!$L$12:$L$47,MATCH(1,($C32&$D32='TaxCred&Subs'!$E$12:$E$47)*($F32='TaxCred&Subs'!$C$12:$C$47),0) ),9999),IFERROR(INDEX('TaxCred&Subs'!$N$12:$N$47,MATCH(1,($C32&$D32='TaxCred&Subs'!$E$12:$E$47)*($F32='TaxCred&Subs'!$C$12:$C$47),0) ),0),0),(IF($M32>=IFERROR(INDEX('TaxCred&Subs'!$H$12:$H$47,MATCH(1,($C32&$D32='TaxCred&Subs'!$D$12:$D$47)*($F32='TaxCred&Subs'!$C$12:$C$47),0) ),9999),IFERROR(INDEX('TaxCred&Subs'!$N$12:$N$47,MATCH(1,($C32&$D32='TaxCred&Subs'!$D$12:$D$47)*($F32='TaxCred&Subs'!$C$12:$C$47),0) ),0),0)))),0)+IF(AND($C32=2,VALUE(RIGHT($AD32,1))>2),(N32-R32)*(IFERROR(INDEX('TaxCred&Subs'!$J$66:$J$99,MATCH(1,($C32&$D32='TaxCred&Subs'!$E$66:$E$99)*($F32='TaxCred&Subs'!$C$66:$C$99),0)),0)),IF(AND($C32=1,VALUE(RIGHT($AD32,1))>2),(N32-R32)*(IFERROR(INDEX('TaxCred&Subs'!$J$66:$J$99,MATCH(1,($C32&$D32='TaxCred&Subs'!$D$66:$D$99)*($F32='TaxCred&Subs'!$C$66:$C$99),0)),0)),IF($C32>2,(N32-R32)*(IFERROR(INDEX('TaxCred&Subs'!$J$66:$J$99,MATCH(1,($C32&$D32='TaxCred&Subs'!$D$66:$D$99)*($F32='TaxCred&Subs'!$C$66:$C$99),0)),0)),0))),0)} -> 0 | Q32: {=ROUND(IF(AND($C32=2,VALUE(RIGHT($AD32,1))>2),(O32-S32)*(IFERROR(INDEX('TaxCred&Subs'!$J$66:$J$99,MATCH(1,($C32&$D32='TaxCred&Subs'!$E$66:$E$99)*($F32='TaxCred&Subs'!$C$66:$C$99),0)),0)),IF(AND($C32=1,VALUE(RIGHT($AD32,1))>2),(O32-S32)*(IFERROR(INDEX('TaxCred&Subs'!$J$66:$J$99,MATCH(1,($C32&$D32='TaxCred&Subs'!$D$66:$D$99)*($F32='TaxCred&Subs'!$C$66:$C$99),0)),0)),IF($C32>2,(O32-S32)*(IFERROR(INDEX('TaxCred&Subs'!$J$66:$J$99,MATCH(1,($C32&$D32='TaxCred&Subs'!$D$66:$D$99)*($F32='TaxCred&Subs'!$C$66:$C$99),0)),0)),0))),0)} -> 0 | R32: {=ROUND(IF(IFERROR(VALUE(RIGHT($AD32,1)),0)>2,IF($C32=8,N32*IFERROR(INDEX('TaxCred&Subs'!$K$139:$S$151,MATCH($C32&$D32&LEFT($AD32,7),'TaxCred&Subs'!$E$139:$E$151,0),MATCH($H32,'TaxCred&Subs'!$K$137:$S$137,0)),0),IF($C32=2,N32*IFERROR(INDEX('TaxCred&Subs'!$K$139:$S$151,MATCH($C32&$D32,'TaxCred&Subs'!$D$139:$D$151,0),MATCH($H32,'TaxCred&Subs'!$K$137:$S$137,0)),0),N32*IFERROR(INDEX('TaxCred&Subs'!$K$139:$S$151,MATCH($C32&$D32,'TaxCred&Subs'!$C$139:$C$151,0),MATCH($H32,'TaxCred&Subs'!$K$137:$S$137,0)),0))),0),0)} -> 0 | S32: {=ROUND(IF(IFERROR(VALUE(RIGHT($AD32,1)),0)>2,IF($C32=8,O32*IFERROR(INDEX('TaxCred&Subs'!$K$139:$S$151,MATCH($C32&$D32&LEFT($AD32,7),'TaxCred&Subs'!$E$139:$E$151,0),MATCH($H32,'TaxCred&Subs'!$K$137:$S$137,0)),0),IF($C32=2,O32*IFERROR(INDEX('TaxCred&Subs'!$K$139:$S$151,MATCH($C32&$D32,'TaxCred&Subs'!$D$139:$D$151,0),MATCH($H32,'TaxCred&Subs'!$K$137:$S$137,0)),0),O32*IFERROR(INDEX('TaxCred&Subs'!$K$139:$S$151,MATCH($C32&$D32,'TaxCred&Subs'!$C$139:$C$151,0),MATCH($H32,'TaxCred&Subs'!$K$137:$S$137,0)),0))),0),0)} -> 0 | T32: =IF($H32=9,IF(R32>0,(N32-P32)*0.15,0),0) -> 0 | U32: =IF($H32=9,IF(S32>0,(O32-Q32)*0.15,0),0) -> 0 | V32: MATURE | W32: 2020 | X32: 1 | Y32: 0 | Z32: -0.00016872968 | AA32: -0.0025958412 | AB32: 0 | AC32: 0 | AD32: ELEC_HP2
B33: =B32+1 -> 9 | C33: 1 | D33: 2 | E33: 4 | F33: 2020 | G33: 2021 | H33: 1 | I33: 4 | J33: 0 | K33: 0 | L33: 0 | M33: 2.4912075 | N33: 3405 | O33: 4110 | P33: {=ROUND(IF($F33<='TaxCred&Subs'!$C$49,(IF($C33=2,IF($M33>=IFERROR(INDEX('TaxCred&Subs'!$L$12:$L$47,MATCH(1,($C33&$D33='TaxCred&Subs'!$E$12:$E$47)*($F33='TaxCred&Subs'!$C$12:$C$47),0) ),9999),IFERROR(INDEX('TaxCred&Subs'!$N$12:$N$47,MATCH(1,($C33&$D33='TaxCred&Subs'!$E$12:$E$47)*($F33='TaxCred&Subs'!$C$12:$C$47),0) ),0),0),(IF($M33>=IFERROR(INDEX('TaxCred&Subs'!$H$12:$H$47,MATCH(1,($C33&$D33='TaxCred&Subs'!$D$12:$D$47)*($F33='TaxCred&Subs'!$C$12:$C$47),0) ),9999),IFERROR(INDEX('TaxCred&Subs'!$N$12:$N$47,MATCH(1,($C33&$D33='TaxCred&Subs'!$D$12:$D$47)*($F33='TaxCred&Subs'!$C$12:$C$47),0) ),0),0)))),0)+IF(AND($C33=2,VALUE(RIGHT($AD33,1))>2),(N33-R33)*(IFERROR(INDEX('TaxCred&Subs'!$J$66:$J$99,MATCH(1,($C33&$D33='TaxCred&Subs'!$E$66:$E$99)*($F33='TaxCred&Subs'!$C$66:$C$99),0)),0)),IF(AND($C33=1,VALUE(RIGHT($AD33,1))>2),(N33-R33)*(IFERROR(INDEX('TaxCred&Subs'!$J$66:$J$99,MATCH(1,($C33&$D33='TaxCred&Subs'!$D$66:$D$99)*($F33='TaxCred&Subs'!$C$66:$C$99),0)),0)),IF($C33>2,(N33-R33)*(IFERROR(INDEX('TaxCred&Subs'!$J$66:$J$99,MATCH(1,($C33&$D33='TaxCred&Subs'!$D$66:$D$99)*($F33='TaxCred&Subs'!$C$66:$C$99),0)),0)),0))),0)} -> 150 | Q33: {=ROUND(IF(AND($C33=2,VALUE(RIGHT($AD33,1))>2),(O33-S33)*(IFERROR(INDEX('TaxCred&Subs'!$J$66:$J$99,MATCH(1,($C33&$D33='TaxCred&Subs'!$E$66:$E$99)*($F33='TaxCred&Subs'!$C$66:$C$99),0)),0)),IF(AND($C33=1,VALUE(RIGHT($AD33,1))>2),(O33-S33)*(IFERROR(INDEX('TaxCred&Subs'!$J$66:$J$99,MATCH(1,($C33&$D33='TaxCred&Subs'!$D$66:$D$99)*($F33='TaxCred&Subs'!$C$66:$C$99),0)),0)),IF($C33>2,(O33-S33)*(IFERROR(INDEX('TaxCred&Subs'!$J$66:$J$99,MATCH(1,($C33&$D33='TaxCred&Subs'!$D$66:$D$99)*($F33='TaxCred&Subs'!$C$66:$C$99),0)),0)),0))),0)} -> 0 | R33: {=ROUND(IF(IFERROR(VALUE(RIGHT($AD33,1)),0)>2,IF($C33=8,N33*IFERROR(INDEX('TaxCred&Subs'!$K$139:$S$151,MATCH($C33&$D33&LEFT($AD33,7),'TaxCred&Subs'!$E$139:$E$151,0),MATCH($H33,'TaxCred&Subs'!$K$137:$S$137,0)),0),IF($C33=2,N33*IFERROR(INDEX('TaxCred&Subs'!$K$139:$S$151,MATCH($C33&$D33,'TaxCred&Subs'!$D$139:$D$151,0),MATCH($H33,'TaxCred&Subs'!$K$137:$S$137,0)),0),N33*IFERROR(INDEX('TaxCred&Subs'!$K$139:$S$151,MATCH($C33&$D33,'TaxCred&Subs'!$C$139:$C$151,0),MATCH($H33,'TaxCred&Subs'!$K$137:$S$137,0)),0))),0),0)} -> 492 | S33: {=ROUND(IF(IFERROR(VALUE(RIGHT($AD33,1)),0)>2,IF($C33=8,O33*IFERROR(INDEX('TaxCred&Subs'!$K$139:$S$151,MATCH($C33&$D33&LEFT($AD33,7),'TaxCred&Subs'!$E$139:$E$151,0),MATCH($H33,'TaxCred&Subs'!$K$137:$S$137,0)),0),IF($C33=2,O33*IFERROR(INDEX('TaxCred&Subs'!$K$139:$S$151,MATCH($C33&$D33,'TaxCred&Subs'!$D$139:$D$151,0),MATCH($H33,'TaxCred&Subs'!$K$137:$S$137,0)),0),O33*IFERROR(INDEX('TaxCred&Subs'!$K$139:$S$151,MATCH($C33&$D33,'TaxCred&Subs'!$C$139:$C$151,0),MATCH($H33,'TaxCred&Subs'!$K$137:$S$137,0)),0))),0),0)} -> 593 | T33: =IF($H33=9,IF(R33>0,(N33-P33)*0.15,0),0) -> 0 | U33: =IF($H33=9,IF(S33>0,(O33-Q33)*0.15,0),0) -> 0 | V33: MATURE | W33: 2020 | X33: 1 | Y33: 0 | Z33: -0.00020762473 | AA33: -0.0031942266 | AB33: 0 | AC33: 0 | AD33: ELEC_HP3
B34: =B33+1 -> 10 | C34: 1 | D34: 2 | E34: 4 | F34: 2020 | G34: 2021 | H34: 2 | I34: 4 | J34: 0 | K34: 0 | L34: 0 | M34: 2.4912075 | N34: 3405 | O34: 4110 | P34: {=ROUND(IF($F34<='TaxCred&Subs'!$C$49,(IF($C34=2,IF($M34>=IFERROR(INDEX('TaxCred&Subs'!$L$12:$L$47,MATCH(1,($C34&$D34='TaxCred&Subs'!$E$12:$E$47)*($F34='TaxCred&Subs'!$C$12:$C$47),0) ),9999),IFERROR(INDEX('TaxCred&Subs'!$N$12:$N$47,MATCH(1,($C34&$D34='TaxCred&Subs'!$E$12:$E$47)*($F34='TaxCred&Subs'!$C$12:$C$47),0) ),0),0),(IF($M34>=IFERROR(INDEX('TaxCred&Subs'!$H$12:$H$47,MATCH(1,($C34&$D34='TaxCred&Subs'!$D$12:$D$47)*($F34='TaxCred&Subs'!$C$12:$C$47),0) ),9999),IFERROR(INDEX('TaxCred&Subs'!$N$12:$N$47,MATCH(1,($C34&$D34='TaxCred&Subs'!$D$12:$D$47)*($F34='TaxCred&Subs'!$C$12:$C$47),0) ),0),0)))),0)+IF(AND($C34=2,VALUE(RIGHT($AD34,1))>2),(N34-R34)*(IFERROR(INDEX('TaxCred&Subs'!$J$66:$J$99,MATCH(1,($C34&$D34='TaxCred&Subs'!$E$66:$E$99)*($F34='TaxCred&Subs'!$C$66:$C$99),0)),0)),IF(AND($C34=1,VALUE(RIGHT($AD34,1))>2),(N34-R34)*(IFERROR(INDEX('TaxCred&Subs'!$J$66:$J$99,MATCH(1,($C34&$D34='TaxCred&Subs'!$D$66:$D$99)*($F34='TaxCred&Subs'!$C$66:$C$99),0)),0)),IF($C34>2,(N34-R34)*(IFERROR(INDEX('TaxCred&Subs'!$J$66:$J$99,MATCH(1,($C34&$D34='TaxCred&Subs'!$D$66:$D$99)*($F34='TaxCred&Subs'!$C$66:$C$99),0)),0)),0))),0)} -> 150 | Q34: {=ROUND(IF(AND($C34=2,VALUE(RIGHT($AD34,1))>2),(O34-S34)*(IFERROR(INDEX('TaxCred&Subs'!$J$66:$J$99,MATCH(1,($C34&$D34='TaxCred&Subs'!$E$66:$E$99)*($F34='TaxCred&Subs'!$C$66:$C$99),0)),0)),IF(AND($C34=1,VALUE(RIGHT($AD34,1))>2),(O34-S34)*(IFERROR(INDEX('TaxCred&Subs'!$J$66:$J$99,MATCH(1,($C34&$D34='TaxCred&Subs'!$D$66:$D$99)*($F34='TaxCred&Subs'!$C$66:$C$99),0)),0)),IF($C34>2,(O34-S34)*(IFERROR(INDEX('TaxCred&Subs'!$J$66:$J$99,MATCH(1,($C34&$D34='TaxCred&Subs'!$D$66:$D$99)*($F34='TaxCred&Subs'!$C$66:$C$99),0)),0)),0))),0)} -> 0 | R34: {=ROUND(IF(IFERROR(VALUE(RIGHT($AD34,1)),0)>2,IF($C34=8,N34*IFERROR(INDEX('TaxCred&Subs'!$K$139:$S$151,MATCH($C34&$D34&LEFT($AD34,7),'TaxCred&Subs'!$E$139:$E$151,0),MATCH($H34,'TaxCred&Subs'!$K$137:$S$137,0)),0),IF($C34=2,N34*IFERROR(INDEX('TaxCred&Subs'!$K$139:$S$151,MATCH($C34&$D34,'TaxCred&Subs'!$D$139:$D$151,0),MATCH($H34,'TaxCred&Subs'!$K$137:$S$137,0)),0),N34*IFERROR(INDEX('TaxCred&Subs'!$K$139:$S$151,MATCH($C34&$D34,'TaxCred&Subs'!$C$139:$C$151,0),MATCH($H34,'TaxCred&Subs'!$K$137:$S$137,0)),0))),0),0)} -> 178 | S34: {=ROUND(IF(IFERROR(VALUE(RIGHT($AD34,1)),0)>2,IF($C34=8,O34*IFERROR(INDEX('TaxCred&Subs'!$K$139:$S$151,MATCH($C34&$D34&LEFT($AD34,7),'TaxCred&Subs'!$E$139:$E$151,0),MATCH($H34,'TaxCred&Subs'!$K$137:$S$137,0)),0),IF($C34=2,O34*IFERROR(INDEX('TaxCred&Subs'!$K$139:$S$151,MATCH($C34&$D34,'TaxCred&Subs'!$D$139:$D$151,0),MATCH($H34,'TaxCred&Subs'!$K$137:$S$137,0)),0),O34*IFERROR(INDEX('TaxCred&Subs'!$K$139:$S$151,MATCH($C34&$D34,'TaxCred&Subs'!$C$139:$C$151,0),MATCH($H34,'TaxCred&Subs'!$K$137:$S$137,0)),0))),0),0)} -> 215 | T34: =IF($H34=9,IF(R34>0,(N34-P34)*0.15,0),0) -> 0 | U34: =IF($H34=9,IF(S34>0,(O34-Q34)*0.15,0),0) -> 0 | V34: MATURE | W34: 2020 | X34: 1 | Y34: 0 | Z34: -0.00020762473 | AA34: -0.0031942266 | AB34: 0 | AC34: 0 | AD34: ELEC_HP3
B35: =B34+1 -> 11 | C35: 1 | D35: 2 | E35: 4 | F35: 2020 | G35: 2021 | H35: 3 | I35: 4 | J35: 0 | K35: 0 | L35: 0 | M35: 2.4912075 | N35: 3405 | O35: 4110 | P35: {=ROUND(IF($F35<='TaxCred&Subs'!$C$49,(IF($C35=2,IF($M35>=IFERROR(INDEX('TaxCred&Subs'!$L$12:$L$47,MATCH(1,($C35&$D35='TaxCred&Subs'!$E$12:$E$47)*($F35='TaxCred&Subs'!$C$12:$C$47),0) ),9999),IFERROR(INDEX('TaxCred&Subs'!$N$12:$N$47,MATCH(1,($C35&$D35='TaxCred&Subs'!$E$12:$E$47)*($F35='TaxCred&Subs'!$C$12:$C$47),0) ),0),0),(IF($M35>=IFERROR(INDEX('TaxCred&Subs'!$H$12:$H$47,MATCH(1,($C35&$D35='TaxCred&Subs'!$D$12:$D$47)*($F35='TaxCred&Subs'!$C$12:$C$47),0) ),9999),IFERROR(INDEX('TaxCred&Subs'!$N$12:$N$47,MATCH(1,($C35&$D35='TaxCred&Subs'!$D$12:$D$47)*($F35='TaxCred&Subs'!$C$12:$C$47),0) ),0),0)))),0)+IF(AND($C35=2,VALUE(RIGHT($AD35,1))>2),(N35-R35)*(IFERROR(INDEX('TaxCred&Subs'!$J$66:$J$99,MATCH(1,($C35&$D35='TaxCred&Subs'!$E$66:$E$99)*($F35='TaxCred&Subs'!$C$66:$C$99),0)),0)),IF(AND($C35=1,VALUE(RIGHT($AD35,1))>2),(N35-R35)*(IFERROR(INDEX('TaxCred&Subs'!$J$66:$J$99,MATCH(1,($C35&$D35='TaxCred&Subs'!$D$66:$D$99)*($F35='TaxCred&Subs'!$C$66:$C$99),0)),0)),IF($C35>2,(N35-R35)*(IFERROR(INDEX('TaxCred&Subs'!$J$66:$J$99,MATCH(1,($C35&$D35='TaxCred&Subs'!$D$66:$D$99)*($F35='TaxCred&Subs'!$C$66:$C$99),0)),0)),0))),0)} -> 150 | Q35: {=ROUND(IF(AND($C35=2,VALUE(RIGHT($AD35,1))>2),(O35-S35)*(IFERROR(INDEX('TaxCred&Subs'!$J$66:$J$99,MATCH(1,($C35&$D35='TaxCred&Subs'!$E$66:$E$99)*($F35='TaxCred&Subs'!$C$66:$C$99),0)),0)),IF(AND($C35=1,VALUE(RIGHT($AD35,1))>2),(O35-S35)*(IFERROR(INDEX('TaxCred&Subs'!$J$66:$J$99,MATCH(1,($C35&$D35='TaxCred&Subs'!$D$66:$D$99)*($F35='TaxCred&Subs'!$C$66:$C$99),0)),0)),IF($C35>2,(O35-S35)*(IFERROR(INDEX('TaxCred&Subs'!$J$66:$J$99,MATCH(1,($C35&$D35='TaxCred&Subs'!$D$66:$D$99)*($F35='TaxCred&Subs'!$C$66:$C$99),0)),0)),0))),0)} -> 0 | R35: {=ROUND(IF(IFERROR(VALUE(RIGHT($AD35,1)),0)>2,IF($C35=8,N35*IFERROR(INDEX('TaxCred&Subs'!$K$139:$S$151,MATCH($C35&$D35&LEFT($AD35,7),'TaxCred&Subs'!$E$139:$E$151,0),MATCH($H35,'TaxCred&Subs'!$K$137:$S$137,0)),0),IF($C35=2,N35*IFERROR(INDEX('TaxCred&Subs'!$K$139:$S$151,MATCH($C35&$D35,'TaxCred&Subs'!$D$139:$D$151,0),MATCH($H35,'TaxCred&Subs'!$K$137:$S$137,0)),0),N35*IFERROR(INDEX('TaxCred&Subs'!$K$139:$S$151,MATCH($C35&$D35,'TaxCred&Subs'!$C$139:$C$151,0),MATCH($H35,'TaxCred&Subs'!$K$137:$S$137,0)),0))),0),0)} -> 269 | S35: {=ROUND(IF(IFERROR(VALUE(RIGHT($AD35,1)),0)>2,IF($C35=8,O35*IFERROR(INDEX('TaxCred&Subs'!$K$139:$S$151,MATCH($C35&$D35&LEFT($AD35,7),'TaxCred&Subs'!$E$139:$E$151,0),MATCH($H35,'TaxCred&Subs'!$K$137:$S$137,0)),0),IF($C35=2,O35*IFERROR(INDEX('TaxCred&Subs'!$K$139:$S$151,MATCH($C35&$D35,'TaxCred&Subs'!$D$139:$D$151,0),MATCH($H35,'TaxCred&Subs'!$K$137:$S$137,0)),0),O35*IFERROR(INDEX('TaxCred&Subs'!$K$139:$S$151,MATCH($C35&$D35,'TaxCred&Subs'!$C$139:$C$151,0),MATCH($H35,'TaxCred&Subs'!$K$137:$S$137,0)),0))),0),0)} -> 325 | T35: =IF($H35=9,IF(R35>0,(N35-P35)*0.15,0),0) -> 0 | U35: =IF($H35=9,IF(S35>0,(O35-Q35)*0.15,0),0) -> 0 | V35: MATURE | W35: 2020 | X35: 1 | Y35: 0 | Z35: -0.00020762473 | AA35: -0.0031942266 | AB35: 0 | AC35: 0 | AD35: ELEC_HP3
B36: =B35+1 -> 12 | C36: 1 | D36: 2 | E36: 4 | F36: 2020 | G36: 2021 | H36: 4 | I36: 4 | J36: 0 | K36: 0 | L36: 0 | M36: 2.4912075 | N36: 3405 | O36: 4110 | P36: {=ROUND(IF($F36<='TaxCred&Subs'!$C$49,(IF($C36=2,IF($M36>=IFERROR(INDEX('TaxCred&Subs'!$L$12:$L$47,MATCH(1,($C36&$D36='TaxCred&Subs'!$E$12:$E$47)*($F36='TaxCred&Subs'!$C$12:$C$47),0) ),9999),IFERROR(INDEX('TaxCred&Subs'!$N$12:$N$47,MATCH(1,($C36&$D36='TaxCred&Subs'!$E$12:$E$47)*($F36='TaxCred&Subs'!$C$12:$C$47),0) ),0),0),(IF($M36>=IFERROR(INDEX('TaxCred&Subs'!$H$12:$H$47,MATCH(1,($C36&$D36='TaxCred&Subs'!$D$12:$D$47)*($F36='TaxCred&Subs'!$C$12:$C$47),0) ),9999),IFERROR(INDEX('TaxCred&Subs'!$N$12:$N$47,MATCH(1,($C36&$D36='TaxCred&Subs'!$D$12:$D$47)*($F36='TaxCred&Subs'!$C$12:$C$47),0) ),0),0)))),0)+IF(AND($C36=2,VALUE(RIGHT($AD36,1))>2),(N36-R36)*(IFERROR(INDEX('TaxCred&Subs'!$J$66:$J$99,MATCH(1,($C36&$D36='TaxCred&Subs'!$E$66:$E$99)*($F36='TaxCred&Subs'!$C$66:$C$99),0)),0)),IF(AND($C36=1,VALUE(RIGHT($AD36,1))>2),(N36-R36)*(IFERROR(INDEX('TaxCred&Subs'!$J$66:$J$99,MATCH(1,($C36&$D36='TaxCred&Subs'!$D$66:$D$99)*($F36='TaxCred&Subs'!$C$66:$C$99),0)),0)),IF($C36>2,(N36-R36)*(IFERROR(INDEX('TaxCred&Subs'!$J$66:$J$99,MATCH(1,($C36&$D36='TaxCred&Subs'!$D$66:$D$99)*($F36='TaxCred&Subs'!$C$66:$C$99),0)),0)),0))),0)} -> 150 | Q36: {=ROUND(IF(AND($C36=2,VALUE(RIGHT($AD36,1))>2),(O36-S36)*(IFERROR(INDEX('TaxCred&Subs'!$J$66:$J$99,MATCH(1,($C36&$D36='TaxCred&Subs'!$E$66:$E$99)*($F36='TaxCred&Subs'!$C$66:$C$99),0)),0)),IF(AND($C36=1,VALUE(RIGHT($AD36,1))>2),(O36-S36)*(IFERROR(INDEX('TaxCred&Subs'!$J$66:$J$99,MATCH(1,($C36&$D36='TaxCred&Subs'!$D$66:$D$99)*($F36='TaxCred&Subs'!$C$66:$C$99),0)),0)),IF($C36>2,(O36-S36)*(IFERROR(INDEX('TaxCred&Subs'!$J$66:$J$99,MATCH(1,($C36&$D36='TaxCred&Subs'!$D$66:$D$99)*($F36='TaxCred&Subs'!$C$66:$C$99),0)),0)),0))),0)} -> 0 | R36: {=ROUND(IF(IFERROR(VALUE(RIGHT($AD36,1)),0)>2,IF($C36=8,N36*IFERROR(INDEX('TaxCred&Subs'!$K$139:$S$151,MATCH($C36&$D36&LEFT($AD36,7),'TaxCred&Subs'!$E$139:$E$151,0),MATCH($H36,'TaxCred&Subs'!$K$137:$S$137,0)),0),IF($C36=2,N36*IFERROR(INDEX('TaxCred&Subs'!$K$139:$S$151,MATCH($C36&$D36,'TaxCred&Subs'!$D$139:$D$151,0),MATCH($H36,'TaxCred&Subs'!$K$137:$S$137,0)),0),N36*IFERROR(INDEX('TaxCred&Subs'!$K$139:$S$151,MATCH($C36&$D36,'TaxCred&Subs'!$C$139:$C$151,0),MATCH($H36,'TaxCred&Subs'!$K$137:$S$137,0)),0))),0),0)} -> 164 | S36: {=ROUND(IF(IFERROR(VALUE(RIGHT($AD36,1)),0)>2,IF($C36=8,O36*IFERROR(INDEX('TaxCred&Subs'!$K$139:$S$151,MATCH($C36&$D36&LEFT($AD36,7),'TaxCred&Subs'!$E$139:$E$151,0),MATCH($H36,'TaxCred&Subs'!$K$137:$S$137,0)),0),IF($C36=2,O36*IFERROR(INDEX('TaxCred&Subs'!$K$139:$S$151,MATCH($C36&$D36,'TaxCred&Subs'!$D$139:$D$151,0),MATCH($H36,'TaxCred&Subs'!$K$137:$S$137,0)),0),O36*IFERROR(INDEX('TaxCred&Subs'!$K$139:$S$151,MATCH($C36&$D36,'TaxCred&Subs'!$C$139:$C$151,0),MATCH($H36,'TaxCred&Subs'!$K$137:$S$137,0)),0))),0),0)} -> 198 | T36: =IF($H36=9,IF(R36>0,(N36-P36)*0.15,0),0) -> 0 | U36: =IF($H36=9,IF(S36>0,(O36-Q36)*0.15,0),0) -> 0 | V36: MATURE | W36: 2020 | X36: 1 | Y36: 0 | Z36: -0.00020762473 | AA36: -0.0031942266 | AB36: 0 | AC36: 0 | AD36: ELEC_HP3
B37: =B36+1 -> 13 | C37: 1 | D37: 2 | E37: 4 | F37: 2020 | G37: 2021 | H37: 5 | I37: 4 | J37: 0 | K37: 0 | L37: 0 | M37: 2.4912075 | N37: 3405 | O37: 4110 | P37: {=ROUND(IF($F37<='TaxCred&Subs'!$C$49,(IF($C37=2,IF($M37>=IFERROR(INDEX('TaxCred&Subs'!$L$12:$L$47,MATCH(1,($C37&$D37='TaxCred&Subs'!$E$12:$E$47)*($F37='TaxCred&Subs'!$C$12:$C$47),0) ),9999),IFERROR(INDEX('TaxCred&Subs'!$N$12:$N$47,MATCH(1,($C37&$D37='TaxCred&Subs'!$E$12:$E$47)*($F37='TaxCred&Subs'!$C$12:$C$47),0) ),0),0),(IF($M37>=IFERROR(INDEX('TaxCred&Subs'!$H$12:$H$47,MATCH(1,($C37&$D37='TaxCred&Subs'!$D$12:$D$47)*($F37='TaxCred&Subs'!$C$12:$C$47),0) ),9999),IFERROR(INDEX('TaxCred&Subs'!$N$12:$N$47,MATCH(1,($C37&$D37='TaxCred&Subs'!$D$12:$D$47)*($F37='TaxCred&Subs'!$C$12:$C$47),0) ),0),0)))),0)+IF(AND($C37=2,VALUE(RIGHT($AD37,1))>2),(N37-R37)*(IFERROR(INDEX('TaxCred&Subs'!$J$66:$J$99,MATCH(1,($C37&$D37='TaxCred&Subs'!$E$66:$E$99)*($F37='TaxCred&Subs'!$C$66:$C$99),0)),0)),IF(AND($C37=1,VALUE(RIGHT($AD37,1))>2),(N37-R37)*(IFERROR(INDEX('TaxCred&Subs'!$J$66:$J$99,MATCH(1,($C37&$D37='TaxCred&Subs'!$D$66:$D$99)*($F37='TaxCred&Subs'!$C$66:$C$99),0)),0)),IF($C37>2,(N37-R37)*(IFERROR(INDEX('TaxCred&Subs'!$J$66:$J$99,MATCH(1,($C37&$D37='TaxCred&Subs'!$D$66:$D$99)*($F37='TaxCred&Subs'!$C$66:$C$99),0)),0)),0))),0)} -> 150 | Q37: {=ROUND(IF(AND($C37=2,VALUE(RIGHT($AD37,1))>2),(O37-S37)*(IFERROR(INDEX('TaxCred&Subs'!$J$66:$J$99,MATCH(1,($C37&$D37='TaxCred&Subs'!$E$66:$E$99)*($F37='TaxCred&Subs'!$C$66:$C$99),0)),0)),IF(AND($C37=1,VALUE(RIGHT($AD37,1))>2),(O37-S37)*(IFERROR(INDEX('TaxCred&Subs'!$J$66:$J$99,MATCH(1,($C37&$D37='TaxCred&Subs'!$D$66:$D$99)*($F37='TaxCred&Subs'!$C$66:$C$99),0)),0)),IF($C37>2,(O37-S37)*(IFERROR(INDEX('TaxCred&Subs'!$J$66:$J$99,MATCH(1,($C37&$D37='TaxCred&Subs'!$D$66:$D$99)*($F37='TaxCred&Subs'!$C$66:$C$99),0)),0)),0))),0)} -> 0 | R37: {=ROUND(IF(IFERROR(VALUE(RIGHT($AD37,1)),0)>2,IF($C37=8,N37*IFERROR(INDEX('TaxCred&Subs'!$K$139:$S$151,MATCH($C37&$D37&LEFT($AD37,7),'TaxCred&Subs'!$E$139:$E$151,0),MATCH($H37,'TaxCred&Subs'!$K$137:$S$137,0)),0),IF($C37=2,N37*IFERROR(INDEX('TaxCred&Subs'!$K$139:$S$151,MATCH($C37&$D37,'TaxCred&Subs'!$D$139:$D$151,0),MATCH($H37,'TaxCred&Subs'!$K$137:$S$137,0)),0),N37*IFERROR(INDEX('TaxCred&Subs'!$K$139:$S$151,MATCH($C37&$D37,'TaxCred&Subs'!$C$139:$C$151,0),MATCH($H37,'TaxCred&Subs'!$K$137:$S$137,0)),0))),0),0)} -> 74 | S37: {=ROUND(IF(IFERROR(VALUE(RIGHT($AD37,1)),0)>2,IF($C37=8,O37*IFERROR(INDEX('TaxCred&Subs'!$K$139:$S$151,MATCH($C37&$D37&LEFT($AD37,7),'TaxCred&Subs'!$E$139:$E$151,0),MATCH($H37,'TaxCred&Subs'!$K$137:$S$137,0)),0),IF($C37=2,O37*IFERROR(INDEX('TaxCred&Subs'!$K$139:$S$151,MATCH($C37&$D37,'TaxCred&Subs'!$D$139:$D$151,0),MATCH($H37,'TaxCred&Subs'!$K$137:$S$137,0)),0),O37*IFERROR(INDEX('TaxCred&Subs'!$K$139:$S$151,MATCH($C37&$D37,'TaxCred&Subs'!$C$139:$C$151,0),MATCH($H37,'TaxCred&Subs'!$K$137:$S$137,0)),0))),0),0)} -> 90 | T37: =IF($H37=9,IF(R37>0,(N37-P37)*0.15,0),0) -> 0 | U37: =IF($H37=9,IF(S37>0,(O37-Q37)*0.15,0),0) -> 0 | V37: MATURE | W37: 2020 | X37: 1 | Y37: 0 | Z37: -0.00020762473 | AA37: -0.0031942266 | AB37: 0 | AC37: 0 | AD37: ELEC_HP3
... B117: =B116+1 -> 93 | C117: 1 | D117: 3 | E117: 8 | F117: 2022 | G117: 2028 | H117: 9 | I117: 8 | J117: 0 | K117: 0 | L117: 0 | M117: 0.9 | N117: 4130 | O117: 1200 | P117: {=ROUND(IF($F117<='TaxCred&Subs'!$C$49,(IF($C117=2,IF($M117>=IFERROR(INDEX('TaxCred&Subs'!$L$12:$L$47,MATCH(1,($C117&$D117='TaxCred&Subs'!$E$12:$E$47)*($F117='TaxCred&Subs'!$C$12:$C$47),0) ),9999),IFERROR(INDEX('TaxCred&Subs'!$N$12:$N$47,MATCH(1,($C117&$D117='TaxCred&Subs'!$E$12:$E$47)*($F117='TaxCred&Subs'!$C$12:$C$47),0) ),0),0),(IF($M117>=IFERROR(INDEX('TaxCred&Subs'!$H$12:$H$47,MATCH(1,($C117&$D117='TaxCred&Subs'!$D$12:$D$47)*($F117='TaxCred&Subs'!$C$12:$C$47),0) ),9999),IFERROR(INDEX('TaxCred&Subs'!$N$12:$N$47,MATCH(1,($C117&$D117='TaxCred&Subs'!$D$12:$D$47)*($F117='TaxCred&Subs'!$C$12:$C$47),0) ),0),0)))),0)+IF(AND($C117=2,VALUE(RIGHT($AD117,1))>2),(N117-R117)*(IFERROR(INDEX('TaxCred&Subs'!$J$66:$J$99,MATCH(1,($C117&$D117='TaxCred&Subs'!$E$66:$E$99)*($F117='TaxCred&Subs'!$C$66:$C$99),0)),0)),IF(AND($C117=1,VALUE(RIGHT($AD117,1))>2),(N117-R117)*(IFERROR(INDEX('TaxCred&Subs'!$J$66:$J$99,MATCH(1,($C117&$D117='TaxCred&Subs'!$D$66:$D$99)*($F117='TaxCred&Subs'!$C$66:$C$99),0)),0)),IF($C117>2,(N117-R117)*(IFERROR(INDEX('TaxCred&Subs'!$J$66:$J$99,MATCH(1,($C117&$D117='TaxCred&Subs'!$D$66:$D$99)*($F117='TaxCred&Subs'!$C$66:$C$99),0)),0)),0))),0)} -> 0 | Q117: {=ROUND(IF(AND($C117=2,VALUE(RIGHT($AD117,1))>2),(O117-S117)*(IFERROR(INDEX('TaxCred&Subs'!$J$66:$J$99,MATCH(1,($C117&$D117='TaxCred&Subs'!$E$66:$E$99)*($F117='TaxCred&Subs'!$C$66:$C$99),0)),0)),IF(AND($C117=1,VALUE(RIGHT($AD117,1))>2),(O117-S117)*(IFERROR(INDEX('TaxCred&Subs'!$J$66:$J$99,MATCH(1,($C117&$D117='TaxCred&Subs'!$D$66:$D$99)*($F117='TaxCred&Subs'!$C$66:$C$99),0)),0)),IF($C117>2,(O117-S117)*(IFERROR(INDEX('TaxCred&Subs'!$J$66:$J$99,MATCH(1,($C117&$D117='TaxCred&Subs'!$D$66:$D$99)*($F117='TaxCred&Subs'!$C$66:$C$99),0)),0)),0))),0)} -> 0 | R117: {=ROUND(IF(IFERROR(VALUE(RIGHT($AD117,1)),0)>2,IF($C117=8,N117*IFERROR(INDEX('TaxCred&Subs'!$K$139:$S$151,MATCH($C117&$D117&LEFT($AD117,7),'TaxCred&Subs'!$E$139:$E$151,0),MATCH($H117,'TaxCred&Subs'!$K$137:$S$137,0)),0),IF($C117=2,N117*IFERROR(INDEX('TaxCred&Subs'!$K$139:$S$151,MATCH($C117&$D117,'TaxCred&Subs'!$D$139:$D$151,0),MATCH($H117,'TaxCred&Subs'!$K$137:$S$137,0)),0),N117*IFERROR(INDEX('TaxCred&Subs'!$K$139:$S$151,MATCH($C117&$D117,'TaxCred&Subs'!$C$139:$C$151,0),MATCH($H117,'TaxCred&Subs'!$K$137:$S$137,0)),0))),0),0)} -> 624 | S117: {=ROUND(IF(IFERROR(VALUE(RIGHT($AD117,1)),0)>2,IF($C117=8,O117*IFERROR(INDEX('TaxCred&Subs'!$K$139:$S$151,MATCH($C117&$D117&LEFT($AD117,7),'TaxCred&Subs'!$E$139:$E$151,0),MATCH($H117,'TaxCred&Subs'!$K$137:$S$137,0)),0),IF($C117=2,O117*IFERROR(INDEX('TaxCred&Subs'!$K$139:$S$151,MATCH($C117&$D117,'TaxCred&Subs'!$D$139:$D$151,0),MATCH($H117,'TaxCred&Subs'!$K$137:$S$137,0)),0),O117*IFERROR(INDEX('TaxCred&Subs'!$K$139:$S$151,MATCH($C117&$D117,'TaxCred&Subs'!$C$139:$C$151,0),MATCH($H117,'TaxCred&Subs'!$K$137:$S$137,0)),0))),0),0)} -> 181 | T117: =IF($H117=9,IF(R117>0,(N117-P117)*0.15,0),0) -> 619.5 | U117: =IF($H117=9,IF(S117>0,(O117-Q117)*0.15,0),0) -> 180 | V117: MATURE | W117: 2020 | X117: 1 | Y117: 0 | Z117: -0.00021540078 | AA117: -0.0033138581 | AB117: 0 | AC117: 0 | AD117: NG_FA3
B118: =B117+1 -> 94 | C118: 1 | D118: 3 | E118: 8 | F118: 2029 | G118: 2050 | H118: 11 | I118: 8 | J118: 0 | K118: 0 | L118: 0 | M118: 0.95 | N118: 4150 | O118: 1220 | P118: {=ROUND(IF($F118<='TaxCred&Subs'!$C$49,(IF($C118=2,IF($M118>=IFERROR(INDEX('TaxCred&Subs'!$L$12:$L$47,MATCH(1,($C118&$D118='TaxCred&Subs'!$E$12:$E$47)*($F118='TaxCred&Subs'!$C$12:$C$47),0) ),9999),IFERROR(INDEX('TaxCred&Subs'!$N$12:$N$47,MATCH(1,($C118&$D118='TaxCred&Subs'!$E$12:$E$47)*($F118='TaxCred&Subs'!$C$12:$C$47),0) ),0),0),(IF($M118>=IFERROR(INDEX('TaxCred&Subs'!$H$12:$H$47,MATCH(1,($C118&$D118='TaxCred&Subs'!$D$12:$D$47)*($F118='TaxCred&Subs'!$C$12:$C$47),0) ),9999),IFERROR(INDEX('TaxCred&Subs'!$N$12:$N$47,MATCH(1,($C118&$D118='TaxCred&Subs'!$D$12:$D$47)*($F118='TaxCred&Subs'!$C$12:$C$47),0) ),0),0)))),0)+IF(AND($C118=2,VALUE(RIGHT($AD118,1))>2),(N118-R118)*(IFERROR(INDEX('TaxCred&Subs'!$J$66:$J$99,MATCH(1,($C118&$D118='TaxCred&Subs'!$E$66:$E$99)*($F118='TaxCred&Subs'!$C$66:$C$99),0)),0)),IF(AND($C118=1,VALUE(RIGHT($AD118,1))>2),(N118-R118)*(IFERROR(INDEX('TaxCred&Subs'!$J$66:$J$99,MATCH(1,($C118&$D118='TaxCred&Subs'!$D$66:$D$99)*($F118='TaxCred&Subs'!$C$66:$C$99),0)),0)),IF($C118>2,(N118-R118)*(IFERROR(INDEX('TaxCred&Subs'!$J$66:$J$99,MATCH(1,($C118&$D118='TaxCred&Subs'!$D$66:$D$99)*($F118='TaxCred&Subs'!$C$66:$C$99),0)),0)),0))),0)} -> 0 | Q118: {=ROUND(IF(AND($C118=2,VALUE(RIGHT($AD118,1))>2),(O118-S118)*(IFERROR(INDEX('TaxCred&Subs'!$J$66:$J$99,MATCH(1,($C118&$D118='TaxCred&Subs'!$E$66:$E$99)*($F118='TaxCred&Subs'!$C$66:$C$99),0)),0)),IF(AND($C118=1,VALUE(RIGHT($AD118,1))>2),(O118-S118)*(IFERROR(INDEX('TaxCred&Subs'!$J$66:$J$99,MATCH(1,($C118&$D118='TaxCred&Subs'!$D$66:$D$99)*($F118='TaxCred&Subs'!$C$66:$C$99),0)),0)),IF($C118>2,(O118-S118)*(IFERROR(INDEX('TaxCred&Subs'!$J$66:$J$99,MATCH(1,($C118&$D118='TaxCred&Subs'!$D$66:$D$99)*($F118='TaxCred&Subs'!$C$66:$C$99),0)),0)),0))),0)} -> 0 | R118: {=ROUND(IF(IFERROR(VALUE(RIGHT($AD118,1)),0)>2,IF($C118=8,N118*IFERROR(INDEX('TaxCred&Subs'!$K$139:$S$151,MATCH($C118&$D118&LEFT($AD118,7),'TaxCred&Subs'!$E$139:$E$151,0),MATCH($H118,'TaxCred&Subs'!$K$137:$S$137,0)),0),IF($C118=2,N118*IFERROR(INDEX('TaxCred&Subs'!$K$139:$S$151,MATCH($C118&$D118,'TaxCred&Subs'!$D$139:$D$151,0),MATCH($H118,'TaxCred&Subs'!$K$137:$S$137,0)),0),N118*IFERROR(INDEX('TaxCred&Subs'!$K$139:$S$151,MATCH($C118&$D118,'TaxCred&Subs'!$C$139:$C$151,0),MATCH($H118,'TaxCred&Subs'!$K$137:$S$137,0)),0))),0),0)} -> 0 | S118: {=ROUND(IF(IFERROR(VALUE(RIGHT($AD118,1)),0)>2,IF($C118=8,O118*IFERROR(INDEX('TaxCred&Subs'!$K$139:$S$151,MATCH($C118&$D118&LEFT($AD118,7),'TaxCred&Subs'!$E$139:$E$151,0),MATCH($H118,'TaxCred&Subs'!$K$137:$S$137,0)),0),IF($C118=2,O118*IFERROR(INDEX('TaxCred&Subs'!$K$139:$S$151,MATCH($C118&$D118,'TaxCred&Subs'!$D$139:$D$151,0),MATCH($H118,'TaxCred&Subs'!$K$137:$S$137,0)),0),O118*IFERROR(INDEX('TaxCred&Subs'!$K$139:$S$151,MATCH($C118&$D118,'TaxCred&Subs'!$C$139:$C$151,0),MATCH($H118,'TaxCred&Subs'!$K$137:$S$137,0)),0))),0),0)} -> 0 | T118: =IF($H118=9,IF(R118>0,(N118-P118)*0.15,0),0) -> 0 | U118: =IF($H118=9,IF(S118>0,(O118-Q118)*0.15,0),0) -> 0 | V118: MATURE | W118: 2020 | X118: 1 | Y118: 0 | Z118: -1 | AA118: -1 | AB118: 0 | AC118: 0 | AD118: NG_FA3 | AE118: Doesn't meet or is same as 2029 standard
B119: =B118+1 -> 95 | C119: 1 | D119: 3 | E119: 9 | F119: 2020 | G119: 2021 | H119: 1 | I119: 9 | J119: 0 | K119: 0 | L119: 0 | M119: 0.99 | N119: 4320 | O119: 1390 | P119: {=ROUND(IF($F119<='TaxCred&Subs'!$C$49,(IF($C119=2,IF($M119>=IFERROR(INDEX('TaxCred&Subs'!$L$12:$L$47,MATCH(1,($C119&$D119='TaxCred&Subs'!$E$12:$E$47)*($F119='TaxCred&Subs'!$C$12:$C$47),0) ),9999),IFERROR(INDEX('TaxCred&Subs'!$N$12:$N$47,MATCH(1,($C119&$D119='TaxCred&Subs'!$E$12:$E$47)*($F119='TaxCred&Subs'!$C$12:$C$47),0) ),0),0),(IF($M119>=IFERROR(INDEX('TaxCred&Subs'!$H$12:$H$47,MATCH(1,($C119&$D119='TaxCred&Subs'!$D$12:$D$47)*($F119='TaxCred&Subs'!$C$12:$C$47),0) ),9999),IFERROR(INDEX('TaxCred&Subs'!$N$12:$N$47,MATCH(1,($C119&$D119='TaxCred&Subs'!$D$12:$D$47)*($F119='TaxCred&Subs'!$C$12:$C$47),0) ),0),0)))),0)+IF(AND($C119=2,VALUE(RIGHT($AD119,1))>2),(N119-R119)*(IFERROR(INDEX('TaxCred&Subs'!$J$66:$J$99,MATCH(1,($C119&$D119='TaxCred&Subs'!$E$66:$E$99)*($F119='TaxCred&Subs'!$C$66:$C$99),0)),0)),IF(AND($C119=1,VALUE(RIGHT($AD119,1))>2),(N119-R119)*(IFERROR(INDEX('TaxCred&Subs'!$J$66:$J$99,MATCH(1,($C119&$D119='TaxCred&Subs'!$D$66:$D$99)*($F119='TaxCred&Subs'!$C$66:$C$99),0)),0)),IF($C119>2,(N119-R119)*(IFERROR(INDEX('TaxCred&Subs'!$J$66:$J$99,MATCH(1,($C119&$D119='TaxCred&Subs'!$D$66:$D$99)*($F119='TaxCred&Subs'!$C$66:$C$99),0)),0)),0))),0)} -> 150 | Q119: {=ROUND(IF(AND($C119=2,VALUE(RIGHT($AD119,1))>2),(O119-S119)*(IFERROR(INDEX('TaxCred&Subs'!$J$66:$J$99,MATCH(1,($C119&$D119='TaxCred&Subs'!$E$66:$E$99)*($F119='TaxCred&Subs'!$C$66:$C$99),0)),0)),IF(AND($C119=1,VALUE(RIGHT($AD119,1))>2),(O119-S119)*(IFERROR(INDEX('TaxCred&Subs'!$J$66:$J$99,MATCH(1,($C119&$D119='TaxCred&Subs'!$D$66:$D$99)*($F119='TaxCred&Subs'!$C$66:$C$99),0)),0)),IF($C119>2,(O119-S119)*(IFERROR(INDEX('TaxCred&Subs'!$J$66:$J$99,MATCH(1,($C119&$D119='TaxCred&Subs'!$D$66:$D$99)*($F119='TaxCred&Subs'!$C$66:$C$99),0)),0)),0))),0)} -> 0 | R119: {=ROUND(IF(IFERROR(VALUE(RIGHT($AD119,1)),0)>2,IF($C119=8,N119*IFERROR(INDEX('TaxCred&Subs'!$K$139:$S$151,MATCH($C119&$D119&LEFT($AD119,7),'TaxCred&Subs'!$E$139:$E$151,0),MATCH($H119,'TaxCred&Subs'!$K$137:$S$137,0)),0),IF($C119=2,N119*IFERROR(INDEX('TaxCred&Subs'!$K$139:$S$151,MATCH($C119&$D119,'TaxCred&Subs'!$D$139:$D$151,0),MATCH($H119,'TaxCred&Subs'!$K$137:$S$137,0)),0),N119*IFERROR(INDEX('TaxCred&Subs'!$K$139:$S$151,MATCH($C119&$D119,'TaxCred&Subs'!$C$139:$C$151,0),MATCH($H119,'TaxCred&Subs'!$K$137:$S$137,0)),0))),0),0)} -> 417 | S119: {=ROUND(IF(IFERROR(VALUE(RIGHT($AD119,1)),0)>2,IF($C119=8,O119*IFERROR(INDEX('TaxCred&Subs'!$K$139:$S$151,MATCH($C119&$D119&LEFT($AD119,7),'TaxCred&Subs'!$E$139:$E$151,0),MATCH($H119,'TaxCred&Subs'!$K$137:$S$137,0)),0),IF($C119=2,O119*IFERROR(INDEX('TaxCred&Subs'!$K$139:$S$151,MATCH($C119&$D119,'TaxCred&Subs'!$D$139:$D$151,0),MATCH($H119,'TaxCred&Subs'!$K$137:$S$137,0)),0),O119*IFERROR(INDEX('TaxCred&Subs'!$K$139:$S$151,MATCH($C119&$D119,'TaxCred&Subs'!$C$139:$C$151,0),MATCH($H119,'TaxCred&Subs'!$K$137:$S$137,0)),0))),0),0)} -> 134 | T119: =IF($H119=9,IF(R119>0,(N119-P119)*0.15,0),0) -> 0 | U119: =IF($H119=9,IF(S119>0,(O119-Q119)*0.15,0),0) -> 0 | V119: MATURE | W119: 2020 | X119: 1 | Y119: 0 | Z119: -0.00021540078 | AA119: -0.0033138581 | AB119: 0 | AC119: 0 | AD119: NG_FA4
B120: =B119+1 -> 96 | C120: 1 | D120: 3 | E120: 9 | F120: 2020 | G120: 2021 | H120: 2 | I120: 9 | J120: 0 | K120: 0 | L120: 0 | M120: 0.99 | N120: 4320 | O120: 1390 | P120: {=ROUND(IF($F120<='TaxCred&Subs'!$C$49,(IF($C120=2,IF($M120>=IFERROR(INDEX('TaxCred&Subs'!$L$12:$L$47,MATCH(1,($C120&$D120='TaxCred&Subs'!$E$12:$E$47)*($F120='TaxCred&Subs'!$C$12:$C$47),0) ),9999),IFERROR(INDEX('TaxCred&Subs'!$N$12:$N$47,MATCH(1,($C120&$D120='TaxCred&Subs'!$E$12:$E$47)*($F120='TaxCred&Subs'!$C$12:$C$47),0) ),0),0),(IF($M120>=IFERROR(INDEX('TaxCred&Subs'!$H$12:$H$47,MATCH(1,($C120&$D120='TaxCred&Subs'!$D$12:$D$47)*($F120='TaxCred&Subs'!$C$12:$C$47),0) ),9999),IFERROR(INDEX('TaxCred&Subs'!$N$12:$N$47,MATCH(1,($C120&$D120='TaxCred&Subs'!$D$12:$D$47)*($F120='TaxCred&Subs'!$C$12:$C$47),0) ),0),0)))),0)+IF(AND($C120=2,VALUE(RIGHT($AD120,1))>2),(N120-R120)*(IFERROR(INDEX('TaxCred&Subs'!$J$66:$J$99,MATCH(1,($C120&$D120='TaxCred&Subs'!$E$66:$E$99)*($F120='TaxCred&Subs'!$C$66:$C$99),0)),0)),IF(AND($C120=1,VALUE(RIGHT($AD120,1))>2),(N120-R120)*(IFERROR(INDEX('TaxCred&Subs'!$J$66:$J$99,MATCH(1,($C120&$D120='TaxCred&Subs'!$D$66:$D$99)*($F120='TaxCred&Subs'!$C$66:$C$99),0)),0)),IF($C120>2,(N120-R120)*(IFERROR(INDEX('TaxCred&Subs'!$J$66:$J$99,MATCH(1,($C120&$D120='TaxCred&Subs'!$D$66:$D$99)*($F120='TaxCred&Subs'!$C$66:$C$99),0)),0)),0))),0)} -> 150 | Q120: {=ROUND(IF(AND($C120=2,VALUE(RIGHT($AD120,1))>2),(O120-S120)*(IFERROR(INDEX('TaxCred&Subs'!$J$66:$J$99,MATCH(1,($C120&$D120='TaxCred&Subs'!$E$66:$E$99)*($F120='TaxCred&Subs'!$C$66:$C$99),0)),0)),IF(AND($C120=1,VALUE(RIGHT($AD120,1))>2),(O120-S120)*(IFERROR(INDEX('TaxCred&Subs'!$J$66:$J$99,MATCH(1,($C120&$D120='TaxCred&Subs'!$D$66:$D$99)*($F120='TaxCred&Subs'!$C$66:$C$99),0)),0)),IF($C120>2,(O120-S120)*(IFERROR(INDEX('TaxCred&Subs'!$J$66:$J$99,MATCH(1,($C120&$D120='TaxCred&Subs'!$D$66:$D$99)*($F120='TaxCred&Subs'!$C$66:$C$99),0)),0)),0))),0)} -> 0 | R120: {=ROUND(IF(IFERROR(VALUE(RIGHT($AD120,1)),0)>2,IF($C120=8,N120*IFERROR(INDEX('TaxCred&Subs'!$K$139:$S$151,MATCH($C120&$D120&LEFT($AD120,7),'TaxCred&Subs'!$E$139:$E$151,0),MATCH($H120,'TaxCred&Subs'!$K$137:$S$137,0)),0),IF($C120=2,N120*IFERROR(INDEX('TaxCred&Subs'!$K$139:$S$151,MATCH($C120&$D120,'TaxCred&Subs'!$D$139:$D$151,0),MATCH($H120,'TaxCred&Subs'!$K$137:$S$137,0)),0),N120*IFERROR(INDEX('TaxCred&Subs'!$K$139:$S$151,MATCH($C120&$D120,'TaxCred&Subs'!$C$139:$C$151,0),MATCH($H120,'TaxCred&Subs'!$K$137:$S$137,0)),0))),0),0)} -> 518 | S120: {=ROUND(IF(IFERROR(VALUE(RIGHT($AD120,1)),0)>2,IF($C120=8,O120*IFERROR(INDEX('TaxCred&Subs'!$K$139:$S$151,MATCH($C120&$D120&LEFT($AD120,7),'TaxCred&Subs'!$E$139:$E$151,0),MATCH($H120,'TaxCred&Subs'!$K$137:$S$137,0)),0),IF($C120=2,O120*IFERROR(INDEX('TaxCred&Subs'!$K$139:$S$151,MATCH($C120&$D120,'TaxCred&Subs'!$D$139:$D$151,0),MATCH($H120,'TaxCred&Subs'!$K$137:$S$137,0)),0),O120*IFERROR(INDEX('TaxCred&Subs'!$K$139:$S$151,MATCH($C120&$D120,'TaxCred&Subs'!$C$139:$C$151,0),MATCH($H120,'TaxCred&Subs'!$K$137:$S$137,0)),0))),0),0)} -> 167 | T120: =IF($H120=9,IF(R120>0,(N120-P120)*0.15,0),0) -> 0 | U120: =IF($H120=9,IF(S120>0,(O120-Q120)*0.15,0),0) -> 0 | V120: MATURE | W120: 2020 | X120: 1 | Y120: 0 | Z120: -0.00021540078 | AA120: -0.0033138581 | AB120: 0 | AC120: 0 | AD120: NG_FA4
B121: =B120+1 -> 97 | C121: 1 | D121: 3 | E121: 9 | F121: 2020 | G121: 2021 | H121: 3 | I121: 9 | J121: 0 | K121: 0 | L121: 0 | M121: 0.99 | N121: 4320 | O121: 1390 | P121: {=ROUND(IF($F121<='TaxCred&Subs'!$C$49,(IF($C121=2,IF($M121>=IFERROR(INDEX('TaxCred&Subs'!$L$12:$L$47,MATCH(1,($C121&$D121='TaxCred&Subs'!$E$12:$E$47)*($F121='TaxCred&Subs'!$C$12:$C$47),0) ),9999),IFERROR(INDEX('TaxCred&Subs'!$N$12:$N$47,MATCH(1,($C121&$D121='TaxCred&Subs'!$E$12:$E$47)*($F121='TaxCred&Subs'!$C$12:$C$47),0) ),0),0),(IF($M121>=IFERROR(INDEX('TaxCred&Subs'!$H$12:$H$47,MATCH(1,($C121&$D121='TaxCred&Subs'!$D$12:$D$47)*($F121='TaxCred&Subs'!$C$12:$C$47),0) ),9999),IFERROR(INDEX('TaxCred&Subs'!$N$12:$N$47,MATCH(1,($C121&$D121='TaxCred&Subs'!$D$12:$D$47)*($F121='TaxCred&Subs'!$C$12:$C$47),0) ),0),0)))),0)+IF(AND($C121=2,VALUE(RIGHT($AD121,1))>2),(N121-R121)*(IFERROR(INDEX('TaxCred&Subs'!$J$66:$J$99,MATCH(1,($C121&$D121='TaxCred&Subs'!$E$66:$E$99)*($F121='TaxCred&Subs'!$C$66:$C$99),0)),0)),IF(AND($C121=1,VALUE(RIGHT($AD121,1))>2),(N121-R121)*(IFERROR(INDEX('TaxCred&Subs'!$J$66:$J$99,MATCH(1,($C121&$D121='TaxCred&Subs'!$D$66:$D$99)*($F121='TaxCred&Subs'!$C$66:$C$99),0)),0)),IF($C121>2,(N121-R121)*(IFERROR(INDEX('TaxCred&Subs'!$J$66:$J$99,MATCH(1,($C121&$D121='TaxCred&Subs'!$D$66:$D$99)*($F121='TaxCred&Subs'!$C$66:$C$99),0)),0)),0))),0)} -> 150 | Q121: {=ROUND(IF(AND($C121=2,VALUE(RIGHT($AD121,1))>2),(O121-S121)*(IFERROR(INDEX('TaxCred&Subs'!$J$66:$J$99,MATCH(1,($C121&$D121='TaxCred&Subs'!$E$66:$E$99)*($F121='TaxCred&Subs'!$C$66:$C$99),0)),0)),IF(AND($C121=1,VALUE(RIGHT($AD121,1))>2),(O121-S121)*(IFERROR(INDEX('TaxCred&Subs'!$J$66:$J$99,MATCH(1,($C121&$D121='TaxCred&Subs'!$D$66:$D$99)*($F121='TaxCred&Subs'!$C$66:$C$99),0)),0)),IF($C121>2,(O121-S121)*(IFERROR(INDEX('TaxCred&Subs'!$J$66:$J$99,MATCH(1,($C121&$D121='TaxCred&Subs'!$D$66:$D$99)*($F121='TaxCred&Subs'!$C$66:$C$99),0)),0)),0))),0)} -> 0 | R121: {=ROUND(IF(IFERROR(VALUE(RIGHT($AD121,1)),0)>2,IF($C121=8,N121*IFERROR(INDEX('TaxCred&Subs'!$K$139:$S$151,MATCH($C121&$D121&LEFT($AD121,7),'TaxCred&Subs'!$E$139:$E$151,0),MATCH($H121,'TaxCred&Subs'!$K$137:$S$137,0)),0),IF($C121=2,N121*IFERROR(INDEX('TaxCred&Subs'!$K$139:$S$151,MATCH($C121&$D121,'TaxCred&Subs'!$D$139:$D$151,0),MATCH($H121,'TaxCred&Subs'!$K$137:$S$137,0)),0),N121*IFERROR(INDEX('TaxCred&Subs'!$K$139:$S$151,MATCH($C121&$D121,'TaxCred&Subs'!$C$139:$C$151,0),MATCH($H121,'TaxCred&Subs'!$K$137:$S$137,0)),0))),0),0)} -> 225 | S121: {=ROUND(IF(IFERROR(VALUE(RIGHT($AD121,1)),0)>2,IF($C121=8,O121*IFERROR(INDEX('TaxCred&Subs'!$K$139:$S$151,MATCH($C121&$D121&LEFT($AD121,7),'TaxCred&Subs'!$E$139:$E$151,0),MATCH($H121,'TaxCred&Subs'!$K$137:$S$137,0)),0),IF($C121=2,O121*IFERROR(INDEX('TaxCred&Subs'!$K$139:$S$151,MATCH($C121&$D121,'TaxCred&Subs'!$D$139:$D$151,0),MATCH($H121,'TaxCred&Subs'!$K$137:$S$137,0)),0),O121*IFERROR(INDEX('TaxCred&Subs'!$K$139:$S$151,MATCH($C121&$D121,'TaxCred&Subs'!$C$139:$C$151,0),MATCH($H121,'TaxCred&Subs'!$K$137:$S$137,0)),0))),0),0)} -> 72 | T121: =IF($H121=9,IF(R121>0,(N121-P121)*0.15,0),0) -> 0 | U121: =IF($H121=9,IF(S121>0,(O121-Q121)*0.15,0),0) -> 0 | V121: MATURE | W121: 2020 | X121: 1 | Y121: 0 | Z121: -0.00021540078 | AA121: -0.0033138581 | AB121: 0 | AC121: 0 | AD121: NG_FA4
B122: =B121+1 -> 98 | C122: 1 | D122: 3 | E122: 9 | F122: 2020 | G122: 2021 | H122: 4 | I122: 9 | J122: 0 | K122: 0 | L122: 0 | M122: 0.99 | N122: 4320 | O122: 1390 | P122: {=ROUND(IF($F122<='TaxCred&Subs'!$C$49,(IF($C122=2,IF($M122>=IFERROR(INDEX('TaxCred&Subs'!$L$12:$L$47,MATCH(1,($C122&$D122='TaxCred&Subs'!$E$12:$E$47)*($F122='TaxCred&Subs'!$C$12:$C$47),0) ),9999),IFERROR(INDEX('TaxCred&Subs'!$N$12:$N$47,MATCH(1,($C122&$D122='TaxCred&Subs'!$E$12:$E$47)*($F122='TaxCred&Subs'!$C$12:$C$47),0) ),0),0),(IF($M122>=IFERROR(INDEX('TaxCred&Subs'!$H$12:$H$47,MATCH(1,($C122&$D122='TaxCred&Subs'!$D$12:$D$47)*($F122='TaxCred&Subs'!$C$12:$C$47),0) ),9999),IFERROR(INDEX('TaxCred&Subs'!$N$12:$N$47,MATCH(1,($C122&$D122='TaxCred&Subs'!$D$12:$D$47)*($F122='TaxCred&Subs'!$C$12:$C$47),0) ),0),0)))),0)+IF(AND($C122=2,VALUE(RIGHT($AD122,1))>2),(N122-R122)*(IFERROR(INDEX('TaxCred&Subs'!$J$66:$J$99,MATCH(1,($C122&$D122='TaxCred&Subs'!$E$66:$E$99)*($F122='TaxCred&Subs'!$C$66:$C$99),0)),0)),IF(AND($C122=1,VALUE(RIGHT($AD122,1))>2),(N122-R122)*(IFERROR(INDEX('TaxCred&Subs'!$J$66:$J$99,MATCH(1,($C122&$D122='TaxCred&Subs'!$D$66:$D$99)*($F122='TaxCred&Subs'!$C$66:$C$99),0)),0)),IF($C122>2,(N122-R122)*(IFERROR(INDEX('TaxCred&Subs'!$J$66:$J$99,MATCH(1,($C122&$D122='TaxCred&Subs'!$D$66:$D$99)*($F122='TaxCred&Subs'!$C$66:$C$99),0)),0)),0))),0)} -> 150 | Q122: {=ROUND(IF(AND($C122=2,VALUE(RIGHT($AD122,1))>2),(O122-S122)*(IFERROR(INDEX('TaxCred&Subs'!$J$66:$J$99,MATCH(1,($C122&$D122='TaxCred&Subs'!$E$66:$E$99)*($F122='TaxCred&Subs'!$C$66:$C$99),0)),0)),IF(AND($C122=1,VALUE(RIGHT($AD122,1))>2),(O122-S122)*(IFERROR(INDEX('TaxCred&Subs'!$J$66:$J$99,MATCH(1,($C122&$D122='TaxCred&Subs'!$D$66:$D$99)*($F122='TaxCred&Subs'!$C$66:$C$99),0)),0)),IF($C122>2,(O122-S122)*(IFERROR(INDEX('TaxCred&Subs'!$J$66:$J$99,MATCH(1,($C122&$D122='TaxCred&Subs'!$D$66:$D$99)*($F122='TaxCred&Subs'!$C$66:$C$99),0)),0)),0))),0)} -> 0 | R122: {=ROUND(IF(IFERROR(VALUE(RIGHT($AD122,1)),0)>2,IF($C122=8,N122*IFERROR(INDEX('TaxCred&Subs'!$K$139:$S$151,MATCH($C122&$D122&LEFT($AD122,7),'TaxCred&Subs'!$E$139:$E$151,0),MATCH($H122,'TaxCred&Subs'!$K$137:$S$137,0)),0),IF($C122=2,N122*IFERROR(INDEX('TaxCred&Subs'!$K$139:$S$151,MATCH($C122&$D122,'TaxCred&Subs'!$D$139:$D$151,0),MATCH($H122,'TaxCred&Subs'!$K$137:$S$137,0)),0),N122*IFERROR(INDEX('TaxCred&Subs'!$K$139:$S$151,MATCH($C122&$D122,'TaxCred&Subs'!$C$139:$C$151,0),MATCH($H122,'TaxCred&Subs'!$K$137:$S$137,0)),0))),0),0)} -> 218 | S122: {=ROUND(IF(IFERROR(VALUE(RIGHT($AD122,1)),0)>2,IF($C122=8,O122*IFERROR(INDEX('TaxCred&Subs'!$K$139:$S$151,MATCH($C122&$D122&LEFT($AD122,7),'TaxCred&Subs'!$E$139:$E$151,0),MATCH($H122,'TaxCred&Subs'!$K$137:$S$137,0)),0),IF($C122=2,O122*IFERROR(INDEX('TaxCred&Subs'!$K$139:$S$151,MATCH($C122&$D122,'TaxCred&Subs'!$D$139:$D$151,0),MATCH($H122,'TaxCred&Subs'!$K$137:$S$137,0)),0),O122*IFERROR(INDEX('TaxCred&Subs'!$K$139:$S$151,MATCH($C122&$D122,'TaxCred&Subs'!$C$139:$C$151,0),MATCH($H122,'TaxCred&Subs'!$K$137:$S$137,0)),0))),0),0)} -> 70 | T122: =IF($H122=9,IF(R122>0,(N122-P122)*0.15,0),0) -> 0 | U122: =IF($H122=9,IF(S122>0,(O122-Q122)*0.15,0),0) -> 0 | V122: MATURE | W122: 2020 | X122: 1 | Y122: 0 | Z122: -0.00021540078 | AA122: -0.0033138581 | AB122: 0 | AC122: 0 | AD122: NG_FA4
B123: =B122+1 -> 99 | C123: 1 | D123: 3 | E123: 9 | F123: 2020 | G123: 2021 | H123: 5 | I123: 9 | J123: 0 | K123: 0 | L123: 0 | M123: 0.99 | N123: 4320 | O123: 1390 | P123: {=ROUND(IF($F123<='TaxCred&Subs'!$C$49,(IF($C123=2,IF($M123>=IFERROR(INDEX('TaxCred&Subs'!$L$12:$L$47,MATCH(1,($C123&$D123='TaxCred&Subs'!$E$12:$E$47)*($F123='TaxCred&Subs'!$C$12:$C$47),0) ),9999),IFERROR(INDEX('TaxCred&Subs'!$N$12:$N$47,MATCH(1,($C123&$D123='TaxCred&Subs'!$E$12:$E$47)*($F123='TaxCred&Subs'!$C$12:$C$47),0) ),0),0),(IF($M123>=IFERROR(INDEX('TaxCred&Subs'!$H$12:$H$47,MATCH(1,($C123&$D123='TaxCred&Subs'!$D$12:$D$47)*($F123='TaxCred&Subs'!$C$12:$C$47),0) ),9999),IFERROR(INDEX('TaxCred&Subs'!$N$12:$N$47,MATCH(1,($C123&$D123='TaxCred&Subs'!$D$12:$D$47)*($F123='TaxCred&Subs'!$C$12:$C$47),0) ),0),0)))),0)+IF(AND($C123=2,VALUE(RIGHT($AD123,1))>2),(N123-R123)*(IFERROR(INDEX('TaxCred&Subs'!$J$66:$J$99,MATCH(1,($C123&$D123='TaxCred&Subs'!$E$66:$E$99)*($F123='TaxCred&Subs'!$C$66:$C$99),0)),0)),IF(AND($C123=1,VALUE(RIGHT($AD123,1))>2),(N123-R123)*(IFERROR(INDEX('TaxCred&Subs'!$J$66:$J$99,MATCH(1,($C123&$D123='TaxCred&Subs'!$D$66:$D$99)*($F123='TaxCred&Subs'!$C$66:$C$99),0)),0)),IF($C123>2,(N123-R123)*(IFERROR(INDEX('TaxCred&Subs'!$J$66:$J$99,MATCH(1,($C123&$D123='TaxCred&Subs'!$D$66:$D$99)*($F123='TaxCred&Subs'!$C$66:$C$99),0)),0)),0))),0)} -> 150 | Q123: {=ROUND(IF(AND($C123=2,VALUE(RIGHT($AD123,1))>2),(O123-S123)*(IFERROR(INDEX('TaxCred&Subs'!$J$66:$J$99,MATCH(1,($C123&$D123='TaxCred&Subs'!$E$66:$E$99)*($F123='TaxCred&Subs'!$C$66:$C$99),0)),0)),IF(AND($C123=1,VALUE(RIGHT($AD123,1))>2),(O123-S123)*(IFERROR(INDEX('TaxCred&Subs'!$J$66:$J$99,MATCH(1,($C123&$D123='TaxCred&Subs'!$D$66:$D$99)*($F123='TaxCred&Subs'!$C$66:$C$99),0)),0)),IF($C123>2,(O123-S123)*(IFERROR(INDEX('TaxCred&Subs'!$J$66:$J$99,MATCH(1,($C123&$D123='TaxCred&Subs'!$D$66:$D$99)*($F123='TaxCred&Subs'!$C$66:$C$99),0)),0)),0))),0)} -> 0 | R123: {=ROUND(IF(IFERROR(VALUE(RIGHT($AD123,1)),0)>2,IF($C123=8,N123*IFERROR(INDEX('TaxCred&Subs'!$K$139:$S$151,MATCH($C123&$D123&LEFT($AD123,7),'TaxCred&Subs'!$E$139:$E$151,0),MATCH($H123,'TaxCred&Subs'!$K$137:$S$137,0)),0),IF($C123=2,N123*IFERROR(INDEX('TaxCred&Subs'!$K$139:$S$151,MATCH($C123&$D123,'TaxCred&Subs'!$D$139:$D$151,0),MATCH($H123,'TaxCred&Subs'!$K$137:$S$137,0)),0),N123*IFERROR(INDEX('TaxCred&Subs'!$K$139:$S$151,MATCH($C123&$D123,'TaxCred&Subs'!$C$139:$C$151,0),MATCH($H123,'TaxCred&Subs'!$K$137:$S$137,0)),0))),0),0)} -> 350 | S123: {=ROUND(IF(IFERROR(VALUE(RIGHT($AD123,1)),0)>2,IF($C123=8,O123*IFERROR(INDEX('TaxCred&Subs'!$K$139:$S$151,MATCH($C123&$D123&LEFT($AD123,7),'TaxCred&Subs'!$E$139:$E$151,0),MATCH($H123,'TaxCred&Subs'!$K$137:$S$137,0)),0),IF($C123=2,O123*IFERROR(INDEX('TaxCred&Subs'!$K$139:$S$151,MATCH($C123&$D123,'TaxCred&Subs'!$D$139:$D$151,0),MATCH($H123,'TaxCred&Subs'!$K$137:$S$137,0)),0),O123*IFERROR(INDEX('TaxCred&Subs'!$K$139:$S$151,MATCH($C123&$D123,'TaxCred&Subs'!$C$139:$C$151,0),MATCH($H123,'TaxCred&Subs'!$K$137:$S$137,0)),0))),0),0)} -> 112 | T123: =IF($H123=9,IF(R123>0,(N123-P123)*0.15,0),0) -> 0 | U123: =IF($H123=9,IF(S123>0,(O123-Q123)*0.15,0),0) -> 0 | V123: MATURE | W123: 2020 | X123: 1 | Y123: 0 | Z123: -0.00021540078 | AA123: -0.0033138581 | AB123: 0 | AC123: 0 | AD123: NG_FA4
B124: =B123+1 -> 100 | C124: 1 | D124: 3 | E124: 9 | F124: 2020 | G124: 2021 | H124: 6 | I124: 9 | J124: 0 | K124: 0 | L124: 0 | M124: 0.99 | N124: 4320 | O124: 1390 | P124: {=ROUND(IF($F124<='TaxCred&Subs'!$C$49,(IF($C124=2,IF($M124>=IFERROR(INDEX('TaxCred&Subs'!$L$12:$L$47,MATCH(1,($C124&$D124='TaxCred&Subs'!$E$12:$E$47)*($F124='TaxCred&Subs'!$C$12:$C$47),0) ),9999),IFERROR(INDEX('TaxCred&Subs'!$N$12:$N$47,MATCH(1,($C124&$D124='TaxCred&Subs'!$E$12:$E$47)*($F124='TaxCred&Subs'!$C$12:$C$47),0) ),0),0),(IF($M124>=IFERROR(INDEX('TaxCred&Subs'!$H$12:$H$47,MATCH(1,($C124&$D124='TaxCred&Subs'!$D$12:$D$47)*($F124='TaxCred&Subs'!$C$12:$C$47),0) ),9999),IFERROR(INDEX('TaxCred&Subs'!$N$12:$N$47,MATCH(1,($C124&$D124='TaxCred&Subs'!$D$12:$D$47)*($F124='TaxCred&Subs'!$C$12:$C$47),0) ),0),0)))),0)+IF(AND($C124=2,VALUE(RIGHT($AD124,1))>2),(N124-R124)*(IFERROR(INDEX('TaxCred&Subs'!$J$66:$J$99,MATCH(1,($C124&$D124='TaxCred&Subs'!$E$66:$E$99)*($F124='TaxCred&Subs'!$C$66:$C$99),0)),0)),IF(AND($C124=1,VALUE(RIGHT($AD124,1))>2),(N124-R124)*(IFERROR(INDEX('TaxCred&Subs'!$J$66:$J$99,MATCH(1,($C124&$D124='TaxCred&Subs'!$D$66:$D$99)*($F124='TaxCred&Subs'!$C$66:$C$99),0)),0)),IF($C124>2,(N124-R124)*(IFERROR(INDEX('TaxCred&Subs'!$J$66:$J$99,MATCH(1,($C124&$D124='TaxCred&Subs'!$D$66:$D$99)*($F124='TaxCred&Subs'!$C$66:$C$99),0)),0)),0))),0)} -> 150 | Q124: {=ROUND(IF(AND($C124=2,VALUE(RIGHT($AD124,1))>2),(O124-S124)*(IFERROR(INDEX('TaxCred&Subs'!$J$66:$J$99,MATCH(1,($C124&$D124='TaxCred&Subs'!$E$66:$E$99)*($F124='TaxCred&Subs'!$C$66:$C$99),0)),0)),IF(AND($C124=1,VALUE(RIGHT($AD124,1))>2),(O124-S124)*(IFERROR(INDEX('TaxCred&Subs'!$J$66:$J$99,MATCH(1,($C124&$D124='TaxCred&Subs'!$D$66:$D$99)*($F124='TaxCred&Subs'!$C$66:$C$99),0)),0)),IF($C124>2,(O124-S124)*(IFERROR(INDEX('TaxCred&Subs'!$J$66:$J$99,MATCH(1,($C124&$D124='TaxCred&Subs'!$D$66:$D$99)*($F124='TaxCred&Subs'!$C$66:$C$99),0)),0)),0))),0)} -> 0 | R124: {=ROUND(IF(IFERROR(VALUE(RIGHT($AD124,1)),0)>2,IF($C124=8,N124*IFERROR(INDEX('TaxCred&Subs'!$K$139:$S$151,MATCH($C124&$D124&LEFT($AD124,7),'TaxCred&Subs'!$E$139:$E$151,0),MATCH($H124,'TaxCred&Subs'!$K$137:$S$137,0)),0),IF($C124=2,N124*IFERROR(INDEX('TaxCred&Subs'!$K$139:$S$151,MATCH($C124&$D124,'TaxCred&Subs'!$D$139:$D$151,0),MATCH($H124,'TaxCred&Subs'!$K$137:$S$137,0)),0),N124*IFERROR(INDEX('TaxCred&Subs'!$K$139:$S$151,MATCH($C124&$D124,'TaxCred&Subs'!$C$139:$C$151,0),MATCH($H124,'TaxCred&Subs'!$K$137:$S$137,0)),0))),0),0)} -> 304 | S124: {=ROUND(IF(IFERROR(VALUE(RIGHT($AD124,1)),0)>2,IF($C124=8,O124*IFERROR(INDEX('TaxCred&Subs'!$K$139:$S$151,MATCH($C124&$D124&LEFT($AD124,7),'TaxCred&Subs'!$E$139:$E$151,0),MATCH($H124,'TaxCred&Subs'!$K$137:$S$137,0)),0),IF($C124=2,O124*IFERROR(INDEX('TaxCred&Subs'!$K$139:$S$151,MATCH($C124&$D124,'TaxCred&Subs'!$D$139:$D$151,0),MATCH($H124,'TaxCred&Subs'!$K$137:$S$137,0)),0),O124*IFERROR(INDEX('TaxCred&Subs'!$K$139:$S$151,MATCH($C124&$D124,'TaxCred&Subs'!$C$139:$C$151,0),MATCH($H124,'TaxCred&Subs'!$K$137:$S$137,0)),0))),0),0)} -> 98 | T124: =IF($H124=9,IF(R124>0,(N124-P124)*0.15,0),0) -> 0 | U124: =IF($H124=9,IF(S124>0,(O124-Q124)*0.15,0),0) -> 0 | V124: MATURE | W124: 2020 | X124: 1 | Y124: 0 | Z124: -0.00021540078 | AA124: -0.0033138581 | AB124: 0 | AC124: 0 | AD124: NG_FA4
B125: =B124+1 -> 101 | C125: 1 | D125: 3 | E125: 9 | F125: 2020 | G125: 2021 | H125: 7 | I125: 9 | J125: 0 | K125: 0 | L125: 0 | M125: 0.99 | N125: 4320 | O125: 1390 | P125: {=ROUND(IF($F125<='TaxCred&Subs'!$C$49,(IF($C125=2,IF($M125>=IFERROR(INDEX('TaxCred&Subs'!$L$12:$L$47,MATCH(1,($C125&$D125='TaxCred&Subs'!$E$12:$E$47)*($F125='TaxCred&Subs'!$C$12:$C$47),0) ),9999),IFERROR(INDEX('TaxCred&Subs'!$N$12:$N$47,MATCH(1,($C125&$D125='TaxCred&Subs'!$E$12:$E$47)*($F125='TaxCred&Subs'!$C$12:$C$47),0) ),0),0),(IF($M125>=IFERROR(INDEX('TaxCred&Subs'!$H$12:$H$47,MATCH(1,($C125&$D125='TaxCred&Subs'!$D$12:$D$47)*($F125='TaxCred&Subs'!$C$12:$C$47),0) ),9999),IFERROR(INDEX('TaxCred&Subs'!$N$12:$N$47,MATCH(1,($C125&$D125='TaxCred&Subs'!$D$12:$D$47)*($F125='TaxCred&Subs'!$C$12:$C$47),0) ),0),0)))),0)+IF(AND($C125=2,VALUE(RIGHT($AD125,1))>2),(N125-R125)*(IFERROR(INDEX('TaxCred&Subs'!$J$66:$J$99,MATCH(1,($C125&$D125='TaxCred&Subs'!$E$66:$E$99)*($F125='TaxCred&Subs'!$C$66:$C$99),0)),0)),IF(AND($C125=1,VALUE(RIGHT($AD125,1))>2),(N125-R125)*(IFERROR(INDEX('TaxCred&Subs'!$J$66:$J$99,MATCH(1,($C125&$D125='TaxCred&Subs'!$D$66:$D$99)*($F125='TaxCred&Subs'!$C$66:$C$99),0)),0)),IF($C125>2,(N125-R125)*(IFERROR(INDEX('TaxCred&Subs'!$J$66:$J$99,MATCH(1,($C125&$D125='TaxCred&Subs'!$D$66:$D$99)*($F125='TaxCred&Subs'!$C$66:$C$99),0)),0)),0))),0)} -> 150 | Q125: {=ROUND(IF(AND($C125=2,VALUE(RIGHT($AD125,1))>2),(O125-S125)*(IFERROR(INDEX('TaxCred&Subs'!$J$66:$J$99,MATCH(1,($C125&$D125='TaxCred&Subs'!$E$66:$E$99)*($F125='TaxCred&Subs'!$C$66:$C$99),0)),0)),IF(AND($C125=1,VALUE(RIGHT($AD125,1))>2),(O125-S125)*(IFERROR(INDEX('TaxCred&Subs'!$J$66:$J$99,MATCH(1,($C125&$D125='TaxCred&Subs'!$D$66:$D$99)*($F125='TaxCred&Subs'!$C$66:$C$99),0)),0)),IF($C125>2,(O125-S125)*(IFERROR(INDEX('TaxCred&Subs'!$J$66:$J$99,MATCH(1,($C125&$D125='TaxCred&Subs'!$D$66:$D$99)*($F125='TaxCred&Subs'!$C$66:$C$99),0)),0)),0))),0)} -> 0 | R125: {=ROUND(IF(IFERROR(VALUE(RIGHT($AD125,1)),0)>2,IF($C125=8,N125*IFERROR(INDEX('TaxCred&Subs'!$K$139:$S$151,MATCH($C125&$D125&LEFT($AD125,7),'TaxCred&Subs'!$E$139:$E$151,0),MATCH($H125,'TaxCred&Subs'!$K$137:$S$137,0)),0),IF($C125=2,N125*IFERROR(INDEX('TaxCred&Subs'!$K$139:$S$151,MATCH($C125&$D125,'TaxCred&Subs'!$D$139:$D$151,0),MATCH($H125,'TaxCred&Subs'!$K$137:$S$137,0)),0),N125*IFERROR(INDEX('TaxCred&Subs'!$K$139:$S$151,MATCH($C125&$D125,'TaxCred&Subs'!$C$139:$C$151,0),MATCH($H125,'TaxCred&Subs'!$K$137:$S$137,0)),0))),0),0)} -> 13 | S125: {=ROUND(IF(IFERROR(VALUE(RIGHT($AD125,1)),0)>2,IF($C125=8,O125*IFERROR(INDEX('TaxCred&Subs'!$K$139:$S$151,MATCH($C125&$D125&LEFT($AD125,7),'TaxCred&Subs'!$E$139:$E$151,0),MATCH($H125,'TaxCred&Subs'!$K$137:$S$137,0)),0),IF($C125=2,O125*IFERROR(INDEX('TaxCred&Subs'!$K$139:$S$151,MATCH($C125&$D125,'TaxCred&Subs'!$D$139:$D$151,0),MATCH($H125,'TaxCred&Subs'!$K$137:$S$137,0)),0),O125*IFERROR(INDEX('TaxCred&Subs'!$K$139:$S$151,MATCH($C125&$D125,'TaxCred&Subs'!$C$139:$C$151,0),MATCH($H125,'TaxCred&Subs'!$K$137:$S$137,0)),0))),0),0)} -> 4 | T125: =IF($H125=9,IF(R125>0,(N125-P125)*0.15,0),0) -> 0 | U125: =IF($H125=9,IF(S125>0,(O125-Q125)*0.15,0),0) -> 0 | V125: MATURE | W125: 2020 | X125: 1 | Y125: 0 | Z125: -0.00021540078 | AA125: -0.0033138581 | AB125: 0 | AC125: 0 | AD125: NG_FA4
B126: =B125+1 -> 102 | C126: 1 | D126: 3 | E126: 9 | F126: 2020 | G126: 2021 | H126: 8 | I126: 9 | J126: 0 | K126: 0 | L126: 0 | M126: 0.99 | N126: 4320 | O126: 1390 | P126: {=ROUND(IF($F126<='TaxCred&Subs'!$C$49,(IF($C126=2,IF($M126>=IFERROR(INDEX('TaxCred&Subs'!$L$12:$L$47,MATCH(1,($C126&$D126='TaxCred&Subs'!$E$12:$E$47)*($F126='TaxCred&Subs'!$C$12:$C$47),0) ),9999),IFERROR(INDEX('TaxCred&Subs'!$N$12:$N$47,MATCH(1,($C126&$D126='TaxCred&Subs'!$E$12:$E$47)*($F126='TaxCred&Subs'!$C$12:$C$47),0) ),0),0),(IF($M126>=IFERROR(INDEX('TaxCred&Subs'!$H$12:$H$47,MATCH(1,($C126&$D126='TaxCred&Subs'!$D$12:$D$47)*($F126='TaxCred&Subs'!$C$12:$C$47),0) ),9999),IFERROR(INDEX('TaxCred&Subs'!$N$12:$N$47,MATCH(1,($C126&$D126='TaxCred&Subs'!$D$12:$D$47)*($F126='TaxCred&Subs'!$C$12:$C$47),0) ),0),0)))),0)+IF(AND($C126=2,VALUE(RIGHT($AD126,1))>2),(N126-R126)*(IFERROR(INDEX('TaxCred&Subs'!$J$66:$J$99,MATCH(1,($C126&$D126='TaxCred&Subs'!$E$66:$E$99)*($F126='TaxCred&Subs'!$C$66:$C$99),0)),0)),IF(AND($C126=1,VALUE(RIGHT($AD126,1))>2),(N126-R126)*(IFERROR(INDEX('TaxCred&Subs'!$J$66:$J$99,MATCH(1,($C126&$D126='TaxCred&Subs'!$D$66:$D$99)*($F126='TaxCred&Subs'!$C$66:$C$99),0)),0)),IF($C126>2,(N126-R126)*(IFERROR(INDEX('TaxCred&Subs'!$J$66:$J$99,MATCH(1,($C126&$D126='TaxCred&Subs'!$D$66:$D$99)*($F126='TaxCred&Subs'!$C$66:$C$99),0)),0)),0))),0)} -> 150 | Q126: {=ROUND(IF(AND($C126=2,VALUE(RIGHT($AD126,1))>2),(O126-S126)*(IFERROR(INDEX('TaxCred&Subs'!$J$66:$J$99,MATCH(1,($C126&$D126='TaxCred&Subs'!$E$66:$E$99)*($F126='TaxCred&Subs'!$C$66:$C$99),0)),0)),IF(AND($C126=1,VALUE(RIGHT($AD126,1))>2),(O126-S126)*(IFERROR(INDEX('TaxCred&Subs'!$J$66:$J$99,MATCH(1,($C126&$D126='TaxCred&Subs'!$D$66:$D$99)*($F126='TaxCred&Subs'!$C$66:$C$99),0)),0)),IF($C126>2,(O126-S126)*(IFERROR(INDEX('TaxCred&Subs'!$J$66:$J$99,MATCH(1,($C126&$D126='TaxCred&Subs'!$D$66:$D$99)*($F126='TaxCred&Subs'!$C$66:$C$99),0)),0)),0))),0)} -> 0 | R126: {=ROUND(IF(IFERROR(VALUE(RIGHT($AD126,1)),0)>2,IF($C126=8,N126*IFERROR(INDEX('TaxCred&Subs'!$K$139:$S$151,MATCH($C126&$D126&LEFT($AD126,7),'TaxCred&Subs'!$E$139:$E$151,0),MATCH($H126,'TaxCred&Subs'!$K$137:$S$137,0)),0),IF($C126=2,N126*IFERROR(INDEX('TaxCred&Subs'!$K$139:$S$151,MATCH($C126&$D126,'TaxCred&Subs'!$D$139:$D$151,0),MATCH($H126,'TaxCred&Subs'!$K$137:$S$137,0)),0),N126*IFERROR(INDEX('TaxCred&Subs'!$K$139:$S$151,MATCH($C126&$D126,'TaxCred&Subs'!$C$139:$C$151,0),MATCH($H126,'TaxCred&Subs'!$K$137:$S$137,0)),0))),0),0)} -> 178 | S126: {=ROUND(IF(IFERROR(VALUE(RIGHT($AD126,1)),0)>2,IF($C126=8,O126*IFERROR(INDEX('TaxCred&Subs'!$K$139:$S$151,MATCH($C126&$D126&LEFT($AD126,7),'TaxCred&Subs'!$E$139:$E$151,0),MATCH($H126,'TaxCred&Subs'!$K$137:$S$137,0)),0),IF($C126=2,O126*IFERROR(INDEX('TaxCred&Subs'!$K$139:$S$151,MATCH($C126&$D126,'TaxCred&Subs'!$D$139:$D$151,0),MATCH($H126,'TaxCred&Subs'!$K$137:$S$137,0)),0),O126*IFERROR(INDEX('TaxCred&Subs'!$K$139:$S$151,MATCH($C126&$D126,'TaxCred&Subs'!$C$139:$C$151,0),MATCH($H126,'TaxCred&Subs'!$K$137:$S$137,0)),0))),0),0)} -> 57 | T126: =IF($H126=9,IF(R126>0,(N126-P126)*0.15,0),0) -> 0 | U126: =IF($H126=9,IF(S126>0,(O126-Q126)*0.15,0),0) -> 0 | V126: MATURE | W126: 2020 | X126: 1 | Y126: 0 | Z126: -0.00021540078 | AA126: -0.0033138581 | AB126: 0 | AC126: 0 | AD126: NG_FA4
B127: =B126+1 -> 103 | C127: 1 | D127: 3 | E127: 9 | F127: 2020 | G127: 2021 | H127: 9 | I127: 9 | J127: 0 | K127: 0 | L127: 0 | M127: 0.99 | N127: 4320 | O127: 1390 | P127: {=ROUND(IF($F127<='TaxCred&Subs'!$C$49,(IF($C127=2,IF($M127>=IFERROR(INDEX('TaxCred&Subs'!$L$12:$L$47,MATCH(1,($C127&$D127='TaxCred&Subs'!$E$12:$E$47)*($F127='TaxCred&Subs'!$C$12:$C$47),0) ),9999),IFERROR(INDEX('TaxCred&Subs'!$N$12:$N$47,MATCH(1,($C127&$D127='TaxCred&Subs'!$E$12:$E$47)*($F127='TaxCred&Subs'!$C$12:$C$47),0) ),0),0),(IF($M127>=IFERROR(INDEX('TaxCred&Subs'!$H$12:$H$47,MATCH(1,($C127&$D127='TaxCred&Subs'!$D$12:$D$47)*($F127='TaxCred&Subs'!$C$12:$C$47),0) ),9999),IFERROR(INDEX('TaxCred&Subs'!$N$12:$N$47,MATCH(1,($C127&$D127='TaxCred&Subs'!$D$12:$D$47)*($F127='TaxCred&Subs'!$C$12:$C$47),0) ),0),0)))),0)+IF(AND($C127=2,VALUE(RIGHT($AD127,1))>2),(N127-R127)*(IFERROR(INDEX('TaxCred&Subs'!$J$66:$J$99,MATCH(1,($C127&$D127='TaxCred&Subs'!$E$66:$E$99)*($F127='TaxCred&Subs'!$C$66:$C$99),0)),0)),IF(AND($C127=1,VALUE(RIGHT($AD127,1))>2),(N127-R127)*(IFERROR(INDEX('TaxCred&Subs'!$J$66:$J$99,MATCH(1,($C127&$D127='TaxCred&Subs'!$D$66:$D$99)*($F127='TaxCred&Subs'!$C$66:$C$99),0)),0)),IF($C127>2,(N127-R127)*(IFERROR(INDEX('TaxCred&Subs'!$J$66:$J$99,MATCH(1,($C127&$D127='TaxCred&Subs'!$D$66:$D$99)*($F127='TaxCred&Subs'!$C$66:$C$99),0)),0)),0))),0)} -> 150 | Q127: {=ROUND(IF(AND($C127=2,VALUE(RIGHT($AD127,1))>2),(O127-S127)*(IFERROR(INDEX('TaxCred&Subs'!$J$66:$J$99,MATCH(1,($C127&$D127='TaxCred&Subs'!$E$66:$E$99)*($F127='TaxCred&Subs'!$C$66:$C$99),0)),0)),IF(AND($C127=1,VALUE(RIGHT($AD127,1))>2),(O127-S127)*(IFERROR(INDEX('TaxCred&Subs'!$J$66:$J$99,MATCH(1,($C127&$D127='TaxCred&Subs'!$D$66:$D$99)*($F127='TaxCred&Subs'!$C$66:$C$99),0)),0)),IF($C127>2,(O127-S127)*(IFERROR(INDEX('TaxCred&Subs'!$J$66:$J$99,MATCH(1,($C127&$D127='TaxCred&Subs'!$D$66:$D$99)*($F127='TaxCred&Subs'!$C$66:$C$99),0)),0)),0))),0)} -> 0 | R127: {=ROUND(IF(IFERROR(VALUE(RIGHT($AD127,1)),0)>2,IF($C127=8,N127*IFERROR(INDEX('TaxCred&Subs'!$K$139:$S$151,MATCH($C127&$D127&LEFT($AD127,7),'TaxCred&Subs'!$E$139:$E$151,0),MATCH($H127,'TaxCred&Subs'!$K$137:$S$137,0)),0),IF($C127=2,N127*IFERROR(INDEX('TaxCred&Subs'!$K$139:$S$151,MATCH($C127&$D127,'TaxCred&Subs'!$D$139:$D$151,0),MATCH($H127,'TaxCred&Subs'!$K$137:$S$137,0)),0),N127*IFERROR(INDEX('TaxCred&Subs'!$K$139:$S$151,MATCH($C127&$D127,'TaxCred&Subs'!$C$139:$C$151,0),MATCH($H127,'TaxCred&Subs'!$K$137:$S$137,0)),0))),0),0)} -> 653 | S127: {=ROUND(IF(IFERROR(VALUE(RIGHT($AD127,1)),0)>2,IF($C127=8,O127*IFERROR(INDEX('TaxCred&Subs'!$K$139:$S$151,MATCH($C127&$D127&LEFT($AD127,7),'TaxCred&Subs'!$E$139:$E$151,0),MATCH($H127,'TaxCred&Subs'!$K$137:$S$137,0)),0),IF($C127=2,O127*IFERROR(INDEX('TaxCred&Subs'!$K$139:$S$151,MATCH($C127&$D127,'TaxCred&Subs'!$D$139:$D$151,0),MATCH($H127,'TaxCred&Subs'!$K$137:$S$137,0)),0),O127*IFERROR(INDEX('TaxCred&Subs'!$K$139:$S$151,MATCH($C127&$D127,'TaxCred&Subs'!$C$139:$C$151,0),MATCH($H127,'TaxCred&Subs'!$K$137:$S$137,0)),0))),0),0)} -> 210 | T127: =IF($H127=9,IF(R127>0,(N127-P127)*0.15,0),0) -> 625.5 | U127: =IF($H127=9,IF(S127>0,(O127-Q127)*0.15,0),0) -> 208.5 | V127: MATURE | W127: 2020 | X127: 1 | Y127: 0 | Z127: -0.00021540078 | AA127: -0.0033138581 | AB127: 0 | AC127: 0 | AD127: NG_FA4
B128: =B127+1 -> 104 | C128: 1 | D128: 3 | E128: 9 | F128: 2022 | G128: 2032 | H128: 1 | I128: 9 | J128: 0 | K128: 0 | L128: 0 | M128: 0.99 | N128: 4320 | O128: 1390 | P128: {=ROUND(IF($F128<='TaxCred&Subs'!$C$49,(IF($C128=2,IF($M128>=IFERROR(INDEX('TaxCred&Subs'!$L$12:$L$47,MATCH(1,($C128&$D128='TaxCred&Subs'!$E$12:$E$47)*($F128='TaxCred&Subs'!$C$12:$C$47),0) ),9999),IFERROR(INDEX('TaxCred&Subs'!$N$12:$N$47,MATCH(1,($C128&$D128='TaxCred&Subs'!$E$12:$E$47)*($F128='TaxCred&Subs'!$C$12:$C$47),0) ),0),0),(IF($M128>=IFERROR(INDEX('TaxCred&Subs'!$H$12:$H$47,MATCH(1,($C128&$D128='TaxCred&Subs'!$D$12:$D$47)*($F128='TaxCred&Subs'!$C$12:$C$47),0) ),9999),IFERROR(INDEX('TaxCred&Subs'!$N$12:$N$47,MATCH(1,($C128&$D128='TaxCred&Subs'!$D$12:$D$47)*($F128='TaxCred&Subs'!$C$12:$C$47),0) ),0),0)))),0)+IF(AND($C128=2,VALUE(RIGHT($AD128,1))>2),(N128-R128)*(IFERROR(INDEX('TaxCred&Subs'!$J$66:$J$99,MATCH(1,($C128&$D128='TaxCred&Subs'!$E$66:$E$99)*($F128='TaxCred&Subs'!$C$66:$C$99),0)),0)),IF(AND($C128=1,VALUE(RIGHT($AD128,1))>2),(N128-R128)*(IFERROR(INDEX('TaxCred&Subs'!$J$66:$J$99,MATCH(1,($C128&$D128='TaxCred&Subs'!$D$66:$D$99)*($F128='TaxCred&Subs'!$C$66:$C$99),0)),0)),IF($C128>2,(N128-R128)*(IFERROR(INDEX('TaxCred&Subs'!$J$66:$J$99,MATCH(1,($C128&$D128='TaxCred&Subs'!$D$66:$D$99)*($F128='TaxCred&Subs'!$C$66:$C$99),0)),0)),0))),0)} -> 600 | Q128: {=ROUND(IF(AND($C128=2,VALUE(RIGHT($AD128,1))>2),(O128-S128)*(IFERROR(INDEX('TaxCred&Subs'!$J$66:$J$99,MATCH(1,($C128&$D128='TaxCred&Subs'!$E$66:$E$99)*($F128='TaxCred&Subs'!$C$66:$C$99),0)),0)),IF(AND($C128=1,VALUE(RIGHT($AD128,1))>2),(O128-S128)*(IFERROR(INDEX('TaxCred&Subs'!$J$66:$J$99,MATCH(1,($C128&$D128='TaxCred&Subs'!$D$66:$D$99)*($F128='TaxCred&Subs'!$C$66:$C$99),0)),0)),IF($C128>2,(O128-S128)*(IFERROR(INDEX('TaxCred&Subs'!$J$66:$J$99,MATCH(1,($C128&$D128='TaxCred&Subs'!$D$66:$D$99)*($F128='TaxCred&Subs'!$C$66:$C$99),0)),0)),0))),0)} -> 0 | R128: {=ROUND(IF(IFERROR(VALUE(RIGHT($AD128,1)),0)>2,IF($C128=8,N128*IFERROR(INDEX('TaxCred&Subs'!$K$139:$S$151,MATCH($C128&$D128&LEFT($AD128,7),'TaxCred&Subs'!$E$139:$E$151,0),MATCH($H128,'TaxCred&Subs'!$K$137:$S$137,0)),0),IF($C128=2,N128*IFERROR(INDEX('TaxCred&Subs'!$K$139:$S$151,MATCH($C128&$D128,'TaxCred&Subs'!$D$139:$D$151,0),MATCH($H128,'TaxCred&Subs'!$K$137:$S$137,0)),0),N128*IFERROR(INDEX('TaxCred&Subs'!$K$139:$S$151,MATCH($C128&$D128,'TaxCred&Subs'!$C$139:$C$151,0),MATCH($H128,'TaxCred&Subs'!$K$137:$S$137,0)),0))),0),0)} -> 417 | S128: {=ROUND(IF(IFERROR(VALUE(RIGHT($AD128,1)),0)>2,IF($C128=8,O128*IFERROR(INDEX('TaxCred&Subs'!$K$139:$S$151,MATCH($C128&$D128&LEFT($AD128,7),'TaxCred&Subs'!$E$139:$E$151,0),MATCH($H128,'TaxCred&Subs'!$K$137:$S$137,0)),0),IF($C128=2,O128*IFERROR(INDEX('TaxCred&Subs'!$K$139:$S$151,MATCH($C128&$D128,'TaxCred&Subs'!$D$139:$D$151,0),MATCH($H128,'TaxCred&Subs'!$K$137:$S$137,0)),0),O128*IFERROR(INDEX('TaxCred&Subs'!$K$139:$S$151,MATCH($C128&$D128,'TaxCred&Subs'!$C$139:$C$151,0),MATCH($H128,'TaxCred&Subs'!$K$137:$S$137,0)),0))),0),0)} -> 134 | T128: =IF($H128=9,IF(R128>0,(N128-P128)*0.15,0),0) -> 0 | U128: =IF($H128=9,IF(S128>0,(O128-Q128)*0.15,0),0) -> 0 | V128: MATURE | W128: 2020 | X128: 1 | Y128: 0 | Z128: -0.00021540078 | AA128: -0.0033138581 | AB128: 0 | AC128: 0 | AD128: NG_FA4
B129: =B128+1 -> 105 | C129: 1 | D129: 3 | E129: 9 | F129: 2022 | G129: 2032 | H129: 2 | I129: 9 | J129: 0 | K129: 0 | L129: 0 | M129: 0.99 | N129: 4320 | O129: 1390 | P129: {=ROUND(IF($F129<='TaxCred&Subs'!$C$49,(IF($C129=2,IF($M129>=IFERROR(INDEX('TaxCred&Subs'!$L$12:$L$47,MATCH(1,($C129&$D129='TaxCred&Subs'!$E$12:$E$47)*($F129='TaxCred&Subs'!$C$12:$C$47),0) ),9999),IFERROR(INDEX('TaxCred&Subs'!$N$12:$N$47,MATCH(1,($C129&$D129='TaxCred&Subs'!$E$12:$E$47)*($F129='TaxCred&Subs'!$C$12:$C$47),0) ),0),0),(IF($M129>=IFERROR(INDEX('TaxCred&Subs'!$H$12:$H$47,MATCH(1,($C129&$D129='TaxCred&Subs'!$D$12:$D$47)*($F129='TaxCred&Subs'!$C$12:$C$47),0) ),9999),IFERROR(INDEX('TaxCred&Subs'!$N$12:$N$47,MATCH(1,($C129&$D129='TaxCred&Subs'!$D$12:$D$47)*($F129='TaxCred&Subs'!$C$12:$C$47),0) ),0),0)))),0)+IF(AND($C129=2,VALUE(RIGHT($AD129,1))>2),(N129-R129)*(IFERROR(INDEX('TaxCred&Subs'!$J$66:$J$99,MATCH(1,($C129&$D129='TaxCred&Subs'!$E$66:$E$99)*($F129='TaxCred&Subs'!$C$66:$C$99),0)),0)),IF(AND($C129=1,VALUE(RIGHT($AD129,1))>2),(N129-R129)*(IFERROR(INDEX('TaxCred&Subs'!$J$66:$J$99,MATCH(1,($C129&$D129='TaxCred&Subs'!$D$66:$D$99)*($F129='TaxCred&Subs'!$C$66:$C$99),0)),0)),IF($C129>2,(N129-R129)*(IFERROR(INDEX('TaxCred&Subs'!$J$66:$J$99,MATCH(1,($C129&$D129='TaxCred&Subs'!$D$66:$D$99)*($F129='TaxCred&Subs'!$C$66:$C$99),0)),0)),0))),0)} -> 600 | Q129: {=ROUND(IF(AND($C129=2,VALUE(RIGHT($AD129,1))>2),(O129-S129)*(IFERROR(INDEX('TaxCred&Subs'!$J$66:$J$99,MATCH(1,($C129&$D129='TaxCred&Subs'!$E$66:$E$99)*($F129='TaxCred&Subs'!$C$66:$C$99),0)),0)),IF(AND($C129=1,VALUE(RIGHT($AD129,1))>2),(O129-S129)*(IFERROR(INDEX('TaxCred&Subs'!$J$66:$J$99,MATCH(1,($C129&$D129='TaxCred&Subs'!$D$66:$D$99)*($F129='TaxCred&Subs'!$C$66:$C$99),0)),0)),IF($C129>2,(O129-S129)*(IFERROR(INDEX('TaxCred&Subs'!$J$66:$J$99,MATCH(1,($C129&$D129='TaxCred&Subs'!$D$66:$D$99)*($F129='TaxCred&Subs'!$C$66:$C$99),0)),0)),0))),0)} -> 0 | R129: {=ROUND(IF(IFERROR(VALUE(RIGHT($AD129,1)),0)>2,IF($C129=8,N129*IFERROR(INDEX('TaxCred&Subs'!$K$139:$S$151,MATCH($C129&$D129&LEFT($AD129,7),'TaxCred&Subs'!$E$139:$E$151,0),MATCH($H129,'TaxCred&Subs'!$K$137:$S$137,0)),0),IF($C129=2,N129*IFERROR(INDEX('TaxCred&Subs'!$K$139:$S$151,MATCH($C129&$D129,'TaxCred&Subs'!$D$139:$D$151,0),MATCH($H129,'TaxCred&Subs'!$K$137:$S$137,0)),0),N129*IFERROR(INDEX('TaxCred&Subs'!$K$139:$S$151,MATCH($C129&$D129,'TaxCred&Subs'!$C$139:$C$151,0),MATCH($H129,'TaxCred&Subs'!$K$137:$S$137,0)),0))),0),0)} -> 518 | S129: {=ROUND(IF(IFERROR(VALUE(RIGHT($AD129,1)),0)>2,IF($C129=8,O129*IFERROR(INDEX('TaxCred&Subs'!$K$139:$S$151,MATCH($C129&$D129&LEFT($AD129,7),'TaxCred&Subs'!$E$139:$E$151,0),MATCH($H129,'TaxCred&Subs'!$K$137:$S$137,0)),0),IF($C129=2,O129*IFERROR(INDEX('TaxCred&Subs'!$K$139:$S$151,MATCH($C129&$D129,'TaxCred&Subs'!$D$139:$D$151,0),MATCH($H129,'TaxCred&Subs'!$K$137:$S$137,0)),0),O129*IFERROR(INDEX('TaxCred&Subs'!$K$139:$S$151,MATCH($C129&$D129,'TaxCred&Subs'!$C$139:$C$151,0),MATCH($H129,'TaxCred&Subs'!$K$137:$S$137,0)),0))),0),0)} -> 167 | T129: =IF($H129=9,IF(R129>0,(N129-P129)*0.15,0),0) -> 0 | U129: =IF($H129=9,IF(S129>0,(O129-Q129)*0.15,0),0) -> 0 | V129: MATURE | W129: 2020 | X129: 1 | Y129: 0 | Z129: -0.00021540078 | AA129: -0.0033138581 | AB129: 0 | AC129: 0 | AD129: NG_FA4
B130: =B129+1 -> 106 | C130: 1 | D130: 3 | E130: 9 | F130: 2022 | G130: 2032 | H130: 3 | I130: 9 | J130: 0 | K130: 0 | L130: 0 | M130: 0.99 | N130: 4320 | O130: 1390 | P130: {=ROUND(IF($F130<='TaxCred&Subs'!$C$49,(IF($C130=2,IF($M130>=IFERROR(INDEX('TaxCred&Subs'!$L$12:$L$47,MATCH(1,($C130&$D130='TaxCred&Subs'!$E$12:$E$47)*($F130='TaxCred&Subs'!$C$12:$C$47),0) ),9999),IFERROR(INDEX('TaxCred&Subs'!$N$12:$N$47,MATCH(1,($C130&$D130='TaxCred&Subs'!$E$12:$E$47)*($F130='TaxCred&Subs'!$C$12:$C$47),0) ),0),0),(IF($M130>=IFERROR(INDEX('TaxCred&Subs'!$H$12:$H$47,MATCH(1,($C130&$D130='TaxCred&Subs'!$D$12:$D$47)*($F130='TaxCred&Subs'!$C$12:$C$47),0) ),9999),IFERROR(INDEX('TaxCred&Subs'!$N$12:$N$47,MATCH(1,($C130&$D130='TaxCred&Subs'!$D$12:$D$47)*($F130='TaxCred&Subs'!$C$12:$C$47),0) ),0),0)))),0)+IF(AND($C130=2,VALUE(RIGHT($AD130,1))>2),(N130-R130)*(IFERROR(INDEX('TaxCred&Subs'!$J$66:$J$99,MATCH(1,($C130&$D130='TaxCred&Subs'!$E$66:$E$99)*($F130='TaxCred&Subs'!$C$66:$C$99),0)),0)),IF(AND($C130=1,VALUE(RIGHT($AD130,1))>2),(N130-R130)*(IFERROR(INDEX('TaxCred&Subs'!$J$66:$J$99,MATCH(1,($C130&$D130='TaxCred&Subs'!$D$66:$D$99)*($F130='TaxCred&Subs'!$C$66:$C$99),0)),0)),IF($C130>2,(N130-R130)*(IFERROR(INDEX('TaxCred&Subs'!$J$66:$J$99,MATCH(1,($C130&$D130='TaxCred&Subs'!$D$66:$D$99)*($F130='TaxCred&Subs'!$C$66:$C$99),0)),0)),0))),0)} -> 600 | Q130: {=ROUND(IF(AND($C130=2,VALUE(RIGHT($AD130,1))>2),(O130-S130)*(IFERROR(INDEX('TaxCred&Subs'!$J$66:$J$99,MATCH(1,($C130&$D130='TaxCred&Subs'!$E$66:$E$99)*($F130='TaxCred&Subs'!$C$66:$C$99),0)),0)),IF(AND($C130=1,VALUE(RIGHT($AD130,1))>2),(O130-S130)*(IFERROR(INDEX('TaxCred&Subs'!$J$66:$J$99,MATCH(1,($C130&$D130='TaxCred&Subs'!$D$66:$D$99)*($F130='TaxCred&Subs'!$C$66:$C$99),0)),0)),IF($C130>2,(O130-S130)*(IFERROR(INDEX('TaxCred&Subs'!$J$66:$J$99,MATCH(1,($C130&$D130='TaxCred&Subs'!$D$66:$D$99)*($F130='TaxCred&Subs'!$C$66:$C$99),0)),0)),0))),0)} -> 0 | R130: {=ROUND(IF(IFERROR(VALUE(RIGHT($AD130,1)),0)>2,IF($C130=8,N130*IFERROR(INDEX('TaxCred&Subs'!$K$139:$S$151,MATCH($C130&$D130&LEFT($AD130,7),'TaxCred&Subs'!$E$139:$E$151,0),MATCH($H130,'TaxCred&Subs'!$K$137:$S$137,0)),0),IF($C130=2,N130*IFERROR(INDEX('TaxCred&Subs'!$K$139:$S$151,MATCH($C130&$D130,'TaxCred&Subs'!$D$139:$D$151,0),MATCH($H130,'TaxCred&Subs'!$K$137:$S$137,0)),0),N130*IFERROR(INDEX('TaxCred&Subs'!$K$139:$S$151,MATCH($C130&$D130,'TaxCred&Subs'!$C$139:$C$151,0),MATCH($H130,'TaxCred&Subs'!$K$137:$S$137,0)),0))),0),0)} -> 225 | S130: {=ROUND(IF(IFERROR(VALUE(RIGHT($AD130,1)),0)>2,IF($C130=8,O130*IFERROR(INDEX('TaxCred&Subs'!$K$139:$S$151,MATCH($C130&$D130&LEFT($AD130,7),'TaxCred&Subs'!$E$139:$E$151,0),MATCH($H130,'TaxCred&Subs'!$K$137:$S$137,0)),0),IF($C130=2,O130*IFERROR(INDEX('TaxCred&Subs'!$K$139:$S$151,MATCH($C130&$D130,'TaxCred&Subs'!$D$139:$D$151,0),MATCH($H130,'TaxCred&Subs'!$K$137:$S$137,0)),0),O130*IFERROR(INDEX('TaxCred&Subs'!$K$139:$S$151,MATCH($C130&$D130,'TaxCred&Subs'!$C$139:$C$151,0),MATCH($H130,'TaxCred&Subs'!$K$137:$S$137,0)),0))),0),0)} -> 72 | T130: =IF($H130=9,IF(R130>0,(N130-P130)*0.15,0),0) -> 0 | U130: =IF($H130=9,IF(S130>0,(O130-Q130)*0.15,0),0) -> 0 | V130: MATURE | W130: 2020 | X130: 1 | Y130: 0 | Z130: -0.00021540078 | AA130: -0.0033138581 | AB130: 0 | AC130: 0 | AD130: NG_FA4
... B183: =B182+1 -> 159 | C183: 1 | D183: 4 | E183: 13 | F183: 2033 | G183: 2050 | H183: 9 | I183: 13 | J183: 0 | K183: 0 | L183: 0 | M183: 0.96 | N183: 6710 | O183: 3670 | P183: {=ROUND(IF($F183<='TaxCred&Subs'!$C$49,(IF($C183=2,IF($M183>=IFERROR(INDEX('TaxCred&Subs'!$L$12:$L$47,MATCH(1,($C183&$D183='TaxCred&Subs'!$E$12:$E$47)*($F183='TaxCred&Subs'!$C$12:$C$47),0) ),9999),IFERROR(INDEX('TaxCred&Subs'!$N$12:$N$47,MATCH(1,($C183&$D183='TaxCred&Subs'!$E$12:$E$47)*($F183='TaxCred&Subs'!$C$12:$C$47),0) ),0),0),(IF($M183>=IFERROR(INDEX('TaxCred&Subs'!$H$12:$H$47,MATCH(1,($C183&$D183='TaxCred&Subs'!$D$12:$D$47)*($F183='TaxCred&Subs'!$C$12:$C$47),0) ),9999),IFERROR(INDEX('TaxCred&Subs'!$N$12:$N$47,MATCH(1,($C183&$D183='TaxCred&Subs'!$D$12:$D$47)*($F183='TaxCred&Subs'!$C$12:$C$47),0) ),0),0)))),0)+IF(AND($C183=2,VALUE(RIGHT($AD183,1))>2),(N183-R183)*(IFERROR(INDEX('TaxCred&Subs'!$J$66:$J$99,MATCH(1,($C183&$D183='TaxCred&Subs'!$E$66:$E$99)*($F183='TaxCred&Subs'!$C$66:$C$99),0)),0)),IF(AND($C183=1,VALUE(RIGHT($AD183,1))>2),(N183-R183)*(IFERROR(INDEX('TaxCred&Subs'!$J$66:$J$99,MATCH(1,($C183&$D183='TaxCred&Subs'!$D$66:$D$99)*($F183='TaxCred&Subs'!$C$66:$C$99),0)),0)),IF($C183>2,(N183-R183)*(IFERROR(INDEX('TaxCred&Subs'!$J$66:$J$99,MATCH(1,($C183&$D183='TaxCred&Subs'!$D$66:$D$99)*($F183='TaxCred&Subs'!$C$66:$C$99),0)),0)),0))),0)} -> 0 | Q183: {=ROUND(IF(AND($C183=2,VALUE(RIGHT($AD183,1))>2),(O183-S183)*(IFERROR(INDEX('TaxCred&Subs'!$J$66:$J$99,MATCH(1,($C183&$D183='TaxCred&Subs'!$E$66:$E$99)*($F183='TaxCred&Subs'!$C$66:$C$99),0)),0)),IF(AND($C183=1,VALUE(RIGHT($AD183,1))>2),(O183-S183)*(IFERROR(INDEX('TaxCred&Subs'!$J$66:$J$99,MATCH(1,($C183&$D183='TaxCred&Subs'!$D$66:$D$99)*($F183='TaxCred&Subs'!$C$66:$C$99),0)),0)),IF($C183>2,(O183-S183)*(IFERROR(INDEX('TaxCred&Subs'!$J$66:$J$99,MATCH(1,($C183&$D183='TaxCred&Subs'!$D$66:$D$99)*($F183='TaxCred&Subs'!$C$66:$C$99),0)),0)),0))),0)} -> 0 | R183: {=ROUND(IF(IFERROR(VALUE(RIGHT($AD183,1)),0)>2,IF($C183=8,N183*IFERROR(INDEX('TaxCred&Subs'!$K$139:$S$151,MATCH($C183&$D183&LEFT($AD183,7),'TaxCred&Subs'!$E$139:$E$151,0),MATCH($H183,'TaxCred&Subs'!$K$137:$S$137,0)),0),IF($C183=2,N183*IFERROR(INDEX('TaxCred&Subs'!$K$139:$S$151,MATCH($C183&$D183,'TaxCred&Subs'!$D$139:$D$151,0),MATCH($H183,'TaxCred&Subs'!$K$137:$S$137,0)),0),N183*IFERROR(INDEX('TaxCred&Subs'!$K$139:$S$151,MATCH($C183&$D183,'TaxCred&Subs'!$C$139:$C$151,0),MATCH($H183,'TaxCred&Subs'!$K$137:$S$137,0)),0))),0),0)} -> 75 | S183: {=ROUND(IF(IFERROR(VALUE(RIGHT($AD183,1)),0)>2,IF($C183=8,O183*IFERROR(INDEX('TaxCred&Subs'!$K$139:$S$151,MATCH($C183&$D183&LEFT($AD183,7),'TaxCred&Subs'!$E$139:$E$151,0),MATCH($H183,'TaxCred&Subs'!$K$137:$S$137,0)),0),IF($C183=2,O183*IFERROR(INDEX('TaxCred&Subs'!$K$139:$S$151,MATCH($C183&$D183,'TaxCred&Subs'!$D$139:$D$151,0),MATCH($H183,'TaxCred&Subs'!$K$137:$S$137,0)),0),O183*IFERROR(INDEX('TaxCred&Subs'!$K$139:$S$151,MATCH($C183&$D183,'TaxCred&Subs'!$C$139:$C$151,0),MATCH($H183,'TaxCred&Subs'!$K$137:$S$137,0)),0))),0),0)} -> 41 | T183: =IF($H183=9,IF(R183>0,(N183-P183)*0.15,0),0) -> 1006.5 | U183: =IF($H183=9,IF(S183>0,(O183-Q183)*0.15,0),0) -> 550.5 | V183: MATURE | W183: 2020 | X183: 1 | Y183: 0 | Z183: -0.00021453722 | AA183: -0.0033005726 | AB183: 0 | AC183: 0 | AD183: NG_RAD4
B184: =B183+1 -> 160 | C184: 1 | D184: 5 | E184: 14 | F184: 2020 | G184: 2050 | H184: 11 | I184: 14 | J184: 0 | K184: 0 | L184: 0 | M184: 0.83 | N184: 4885 | O184: 3035 | P184: {=ROUND(IF($F184<='TaxCred&Subs'!$C$49,(IF($C184=2,IF($M184>=IFERROR(INDEX('TaxCred&Subs'!$L$12:$L$47,MATCH(1,($C184&$D184='TaxCred&Subs'!$E$12:$E$47)*($F184='TaxCred&Subs'!$C$12:$C$47),0) ),9999),IFERROR(INDEX('TaxCred&Subs'!$N$12:$N$47,MATCH(1,($C184&$D184='TaxCred&Subs'!$E$12:$E$47)*($F184='TaxCred&Subs'!$C$12:$C$47),0) ),0),0),(IF($M184>=IFERROR(INDEX('TaxCred&Subs'!$H$12:$H$47,MATCH(1,($C184&$D184='TaxCred&Subs'!$D$12:$D$47)*($F184='TaxCred&Subs'!$C$12:$C$47),0) ),9999),IFERROR(INDEX('TaxCred&Subs'!$N$12:$N$47,MATCH(1,($C184&$D184='TaxCred&Subs'!$D$12:$D$47)*($F184='TaxCred&Subs'!$C$12:$C$47),0) ),0),0)))),0)+IF(AND($C184=2,VALUE(RIGHT($AD184,1))>2),(N184-R184)*(IFERROR(INDEX('TaxCred&Subs'!$J$66:$J$99,MATCH(1,($C184&$D184='TaxCred&Subs'!$E$66:$E$99)*($F184='TaxCred&Subs'!$C$66:$C$99),0)),0)),IF(AND($C184=1,VALUE(RIGHT($AD184,1))>2),(N184-R184)*(IFERROR(INDEX('TaxCred&Subs'!$J$66:$J$99,MATCH(1,($C184&$D184='TaxCred&Subs'!$D$66:$D$99)*($F184='TaxCred&Subs'!$C$66:$C$99),0)),0)),IF($C184>2,(N184-R184)*(IFERROR(INDEX('TaxCred&Subs'!$J$66:$J$99,MATCH(1,($C184&$D184='TaxCred&Subs'!$D$66:$D$99)*($F184='TaxCred&Subs'!$C$66:$C$99),0)),0)),0))),0)} -> 0 | Q184: {=ROUND(IF(AND($C184=2,VALUE(RIGHT($AD184,1))>2),(O184-S184)*(IFERROR(INDEX('TaxCred&Subs'!$J$66:$J$99,MATCH(1,($C184&$D184='TaxCred&Subs'!$E$66:$E$99)*($F184='TaxCred&Subs'!$C$66:$C$99),0)),0)),IF(AND($C184=1,VALUE(RIGHT($AD184,1))>2),(O184-S184)*(IFERROR(INDEX('TaxCred&Subs'!$J$66:$J$99,MATCH(1,($C184&$D184='TaxCred&Subs'!$D$66:$D$99)*($F184='TaxCred&Subs'!$C$66:$C$99),0)),0)),IF($C184>2,(O184-S184)*(IFERROR(INDEX('TaxCred&Subs'!$J$66:$J$99,MATCH(1,($C184&$D184='TaxCred&Subs'!$D$66:$D$99)*($F184='TaxCred&Subs'!$C$66:$C$99),0)),0)),0))),0)} -> 0 | R184: {=ROUND(IF(IFERROR(VALUE(RIGHT($AD184,1)),0)>2,IF($C184=8,N184*IFERROR(INDEX('TaxCred&Subs'!$K$139:$S$151,MATCH($C184&$D184&LEFT($AD184,7),'TaxCred&Subs'!$E$139:$E$151,0),MATCH($H184,'TaxCred&Subs'!$K$137:$S$137,0)),0),IF($C184=2,N184*IFERROR(INDEX('TaxCred&Subs'!$K$139:$S$151,MATCH($C184&$D184,'TaxCred&Subs'!$D$139:$D$151,0),MATCH($H184,'TaxCred&Subs'!$K$137:$S$137,0)),0),N184*IFERROR(INDEX('TaxCred&Subs'!$K$139:$S$151,MATCH($C184&$D184,'TaxCred&Subs'!$C$139:$C$151,0),MATCH($H184,'TaxCred&Subs'!$K$137:$S$137,0)),0))),0),0)} -> 0 | S184: {=ROUND(IF(IFERROR(VALUE(RIGHT($AD184,1)),0)>2,IF($C184=8,O184*IFERROR(INDEX('TaxCred&Subs'!$K$139:$S$151,MATCH($C184&$D184&LEFT($AD184,7),'TaxCred&Subs'!$E$139:$E$151,0),MATCH($H184,'TaxCred&Subs'!$K$137:$S$137,0)),0),IF($C184=2,O184*IFERROR(INDEX('TaxCred&Subs'!$K$139:$S$151,MATCH($C184&$D184,'TaxCred&Subs'!$D$139:$D$151,0),MATCH($H184,'TaxCred&Subs'!$K$137:$S$137,0)),0),O184*IFERROR(INDEX('TaxCred&Subs'!$K$139:$S$151,MATCH($C184&$D184,'TaxCred&Subs'!$C$139:$C$151,0),MATCH($H184,'TaxCred&Subs'!$K$137:$S$137,0)),0))),0),0)} -> 0 | T184: =IF($H184=9,IF(R184>0,(N184-P184)*0.15,0),0) -> 0 | U184: =IF($H184=9,IF(S184>0,(O184-Q184)*0.15,0),0) -> 0 | V184: MATURE | W184: 2020 | X184: 1 | Y184: 0 | Z184: -0.00016333453 | AA184: -0.002512839 | AB184: 0 | AC184: 0 | AD184: KERO_FA1 | AE184: Kerosene equipment is now assumed to be included with distillate fuel oil
B185: =B184+1 -> 161 | C185: 1 | D185: 5 | E185: 15 | F185: 2020 | G185: 2050 | H185: 11 | I185: 15 | J185: 0 | K185: 0 | L185: 0 | M185: 0.85487 | N185: 5150 | O185: 3070 | P185: {=ROUND(IF($F185<='TaxCred&Subs'!$C$49,(IF($C185=2,IF($M185>=IFERROR(INDEX('TaxCred&Subs'!$L$12:$L$47,MATCH(1,($C185&$D185='TaxCred&Subs'!$E$12:$E$47)*($F185='TaxCred&Subs'!$C$12:$C$47),0) ),9999),IFERROR(INDEX('TaxCred&Subs'!$N$12:$N$47,MATCH(1,($C185&$D185='TaxCred&Subs'!$E$12:$E$47)*($F185='TaxCred&Subs'!$C$12:$C$47),0) ),0),0),(IF($M185>=IFERROR(INDEX('TaxCred&Subs'!$H$12:$H$47,MATCH(1,($C185&$D185='TaxCred&Subs'!$D$12:$D$47)*($F185='TaxCred&Subs'!$C$12:$C$47),0) ),9999),IFERROR(INDEX('TaxCred&Subs'!$N$12:$N$47,MATCH(1,($C185&$D185='TaxCred&Subs'!$D$12:$D$47)*($F185='TaxCred&Subs'!$C$12:$C$47),0) ),0),0)))),0)+IF(AND($C185=2,VALUE(RIGHT($AD185,1))>2),(N185-R185)*(IFERROR(INDEX('TaxCred&Subs'!$J$66:$J$99,MATCH(1,($C185&$D185='TaxCred&Subs'!$E$66:$E$99)*($F185='TaxCred&Subs'!$C$66:$C$99),0)),0)),IF(AND($C185=1,VALUE(RIGHT($AD185,1))>2),(N185-R185)*(IFERROR(INDEX('TaxCred&Subs'!$J$66:$J$99,MATCH(1,($C185&$D185='TaxCred&Subs'!$D$66:$D$99)*($F185='TaxCred&Subs'!$C$66:$C$99),0)),0)),IF($C185>2,(N185-R185)*(IFERROR(INDEX('TaxCred&Subs'!$J$66:$J$99,MATCH(1,($C185&$D185='TaxCred&Subs'!$D$66:$D$99)*($F185='TaxCred&Subs'!$C$66:$C$99),0)),0)),0))),0)} -> 150 | Q185: {=ROUND(IF(AND($C185=2,VALUE(RIGHT($AD185,1))>2),(O185-S185)*(IFERROR(INDEX('TaxCred&Subs'!$J$66:$J$99,MATCH(1,($C185&$D185='TaxCred&Subs'!$E$66:$E$99)*($F185='TaxCred&Subs'!$C$66:$C$99),0)),0)),IF(AND($C185=1,VALUE(RIGHT($AD185,1))>2),(O185-S185)*(IFERROR(INDEX('TaxCred&Subs'!$J$66:$J$99,MATCH(1,($C185&$D185='TaxCred&Subs'!$D$66:$D$99)*($F185='TaxCred&Subs'!$C$66:$C$99),0)),0)),IF($C185>2,(O185-S185)*(IFERROR(INDEX('TaxCred&Subs'!$J$66:$J$99,MATCH(1,($C185&$D185='TaxCred&Subs'!$D$66:$D$99)*($F185='TaxCred&Subs'!$C$66:$C$99),0)),0)),0))),0)} -> 0 | R185: {=ROUND(IF(IFERROR(VALUE(RIGHT($AD185,1)),0)>2,IF($C185=8,N185*IFERROR(INDEX('TaxCred&Subs'!$K$139:$S$151,MATCH($C185&$D185&LEFT($AD185,7),'TaxCred&Subs'!$E$139:$E$151,0),MATCH($H185,'TaxCred&Subs'!$K$137:$S$137,0)),0),IF($C185=2,N185*IFERROR(INDEX('TaxCred&Subs'!$K$139:$S$151,MATCH($C185&$D185,'TaxCred&Subs'!$D$139:$D$151,0),MATCH($H185,'TaxCred&Subs'!$K$137:$S$137,0)),0),N185*IFERROR(INDEX('TaxCred&Subs'!$K$139:$S$151,MATCH($C185&$D185,'TaxCred&Subs'!$C$139:$C$151,0),MATCH($H185,'TaxCred&Subs'!$K$137:$S$137,0)),0))),0),0)} -> 0 | S185: {=ROUND(IF(IFERROR(VALUE(RIGHT($AD185,1)),0)>2,IF($C185=8,O185*IFERROR(INDEX('TaxCred&Subs'!$K$139:$S$151,MATCH($C185&$D185&LEFT($AD185,7),'TaxCred&Subs'!$E$139:$E$151,0),MATCH($H185,'TaxCred&Subs'!$K$137:$S$137,0)),0),IF($C185=2,O185*IFERROR(INDEX('TaxCred&Subs'!$K$139:$S$151,MATCH($C185&$D185,'TaxCred&Subs'!$D$139:$D$151,0),MATCH($H185,'TaxCred&Subs'!$K$137:$S$137,0)),0),O185*IFERROR(INDEX('TaxCred&Subs'!$K$139:$S$151,MATCH($C185&$D185,'TaxCred&Subs'!$C$139:$C$151,0),MATCH($H185,'TaxCred&Subs'!$K$137:$S$137,0)),0))),0),0)} -> 0 | T185: =IF($H185=9,IF(R185>0,(N185-P185)*0.15,0),0) -> 0 | U185: =IF($H185=9,IF(S185>0,(O185-Q185)*0.15,0),0) -> 0 | V185: MATURE | W185: 2020 | X185: 1 | Y185: 0 | Z185: -0.00016333453 | AA185: -0.002512839 | AB185: 0 | AC185: 0 | AD185: KERO_FA2 | AE185: Kerosene equipment is now assumed to be included with distillate fuel oil
B186: =B185+1 -> 162 | C186: 1 | D186: 5 | E186: 16 | F186: 2020 | G186: 2022 | H186: 11 | I186: 16 | J186: 0 | K186: 0 | L186: 0 | M186: 0.85 | N186: 5150 | O186: 3070 | P186: {=ROUND(IF($F186<='TaxCred&Subs'!$C$49,(IF($C186=2,IF($M186>=IFERROR(INDEX('TaxCred&Subs'!$L$12:$L$47,MATCH(1,($C186&$D186='TaxCred&Subs'!$E$12:$E$47)*($F186='TaxCred&Subs'!$C$12:$C$47),0) ),9999),IFERROR(INDEX('TaxCred&Subs'!$N$12:$N$47,MATCH(1,($C186&$D186='TaxCred&Subs'!$E$12:$E$47)*($F186='TaxCred&Subs'!$C$12:$C$47),0) ),0),0),(IF($M186>=IFERROR(INDEX('TaxCred&Subs'!$H$12:$H$47,MATCH(1,($C186&$D186='TaxCred&Subs'!$D$12:$D$47)*($F186='TaxCred&Subs'!$C$12:$C$47),0) ),9999),IFERROR(INDEX('TaxCred&Subs'!$N$12:$N$47,MATCH(1,($C186&$D186='TaxCred&Subs'!$D$12:$D$47)*($F186='TaxCred&Subs'!$C$12:$C$47),0) ),0),0)))),0)+IF(AND($C186=2,VALUE(RIGHT($AD186,1))>2),(N186-R186)*(IFERROR(INDEX('TaxCred&Subs'!$J$66:$J$99,MATCH(1,($C186&$D186='TaxCred&Subs'!$E$66:$E$99)*($F186='TaxCred&Subs'!$C$66:$C$99),0)),0)),IF(AND($C186=1,VALUE(RIGHT($AD186,1))>2),(N186-R186)*(IFERROR(INDEX('TaxCred&Subs'!$J$66:$J$99,MATCH(1,($C186&$D186='TaxCred&Subs'!$D$66:$D$99)*($F186='TaxCred&Subs'!$C$66:$C$99),0)),0)),IF($C186>2,(N186-R186)*(IFERROR(INDEX('TaxCred&Subs'!$J$66:$J$99,MATCH(1,($C186&$D186='TaxCred&Subs'!$D$66:$D$99)*($F186='TaxCred&Subs'!$C$66:$C$99),0)),0)),0))),0)} -> 150 | Q186: {=ROUND(IF(AND($C186=2,VALUE(RIGHT($AD186,1))>2),(O186-S186)*(IFERROR(INDEX('TaxCred&Subs'!$J$66:$J$99,MATCH(1,($C186&$D186='TaxCred&Subs'!$E$66:$E$99)*($F186='TaxCred&Subs'!$C$66:$C$99),0)),0)),IF(AND($C186=1,VALUE(RIGHT($AD186,1))>2),(O186-S186)*(IFERROR(INDEX('TaxCred&Subs'!$J$66:$J$99,MATCH(1,($C186&$D186='TaxCred&Subs'!$D$66:$D$99)*($F186='TaxCred&Subs'!$C$66:$C$99),0)),0)),IF($C186>2,(O186-S186)*(IFERROR(INDEX('TaxCred&Subs'!$J$66:$J$99,MATCH(1,($C186&$D186='TaxCred&Subs'!$D$66:$D$99)*($F186='TaxCred&Subs'!$C$66:$C$99),0)),0)),0))),0)} -> 0 | R186: {=ROUND(IF(IFERROR(VALUE(RIGHT($AD186,1)),0)>2,IF($C186=8,N186*IFERROR(INDEX('TaxCred&Subs'!$K$139:$S$151,MATCH($C186&$D186&LEFT($AD186,7),'TaxCred&Subs'!$E$139:$E$151,0),MATCH($H186,'TaxCred&Subs'!$K$137:$S$137,0)),0),IF($C186=2,N186*IFERROR(INDEX('TaxCred&Subs'!$K$139:$S$151,MATCH($C186&$D186,'TaxCred&Subs'!$D$139:$D$151,0),MATCH($H186,'TaxCred&Subs'!$K$137:$S$137,0)),0),N186*IFERROR(INDEX('TaxCred&Subs'!$K$139:$S$151,MATCH($C186&$D186,'TaxCred&Subs'!$C$139:$C$151,0),MATCH($H186,'TaxCred&Subs'!$K$137:$S$137,0)),0))),0),0)} -> 0 | S186: {=ROUND(IF(IFERROR(VALUE(RIGHT($AD186,1)),0)>2,IF($C186=8,O186*IFERROR(INDEX('TaxCred&Subs'!$K$139:$S$151,MATCH($C186&$D186&LEFT($AD186,7),'TaxCred&Subs'!$E$139:$E$151,0),MATCH($H186,'TaxCred&Subs'!$K$137:$S$137,0)),0),IF($C186=2,O186*IFERROR(INDEX('TaxCred&Subs'!$K$139:$S$151,MATCH($C186&$D186,'TaxCred&Subs'!$D$139:$D$151,0),MATCH($H186,'TaxCred&Subs'!$K$137:$S$137,0)),0),O186*IFERROR(INDEX('TaxCred&Subs'!$K$139:$S$151,MATCH($C186&$D186,'TaxCred&Subs'!$C$139:$C$151,0),MATCH($H186,'TaxCred&Subs'!$K$137:$S$137,0)),0))),0),0)} -> 0 | T186: =IF($H186=9,IF(R186>0,(N186-P186)*0.15,0),0) -> 0 | U186: =IF($H186=9,IF(S186>0,(O186-Q186)*0.15,0),0) -> 0 | V186: MATURE | W186: 2020 | X186: 1 | Y186: 0 | Z186: -0.00020586784 | AA186: -0.0031671975 | AB186: 0 | AC186: 0 | AD186: KERO_FA3 | AE186: Kerosene equipment is now assumed to be included with distillate fuel oil
B187: =B186+1 -> 163 | C187: 1 | D187: 5 | E187: 16 | F187: 2023 | G187: 2026 | H187: 11 | I187: 16 | J187: 0 | K187: 0 | L187: 0 | M187: 0.85 | N187: 5150 | O187: 3070 | P187: {=ROUND(IF($F187<='TaxCred&Subs'!$C$49,(IF($C187=2,IF($M187>=IFERROR(INDEX('TaxCred&Subs'!$L$12:$L$47,MATCH(1,($C187&$D187='TaxCred&Subs'!$E$12:$E$47)*($F187='TaxCred&Subs'!$C$12:$C$47),0) ),9999),IFERROR(INDEX('TaxCred&Subs'!$N$12:$N$47,MATCH(1,($C187&$D187='TaxCred&Subs'!$E$12:$E$47)*($F187='TaxCred&Subs'!$C$12:$C$47),0) ),0),0),(IF($M187>=IFERROR(INDEX('TaxCred&Subs'!$H$12:$H$47,MATCH(1,($C187&$D187='TaxCred&Subs'!$D$12:$D$47)*($F187='TaxCred&Subs'!$C$12:$C$47),0) ),9999),IFERROR(INDEX('TaxCred&Subs'!$N$12:$N$47,MATCH(1,($C187&$D187='TaxCred&Subs'!$D$12:$D$47)*($F187='TaxCred&Subs'!$C$12:$C$47),0) ),0),0)))),0)+IF(AND($C187=2,VALUE(RIGHT($AD187,1))>2),(N187-R187)*(IFERROR(INDEX('TaxCred&Subs'!$J$66:$J$99,MATCH(1,($C187&$D187='TaxCred&Subs'!$E$66:$E$99)*($F187='TaxCred&Subs'!$C$66:$C$99),0)),0)),IF(AND($C187=1,VALUE(RIGHT($AD187,1))>2),(N187-R187)*(IFERROR(INDEX('TaxCred&Subs'!$J$66:$J$99,MATCH(1,($C187&$D187='TaxCred&Subs'!$D$66:$D$99)*($F187='TaxCred&Subs'!$C$66:$C$99),0)),0)),IF($C187>2,(N187-R187)*(IFERROR(INDEX('TaxCred&Subs'!$J$66:$J$99,MATCH(1,($C187&$D187='TaxCred&Subs'!$D$66:$D$99)*($F187='TaxCred&Subs'!$C$66:$C$99),0)),0)),0))),0)} -> 600 | Q187: {=ROUND(IF(AND($C187=2,VALUE(RIGHT($AD187,1))>2),(O187-S187)*(IFERROR(INDEX('TaxCred&Subs'!$J$66:$J$99,MATCH(1,($C187&$D187='TaxCred&Subs'!$E$66:$E$99)*($F187='TaxCred&Subs'!$C$66:$C$99),0)),0)),IF(AND($C187=1,VALUE(RIGHT($AD187,1))>2),(O187-S187)*(IFERROR(INDEX('TaxCred&Subs'!$J$66:$J$99,MATCH(1,($C187&$D187='TaxCred&Subs'!$D$66:$D$99)*($F187='TaxCred&Subs'!$C$66:$C$99),0)),0)),IF($C187>2,(O187-S187)*(IFERROR(INDEX('TaxCred&Subs'!$J$66:$J$99,MATCH(1,($C187&$D187='TaxCred&Subs'!$D$66:$D$99)*($F187='TaxCred&Subs'!$C$66:$C$99),0)),0)),0))),0)} -> 0 | R187: {=ROUND(IF(IFERROR(VALUE(RIGHT($AD187,1)),0)>2,IF($C187=8,N187*IFERROR(INDEX('TaxCred&Subs'!$K$139:$S$151,MATCH($C187&$D187&LEFT($AD187,7),'TaxCred&Subs'!$E$139:$E$151,0),MATCH($H187,'TaxCred&Subs'!$K$137:$S$137,0)),0),IF($C187=2,N187*IFERROR(INDEX('TaxCred&Subs'!$K$139:$S$151,MATCH($C187&$D187,'TaxCred&Subs'!$D$139:$D$151,0),MATCH($H187,'TaxCred&Subs'!$K$137:$S$137,0)),0),N187*IFERROR(INDEX('TaxCred&Subs'!$K$139:$S$151,MATCH($C187&$D187,'TaxCred&Subs'!$C$139:$C$151,0),MATCH($H187,'TaxCred&Subs'!$K$137:$S$137,0)),0))),0),0)} -> 0 | S187: {=ROUND(IF(IFERROR(VALUE(RIGHT($AD187,1)),0)>2,IF($C187=8,O187*IFERROR(INDEX('TaxCred&Subs'!$K$139:$S$151,MATCH($C187&$D187&LEFT($AD187,7),'TaxCred&Subs'!$E$139:$E$151,0),MATCH($H187,'TaxCred&Subs'!$K$137:$S$137,0)),0),IF($C187=2,O187*IFERROR(INDEX('TaxCred&Subs'!$K$139:$S$151,MATCH($C187&$D187,'TaxCred&Subs'!$D$139:$D$151,0),MATCH($H187,'TaxCred&Subs'!$K$137:$S$137,0)),0),O187*IFERROR(INDEX('TaxCred&Subs'!$K$139:$S$151,MATCH($C187&$D187,'TaxCred&Subs'!$C$139:$C$151,0),MATCH($H187,'TaxCred&Subs'!$K$137:$S$137,0)),0))),0),0)} -> 0 | T187: =IF($H187=9,IF(R187>0,(N187-P187)*0.15,0),0) -> 0 | U187: =IF($H187=9,IF(S187>0,(O187-Q187)*0.15,0),0) -> 0 | V187: MATURE | W187: 2020 | X187: 1 | Y187: 0 | Z187: -0.00020586784 | AA187: -0.0031671975 | AB187: 0 | AC187: 0 | AD187: KERO_FA3 | AE187: Kerosene equipment is now assumed to be included with distillate fuel oil
B188: =B187+1 -> 164 | C188: 1 | D188: 5 | E188: 16 | F188: 2027 | G188: 2050 | H188: 11 | I188: 16 | J188: 0 | K188: 0 | L188: 0 | M188: 0.85 | N188: 5150 | O188: 3070 | P188: {=ROUND(IF($F188<='TaxCred&Subs'!$C$49,(IF($C188=2,IF($M188>=IFERROR(INDEX('TaxCred&Subs'!$L$12:$L$47,MATCH(1,($C188&$D188='TaxCred&Subs'!$E$12:$E$47)*($F188='TaxCred&Subs'!$C$12:$C$47),0) ),9999),IFERROR(INDEX('TaxCred&Subs'!$N$12:$N$47,MATCH(1,($C188&$D188='TaxCred&Subs'!$E$12:$E$47)*($F188='TaxCred&Subs'!$C$12:$C$47),0) ),0),0),(IF($M188>=IFERROR(INDEX('TaxCred&Subs'!$H$12:$H$47,MATCH(1,($C188&$D188='TaxCred&Subs'!$D$12:$D$47)*($F188='TaxCred&Subs'!$C$12:$C$47),0) ),9999),IFERROR(INDEX('TaxCred&Subs'!$N$12:$N$47,MATCH(1,($C188&$D188='TaxCred&Subs'!$D$12:$D$47)*($F188='TaxCred&Subs'!$C$12:$C$47),0) ),0),0)))),0)+IF(AND($C188=2,VALUE(RIGHT($AD188,1))>2),(N188-R188)*(IFERROR(INDEX('TaxCred&Subs'!$J$66:$J$99,MATCH(1,($C188&$D188='TaxCred&Subs'!$E$66:$E$99)*($F188='TaxCred&Subs'!$C$66:$C$99),0)),0)),IF(AND($C188=1,VALUE(RIGHT($AD188,1))>2),(N188-R188)*(IFERROR(INDEX('TaxCred&Subs'!$J$66:$J$99,MATCH(1,($C188&$D188='TaxCred&Subs'!$D$66:$D$99)*($F188='TaxCred&Subs'!$C$66:$C$99),0)),0)),IF($C188>2,(N188-R188)*(IFERROR(INDEX('TaxCred&Subs'!$J$66:$J$99,MATCH(1,($C188&$D188='TaxCred&Subs'!$D$66:$D$99)*($F188='TaxCred&Subs'!$C$66:$C$99),0)),0)),0))),0)} -> 0 | Q188: {=ROUND(IF(AND($C188=2,VALUE(RIGHT($AD188,1))>2),(O188-S188)*(IFERROR(INDEX('TaxCred&Subs'!$J$66:$J$99,MATCH(1,($C188&$D188='TaxCred&Subs'!$E$66:$E$99)*($F188='TaxCred&Subs'!$C$66:$C$99),0)),0)),IF(AND($C188=1,VALUE(RIGHT($AD188,1))>2),(O188-S188)*(IFERROR(INDEX('TaxCred&Subs'!$J$66:$J$99,MATCH(1,($C188&$D188='TaxCred&Subs'!$D$66:$D$99)*($F188='TaxCred&Subs'!$C$66:$C$99),0)),0)),IF($C188>2,(O188-S188)*(IFERROR(INDEX('TaxCred&Subs'!$J$66:$J$99,MATCH(1,($C188&$D188='TaxCred&Subs'!$D$66:$D$99)*($F188='TaxCred&Subs'!$C$66:$C$99),0)),0)),0))),0)} -> 0 | R188: {=ROUND(IF(IFERROR(VALUE(RIGHT($AD188,1)),0)>2,IF($C188=8,N188*IFERROR(INDEX('TaxCred&Subs'!$K$139:$S$151,MATCH($C188&$D188&LEFT($AD188,7),'TaxCred&Subs'!$E$139:$E$151,0),MATCH($H188,'TaxCred&Subs'!$K$137:$S$137,0)),0),IF($C188=2,N188*IFERROR(INDEX('TaxCred&Subs'!$K$139:$S$151,MATCH($C188&$D188,'TaxCred&Subs'!$D$139:$D$151,0),MATCH($H188,'TaxCred&Subs'!$K$137:$S$137,0)),0),N188*IFERROR(INDEX('TaxCred&Subs'!$K$139:$S$151,MATCH($C188&$D188,'TaxCred&Subs'!$C$139:$C$151,0),MATCH($H188,'TaxCred&Subs'!$K$137:$S$137,0)),0))),0),0)} -> 0 | S188: {=ROUND(IF(IFERROR(VALUE(RIGHT($AD188,1)),0)>2,IF($C188=8,O188*IFERROR(INDEX('TaxCred&Subs'!$K$139:$S$151,MATCH($C188&$D188&LEFT($AD188,7),'TaxCred&Subs'!$E$139:$E$151,0),MATCH($H188,'TaxCred&Subs'!$K$137:$S$137,0)),0),IF($C188=2,O188*IFERROR(INDEX('TaxCred&Subs'!$K$139:$S$151,MATCH($C188&$D188,'TaxCred&Subs'!$D$139:$D$151,0),MATCH($H188,'TaxCred&Subs'!$K$137:$S$137,0)),0),O188*IFERROR(INDEX('TaxCred&Subs'!$K$139:$S$151,MATCH($C188&$D188,'TaxCred&Subs'!$C$139:$C$151,0),MATCH($H188,'TaxCred&Subs'!$K$137:$S$137,0)),0))),0),0)} -> 0 | T188: =IF($H188=9,IF(R188>0,(N188-P188)*0.15,0),0) -> 0 | U188: =IF($H188=9,IF(S188>0,(O188-Q188)*0.15,0),0) -> 0 | V188: MATURE | W188: 2020 | X188: 1 | Y188: 0 | Z188: -0.00020586784 | AA188: -0.0031671975 | AB188: 0 | AC188: 0 | AD188: KERO_FA3 | AE188: Kerosene equipment is now assumed to be included with distillate fuel oil
B189: =B188+1 -> 165 | C189: 1 | D189: 5 | E189: 17 | F189: 2020 | G189: 2022 | H189: 11 | I189: 17 | J189: 0 | K189: 0 | L189: 0 | M189: 0.967 | N189: 7625 | O189: 3630 | P189: {=ROUND(IF($F189<='TaxCred&Subs'!$C$49,(IF($C189=2,IF($M189>=IFERROR(INDEX('TaxCred&Subs'!$L$12:$L$47,MATCH(1,($C189&$D189='TaxCred&Subs'!$E$12:$E$47)*($F189='TaxCred&Subs'!$C$12:$C$47),0) ),9999),IFERROR(INDEX('TaxCred&Subs'!$N$12:$N$47,MATCH(1,($C189&$D189='TaxCred&Subs'!$E$12:$E$47)*($F189='TaxCred&Subs'!$C$12:$C$47),0) ),0),0),(IF($M189>=IFERROR(INDEX('TaxCred&Subs'!$H$12:$H$47,MATCH(1,($C189&$D189='TaxCred&Subs'!$D$12:$D$47)*($F189='TaxCred&Subs'!$C$12:$C$47),0) ),9999),IFERROR(INDEX('TaxCred&Subs'!$N$12:$N$47,MATCH(1,($C189&$D189='TaxCred&Subs'!$D$12:$D$47)*($F189='TaxCred&Subs'!$C$12:$C$47),0) ),0),0)))),0)+IF(AND($C189=2,VALUE(RIGHT($AD189,1))>2),(N189-R189)*(IFERROR(INDEX('TaxCred&Subs'!$J$66:$J$99,MATCH(1,($C189&$D189='TaxCred&Subs'!$E$66:$E$99)*($F189='TaxCred&Subs'!$C$66:$C$99),0)),0)),IF(AND($C189=1,VALUE(RIGHT($AD189,1))>2),(N189-R189)*(IFERROR(INDEX('TaxCred&Subs'!$J$66:$J$99,MATCH(1,($C189&$D189='TaxCred&Subs'!$D$66:$D$99)*($F189='TaxCred&Subs'!$C$66:$C$99),0)),0)),IF($C189>2,(N189-R189)*(IFERROR(INDEX('TaxCred&Subs'!$J$66:$J$99,MATCH(1,($C189&$D189='TaxCred&Subs'!$D$66:$D$99)*($F189='TaxCred&Subs'!$C$66:$C$99),0)),0)),0))),0)} -> 150 | Q189: {=ROUND(IF(AND($C189=2,VALUE(RIGHT($AD189,1))>2),(O189-S189)*(IFERROR(INDEX('TaxCred&Subs'!$J$66:$J$99,MATCH(1,($C189&$D189='TaxCred&Subs'!$E$66:$E$99)*($F189='TaxCred&Subs'!$C$66:$C$99),0)),0)),IF(AND($C189=1,VALUE(RIGHT($AD189,1))>2),(O189-S189)*(IFERROR(INDEX('TaxCred&Subs'!$J$66:$J$99,MATCH(1,($C189&$D189='TaxCred&Subs'!$D$66:$D$99)*($F189='TaxCred&Subs'!$C$66:$C$99),0)),0)),IF($C189>2,(O189-S189)*(IFERROR(INDEX('TaxCred&Subs'!$J$66:$J$99,MATCH(1,($C189&$D189='TaxCred&Subs'!$D$66:$D$99)*($F189='TaxCred&Subs'!$C$66:$C$99),0)),0)),0))),0)} -> 0 | R189: {=ROUND(IF(IFERROR(VALUE(RIGHT($AD189,1)),0)>2,IF($C189=8,N189*IFERROR(INDEX('TaxCred&Subs'!$K$139:$S$151,MATCH($C189&$D189&LEFT($AD189,7),'TaxCred&Subs'!$E$139:$E$151,0),MATCH($H189,'TaxCred&Subs'!$K$137:$S$137,0)),0),IF($C189=2,N189*IFERROR(INDEX('TaxCred&Subs'!$K$139:$S$151,MATCH($C189&$D189,'TaxCred&Subs'!$D$139:$D$151,0),MATCH($H189,'TaxCred&Subs'!$K$137:$S$137,0)),0),N189*IFERROR(INDEX('TaxCred&Subs'!$K$139:$S$151,MATCH($C189&$D189,'TaxCred&Subs'!$C$139:$C$151,0),MATCH($H189,'TaxCred&Subs'!$K$137:$S$137,0)),0))),0),0)} -> 0 | S189: {=ROUND(IF(IFERROR(VALUE(RIGHT($AD189,1)),0)>2,IF($C189=8,O189*IFERROR(INDEX('TaxCred&Subs'!$K$139:$S$151,MATCH($C189&$D189&LEFT($AD189,7),'TaxCred&Subs'!$E$139:$E$151,0),MATCH($H189,'TaxCred&Subs'!$K$137:$S$137,0)),0),IF($C189=2,O189*IFERROR(INDEX('TaxCred&Subs'!$K$139:$S$151,MATCH($C189&$D189,'TaxCred&Subs'!$D$139:$D$151,0),MATCH($H189,'TaxCred&Subs'!$K$137:$S$137,0)),0),O189*IFERROR(INDEX('TaxCred&Subs'!$K$139:$S$151,MATCH($C189&$D189,'TaxCred&Subs'!$C$139:$C$151,0),MATCH($H189,'TaxCred&Subs'!$K$137:$S$137,0)),0))),0),0)} -> 0 | T189: =IF($H189=9,IF(R189>0,(N189-P189)*0.15,0),0) -> 0 | U189: =IF($H189=9,IF(S189>0,(O189-Q189)*0.15,0),0) -> 0 | V189: MATURE | W189: 2020 | X189: 1 | Y189: 0 | Z189: -0.00020586784 | AA189: -0.0031671975 | AB189: 0 | AC189: 0 | AD189: KERO_FA4 | AE189: Kerosene equipment is now assumed to be included with distillate fuel oil
B190: =B189+1 -> 166 | C190: 1 | D190: 5 | E190: 17 | F190: 2023 | G190: 2026 | H190: 11 | I190: 17 | J190: 0 | K190: 0 | L190: 0 | M190: 0.967 | N190: 7625 | O190: 3630 | P190: {=ROUND(IF($F190<='TaxCred&Subs'!$C$49,(IF($C190=2,IF($M190>=IFERROR(INDEX('TaxCred&Subs'!$L$12:$L$47,MATCH(1,($C190&$D190='TaxCred&Subs'!$E$12:$E$47)*($F190='TaxCred&Subs'!$C$12:$C$47),0) ),9999),IFERROR(INDEX('TaxCred&Subs'!$N$12:$N$47,MATCH(1,($C190&$D190='TaxCred&Subs'!$E$12:$E$47)*($F190='TaxCred&Subs'!$C$12:$C$47),0) ),0),0),(IF($M190>=IFERROR(INDEX('TaxCred&Subs'!$H$12:$H$47,MATCH(1,($C190&$D190='TaxCred&Subs'!$D$12:$D$47)*($F190='TaxCred&Subs'!$C$12:$C$47),0) ),9999),IFERROR(INDEX('TaxCred&Subs'!$N$12:$N$47,MATCH(1,($C190&$D190='TaxCred&Subs'!$D$12:$D$47)*($F190='TaxCred&Subs'!$C$12:$C$47),0) ),0),0)))),0)+IF(AND($C190=2,VALUE(RIGHT($AD190,1))>2),(N190-R190)*(IFERROR(INDEX('TaxCred&Subs'!$J$66:$J$99,MATCH(1,($C190&$D190='TaxCred&Subs'!$E$66:$E$99)*($F190='TaxCred&Subs'!$C$66:$C$99),0)),0)),IF(AND($C190=1,VALUE(RIGHT($AD190,1))>2),(N190-R190)*(IFERROR(INDEX('TaxCred&Subs'!$J$66:$J$99,MATCH(1,($C190&$D190='TaxCred&Subs'!$D$66:$D$99)*($F190='TaxCred&Subs'!$C$66:$C$99),0)),0)),IF($C190>2,(N190-R190)*(IFERROR(INDEX('TaxCred&Subs'!$J$66:$J$99,MATCH(1,($C190&$D190='TaxCred&Subs'!$D$66:$D$99)*($F190='TaxCred&Subs'!$C$66:$C$99),0)),0)),0))),0)} -> 600 | Q190: {=ROUND(IF(AND($C190=2,VALUE(RIGHT($AD190,1))>2),(O190-S190)*(IFERROR(INDEX('TaxCred&Subs'!$J$66:$J$99,MATCH(1,($C190&$D190='TaxCred&Subs'!$E$66:$E$99)*($F190='TaxCred&Subs'!$C$66:$C$99),0)),0)),IF(AND($C190=1,VALUE(RIGHT($AD190,1))>2),(O190-S190)*(IFERROR(INDEX('TaxCred&Subs'!$J$66:$J$99,MATCH(1,($C190&$D190='TaxCred&Subs'!$D$66:$D$99)*($F190='TaxCred&Subs'!$C$66:$C$99),0)),0)),IF($C190>2,(O190-S190)*(IFERROR(INDEX('TaxCred&Subs'!$J$66:$J$99,MATCH(1,($C190&$D190='TaxCred&Subs'!$D$66:$D$99)*($F190='TaxCred&Subs'!$C$66:$C$99),0)),0)),0))),0)} -> 0 | R190: {=ROUND(IF(IFERROR(VALUE(RIGHT($AD190,1)),0)>2,IF($C190=8,N190*IFERROR(INDEX('TaxCred&Subs'!$K$139:$S$151,MATCH($C190&$D190&LEFT($AD190,7),'TaxCred&Subs'!$E$139:$E$151,0),MATCH($H190,'TaxCred&Subs'!$K$137:$S$137,0)),0),IF($C190=2,N190*IFERROR(INDEX('TaxCred&Subs'!$K$139:$S$151,MATCH($C190&$D190,'TaxCred&Subs'!$D$139:$D$151,0),MATCH($H190,'TaxCred&Subs'!$K$137:$S$137,0)),0),N190*IFERROR(INDEX('TaxCred&Subs'!$K$139:$S$151,MATCH($C190&$D190,'TaxCred&Subs'!$C$139:$C$151,0),MATCH($H190,'TaxCred&Subs'!$K$137:$S$137,0)),0))),0),0)} -> 0 | S190: {=ROUND(IF(IFERROR(VALUE(RIGHT($AD190,1)),0)>2,IF($C190=8,O190*IFERROR(INDEX('TaxCred&Subs'!$K$139:$S$151,MATCH($C190&$D190&LEFT($AD190,7),'TaxCred&Subs'!$E$139:$E$151,0),MATCH($H190,'TaxCred&Subs'!$K$137:$S$137,0)),0),IF($C190=2,O190*IFERROR(INDEX('TaxCred&Subs'!$K$139:$S$151,MATCH($C190&$D190,'TaxCred&Subs'!$D$139:$D$151,0),MATCH($H190,'TaxCred&Subs'!$K$137:$S$137,0)),0),O190*IFERROR(INDEX('TaxCred&Subs'!$K$139:$S$151,MATCH($C190&$D190,'TaxCred&Subs'!$C$139:$C$151,0),MATCH($H190,'TaxCred&Subs'!$K$137:$S$137,0)),0))),0),0)} -> 0 | T190: =IF($H190=9,IF(R190>0,(N190-P190)*0.15,0),0) -> 0 | U190: =IF($H190=9,IF(S190>0,(O190-Q190)*0.15,0),0) -> 0 | V190: MATURE | W190: 2020 | X190: 1 | Y190: 0 | Z190: -0.00020586784 | AA190: -0.0031671975 | AB190: 0 | AC190: 0 | AD190: KERO_FA4 | AE190: Kerosene equipment is now assumed to be included with distillate fuel oil
B191: =B190+1 -> 167 | C191: 1 | D191: 5 | E191: 17 | F191: 2027 | G191: 2050 | H191: 11 | I191: 17 | J191: 0 | K191: 0 | L191: 0 | M191: 0.967 | N191: 7625 | O191: 3630 | P191: {=ROUND(IF($F191<='TaxCred&Subs'!$C$49,(IF($C191=2,IF($M191>=IFERROR(INDEX('TaxCred&Subs'!$L$12:$L$47,MATCH(1,($C191&$D191='TaxCred&Subs'!$E$12:$E$47)*($F191='TaxCred&Subs'!$C$12:$C$47),0) ),9999),IFERROR(INDEX('TaxCred&Subs'!$N$12:$N$47,MATCH(1,($C191&$D191='TaxCred&Subs'!$E$12:$E$47)*($F191='TaxCred&Subs'!$C$12:$C$47),0) ),0),0),(IF($M191>=IFERROR(INDEX('TaxCred&Subs'!$H$12:$H$47,MATCH(1,($C191&$D191='TaxCred&Subs'!$D$12:$D$47)*($F191='TaxCred&Subs'!$C$12:$C$47),0) ),9999),IFERROR(INDEX('TaxCred&Subs'!$N$12:$N$47,MATCH(1,($C191&$D191='TaxCred&Subs'!$D$12:$D$47)*($F191='TaxCred&Subs'!$C$12:$C$47),0) ),0),0)))),0)+IF(AND($C191=2,VALUE(RIGHT($AD191,1))>2),(N191-R191)*(IFERROR(INDEX('TaxCred&Subs'!$J$66:$J$99,MATCH(1,($C191&$D191='TaxCred&Subs'!$E$66:$E$99)*($F191='TaxCred&Subs'!$C$66:$C$99),0)),0)),IF(AND($C191=1,VALUE(RIGHT($AD191,1))>2),(N191-R191)*(IFERROR(INDEX('TaxCred&Subs'!$J$66:$J$99,MATCH(1,($C191&$D191='TaxCred&Subs'!$D$66:$D$99)*($F191='TaxCred&Subs'!$C$66:$C$99),0)),0)),IF($C191>2,(N191-R191)*(IFERROR(INDEX('TaxCred&Subs'!$J$66:$J$99,MATCH(1,($C191&$D191='TaxCred&Subs'!$D$66:$D$99)*($F191='TaxCred&Subs'!$C$66:$C$99),0)),0)),0))),0)} -> 600 | Q191: {=ROUND(IF(AND($C191=2,VALUE(RIGHT($AD191,1))>2),(O191-S191)*(IFERROR(INDEX('TaxCred&Subs'!$J$66:$J$99,MATCH(1,($C191&$D191='TaxCred&Subs'!$E$66:$E$99)*($F191='TaxCred&Subs'!$C$66:$C$99),0)),0)),IF(AND($C191=1,VALUE(RIGHT($AD191,1))>2),(O191-S191)*(IFERROR(INDEX('TaxCred&Subs'!$J$66:$J$99,MATCH(1,($C191&$D191='TaxCred&Subs'!$D$66:$D$99)*($F191='TaxCred&Subs'!$C$66:$C$99),0)),0)),IF($C191>2,(O191-S191)*(IFERROR(INDEX('TaxCred&Subs'!$J$66:$J$99,MATCH(1,($C191&$D191='TaxCred&Subs'!$D$66:$D$99)*($F191='TaxCred&Subs'!$C$66:$C$99),0)),0)),0))),0)} -> 0 | R191: {=ROUND(IF(IFERROR(VALUE(RIGHT($AD191,1)),0)>2,IF($C191=8,N191*IFERROR(INDEX('TaxCred&Subs'!$K$139:$S$151,MATCH($C191&$D191&LEFT($AD191,7),'TaxCred&Subs'!$E$139:$E$151,0),MATCH($H191,'TaxCred&Subs'!$K$137:$S$137,0)),0),IF($C191=2,N191*IFERROR(INDEX('TaxCred&Subs'!$K$139:$S$151,MATCH($C191&$D191,'TaxCred&Subs'!$D$139:$D$151,0),MATCH($H191,'TaxCred&Subs'!$K$137:$S$137,0)),0),N191*IFERROR(INDEX('TaxCred&Subs'!$K$139:$S$151,MATCH($C191&$D191,'TaxCred&Subs'!$C$139:$C$151,0),MATCH($H191,'TaxCred&Subs'!$K$137:$S$137,0)),0))),0),0)} -> 0 | S191: {=ROUND(IF(IFERROR(VALUE(RIGHT($AD191,1)),0)>2,IF($C191=8,O191*IFERROR(INDEX('TaxCred&Subs'!$K$139:$S$151,MATCH($C191&$D191&LEFT($AD191,7),'TaxCred&Subs'!$E$139:$E$151,0),MATCH($H191,'TaxCred&Subs'!$K$137:$S$137,0)),0),IF($C191=2,O191*IFERROR(INDEX('TaxCred&Subs'!$K$139:$S$151,MATCH($C191&$D191,'TaxCred&Subs'!$D$139:$D$151,0),MATCH($H191,'TaxCred&Subs'!$K$137:$S$137,0)),0),O191*IFERROR(INDEX('TaxCred&Subs'!$K$139:$S$151,MATCH($C191&$D191,'TaxCred&Subs'!$C$139:$C$151,0),MATCH($H191,'TaxCred&Subs'!$K$137:$S$137,0)),0))),0),0)} -> 0 | T191: =IF($H191=9,IF(R191>0,(N191-P191)*0.15,0),0) -> 0 | U191: =IF($H191=9,IF(S191>0,(O191-Q191)*0.15,0),0) -> 0 | V191: MATURE | W191: 2020 | X191: 1 | Y191: 0 | Z191: -0.00020586784 | AA191: -0.0031671975 | AB191: 0 | AC191: 0 | AD191: KERO_FA4 | AE191: Kerosene equipment is now assumed to be included with distillate fuel oil
B192: =B191+1 -> 168 | C192: 1 | D192: 6 | E192: 18 | F192: 2020 | G192: 2028 | H192: 11 | I192: 18 | J192: 0 | K192: 0 | L192: 0 | M192: 0.8 | N192: 3690 | O192: 1080 | P192: {=ROUND(IF($F192<='TaxCred&Subs'!$C$49,(IF($C192=2,IF($M192>=IFERROR(INDEX('TaxCred&Subs'!$L$12:$L$47,MATCH(1,($C192&$D192='TaxCred&Subs'!$E$12:$E$47)*($F192='TaxCred&Subs'!$C$12:$C$47),0) ),9999),IFERROR(INDEX('TaxCred&Subs'!$N$12:$N$47,MATCH(1,($C192&$D192='TaxCred&Subs'!$E$12:$E$47)*($F192='TaxCred&Subs'!$C$12:$C$47),0) ),0),0),(IF($M192>=IFERROR(INDEX('TaxCred&Subs'!$H$12:$H$47,MATCH(1,($C192&$D192='TaxCred&Subs'!$D$12:$D$47)*($F192='TaxCred&Subs'!$C$12:$C$47),0) ),9999),IFERROR(INDEX('TaxCred&Subs'!$N$12:$N$47,MATCH(1,($C192&$D192='TaxCred&Subs'!$D$12:$D$47)*($F192='TaxCred&Subs'!$C$12:$C$47),0) ),0),0)))),0)+IF(AND($C192=2,VALUE(RIGHT($AD192,1))>2),(N192-R192)*(IFERROR(INDEX('TaxCred&Subs'!$J$66:$J$99,MATCH(1,($C192&$D192='TaxCred&Subs'!$E$66:$E$99)*($F192='TaxCred&Subs'!$C$66:$C$99),0)),0)),IF(AND($C192=1,VALUE(RIGHT($AD192,1))>2),(N192-R192)*(IFERROR(INDEX('TaxCred&Subs'!$J$66:$J$99,MATCH(1,($C192&$D192='TaxCred&Subs'!$D$66:$D$99)*($F192='TaxCred&Subs'!$C$66:$C$99),0)),0)),IF($C192>2,(N192-R192)*(IFERROR(INDEX('TaxCred&Subs'!$J$66:$J$99,MATCH(1,($C192&$D192='TaxCred&Subs'!$D$66:$D$99)*($F192='TaxCred&Subs'!$C$66:$C$99),0)),0)),0))),0)} -> 0 | Q192: {=ROUND(IF(AND($C192=2,VALUE(RIGHT($AD192,1))>2),(O192-S192)*(IFERROR(INDEX('TaxCred&Subs'!$J$66:$J$99,MATCH(1,($C192&$D192='TaxCred&Subs'!$E$66:$E$99)*($F192='TaxCred&Subs'!$C$66:$C$99),0)),0)),IF(AND($C192=1,VALUE(RIGHT($AD192,1))>2),(O192-S192)*(IFERROR(INDEX('TaxCred&Subs'!$J$66:$J$99,MATCH(1,($C192&$D192='TaxCred&Subs'!$D$66:$D$99)*($F192='TaxCred&Subs'!$C$66:$C$99),0)),0)),IF($C192>2,(O192-S192)*(IFERROR(INDEX('TaxCred&Subs'!$J$66:$J$99,MATCH(1,($C192&$D192='TaxCred&Subs'!$D$66:$D$99)*($F192='TaxCred&Subs'!$C$66:$C$99),0)),0)),0))),0)} -> 0 | R192: {=ROUND(IF(IFERROR(VALUE(RIGHT($AD192,1)),0)>2,IF($C192=8,N192*IFERROR(INDEX('TaxCred&Subs'!$K$139:$S$151,MATCH($C192&$D192&LEFT($AD192,7),'TaxCred&Subs'!$E$139:$E$151,0),MATCH($H192,'TaxCred&Subs'!$K$137:$S$137,0)),0),IF($C192=2,N192*IFERROR(INDEX('TaxCred&Subs'!$K$139:$S$151,MATCH($C192&$D192,'TaxCred&Subs'!$D$139:$D$151,0),MATCH($H192,'TaxCred&Subs'!$K$137:$S$137,0)),0),N192*IFERROR(INDEX('TaxCred&Subs'!$K$139:$S$151,MATCH($C192&$D192,'TaxCred&Subs'!$C$139:$C$151,0),MATCH($H192,'TaxCred&Subs'!$K$137:$S$137,0)),0))),0),0)} -> 0 | S192: {=ROUND(IF(IFERROR(VALUE(RIGHT($AD192,1)),0)>2,IF($C192=8,O192*IFERROR(INDEX('TaxCred&Subs'!$K$139:$S$151,MATCH($C192&$D192&LEFT($AD192,7),'TaxCred&Subs'!$E$139:$E$151,0),MATCH($H192,'TaxCred&Subs'!$K$137:$S$137,0)),0),IF($C192=2,O192*IFERROR(INDEX('TaxCred&Subs'!$K$139:$S$151,MATCH($C192&$D192,'TaxCred&Subs'!$D$139:$D$151,0),MATCH($H192,'TaxCred&Subs'!$K$137:$S$137,0)),0),O192*IFERROR(INDEX('TaxCred&Subs'!$K$139:$S$151,MATCH($C192&$D192,'TaxCred&Subs'!$C$139:$C$151,0),MATCH($H192,'TaxCred&Subs'!$K$137:$S$137,0)),0))),0),0)} -> 0 | T192: =IF($H192=9,IF(R192>0,(N192-P192)*0.15,0),0) -> 0 | U192: =IF($H192=9,IF(S192>0,(O192-Q192)*0.15,0),0) -> 0 | V192: MATURE | W192: 2020 | X192: 1 | Y192: 0 | Z192: -0.0001782623 | AA192: -0.0027424969 | AB192: 0 | AC192: 0 | AD192: LPG_FA1
B193: =B192+1 -> 169 | C193: 1 | D193: 6 | E193: 18 | F193: 2029 | G193: 2050 | H193: 11 | I193: 18 | J193: 0 | K193: 0 | L193: 0 | M193: 0.95 | N193: 4150 | O193: 1220 | P193: {=ROUND(IF($F193<='TaxCred&Subs'!$C$49,(IF($C193=2,IF($M193>=IFERROR(INDEX('TaxCred&Subs'!$L$12:$L$47,MATCH(1,($C193&$D193='TaxCred&Subs'!$E$12:$E$47)*($F193='TaxCred&Subs'!$C$12:$C$47),0) ),9999),IFERROR(INDEX('TaxCred&Subs'!$N$12:$N$47,MATCH(1,($C193&$D193='TaxCred&Subs'!$E$12:$E$47)*($F193='TaxCred&Subs'!$C$12:$C$47),0) ),0),0),(IF($M193>=IFERROR(INDEX('TaxCred&Subs'!$H$12:$H$47,MATCH(1,($C193&$D193='TaxCred&Subs'!$D$12:$D$47)*($F193='TaxCred&Subs'!$C$12:$C$47),0) ),9999),IFERROR(INDEX('TaxCred&Subs'!$N$12:$N$47,MATCH(1,($C193&$D193='TaxCred&Subs'!$D$12:$D$47)*($F193='TaxCred&Subs'!$C$12:$C$47),0) ),0),0)))),0)+IF(AND($C193=2,VALUE(RIGHT($AD193,1))>2),(N193-R193)*(IFERROR(INDEX('TaxCred&Subs'!$J$66:$J$99,MATCH(1,($C193&$D193='TaxCred&Subs'!$E$66:$E$99)*($F193='TaxCred&Subs'!$C$66:$C$99),0)),0)),IF(AND($C193=1,VALUE(RIGHT($AD193,1))>2),(N193-R193)*(IFERROR(INDEX('TaxCred&Subs'!$J$66:$J$99,MATCH(1,($C193&$D193='TaxCred&Subs'!$D$66:$D$99)*($F193='TaxCred&Subs'!$C$66:$C$99),0)),0)),IF($C193>2,(N193-R193)*(IFERROR(INDEX('TaxCred&Subs'!$J$66:$J$99,MATCH(1,($C193&$D193='TaxCred&Subs'!$D$66:$D$99)*($F193='TaxCred&Subs'!$C$66:$C$99),0)),0)),0))),0)} -> 0 | Q193: {=ROUND(IF(AND($C193=2,VALUE(RIGHT($AD193,1))>2),(O193-S193)*(IFERROR(INDEX('TaxCred&Subs'!$J$66:$J$99,MATCH(1,($C193&$D193='TaxCred&Subs'!$E$66:$E$99)*($F193='TaxCred&Subs'!$C$66:$C$99),0)),0)),IF(AND($C193=1,VALUE(RIGHT($AD193,1))>2),(O193-S193)*(IFERROR(INDEX('TaxCred&Subs'!$J$66:$J$99,MATCH(1,($C193&$D193='TaxCred&Subs'!$D$66:$D$99)*($F193='TaxCred&Subs'!$C$66:$C$99),0)),0)),IF($C193>2,(O193-S193)*(IFERROR(INDEX('TaxCred&Subs'!$J$66:$J$99,MATCH(1,($C193&$D193='TaxCred&Subs'!$D$66:$D$99)*($F193='TaxCred&Subs'!$C$66:$C$99),0)),0)),0))),0)} -> 0 | R193: {=ROUND(IF(IFERROR(VALUE(RIGHT($AD193,1)),0)>2,IF($C193=8,N193*IFERROR(INDEX('TaxCred&Subs'!$K$139:$S$151,MATCH($C193&$D193&LEFT($AD193,7),'TaxCred&Subs'!$E$139:$E$151,0),MATCH($H193,'TaxCred&Subs'!$K$137:$S$137,0)),0),IF($C193=2,N193*IFERROR(INDEX('TaxCred&Subs'!$K$139:$S$151,MATCH($C193&$D193,'TaxCred&Subs'!$D$139:$D$151,0),MATCH($H193,'TaxCred&Subs'!$K$137:$S$137,0)),0),N193*IFERROR(INDEX('TaxCred&Subs'!$K$139:$S$151,MATCH($C193&$D193,'TaxCred&Subs'!$C$139:$C$151,0),MATCH($H193,'TaxCred&Subs'!$K$137:$S$137,0)),0))),0),0)} -> 0 | S193: {=ROUND(IF(IFERROR(VALUE(RIGHT($AD193,1)),0)>2,IF($C193=8,O193*IFERROR(INDEX('TaxCred&Subs'!$K$139:$S$151,MATCH($C193&$D193&LEFT($AD193,7),'TaxCred&Subs'!$E$139:$E$151,0),MATCH($H193,'TaxCred&Subs'!$K$137:$S$137,0)),0),IF($C193=2,O193*IFERROR(INDEX('TaxCred&Subs'!$K$139:$S$151,MATCH($C193&$D193,'TaxCred&Subs'!$D$139:$D$151,0),MATCH($H193,'TaxCred&Subs'!$K$137:$S$137,0)),0),O193*IFERROR(INDEX('TaxCred&Subs'!$K$139:$S$151,MATCH($C193&$D193,'TaxCred&Subs'!$C$139:$C$151,0),MATCH($H193,'TaxCred&Subs'!$K$137:$S$137,0)),0))),0),0)} -> 0 | T193: =IF($H193=9,IF(R193>0,(N193-P193)*0.15,0),0) -> 0 | U193: =IF($H193=9,IF(S193>0,(O193-Q193)*0.15,0),0) -> 0 | V193: MATURE | W193: 2020 | X193: 1 | Y193: 0 | Z193: -0.0001782623 | AA193: -0.0027424969 | AB193: 0 | AC193: 0 | AD193: LPG_FA1
B194: =B193+1 -> 170 | C194: 1 | D194: 6 | E194: 19 | F194: 2020 | G194: 2029 | H194: 11 | I194: 19 | J194: 0 | K194: 0 | L194: 0 | M194: 0.9 | N194: 4130 | O194: 1200 | P194: {=ROUND(IF($F194<='TaxCred&Subs'!$C$49,(IF($C194=2,IF($M194>=IFERROR(INDEX('TaxCred&Subs'!$L$12:$L$47,MATCH(1,($C194&$D194='TaxCred&Subs'!$E$12:$E$47)*($F194='TaxCred&Subs'!$C$12:$C$47),0) ),9999),IFERROR(INDEX('TaxCred&Subs'!$N$12:$N$47,MATCH(1,($C194&$D194='TaxCred&Subs'!$E$12:$E$47)*($F194='TaxCred&Subs'!$C$12:$C$47),0) ),0),0),(IF($M194>=IFERROR(INDEX('TaxCred&Subs'!$H$12:$H$47,MATCH(1,($C194&$D194='TaxCred&Subs'!$D$12:$D$47)*($F194='TaxCred&Subs'!$C$12:$C$47),0) ),9999),IFERROR(INDEX('TaxCred&Subs'!$N$12:$N$47,MATCH(1,($C194&$D194='TaxCred&Subs'!$D$12:$D$47)*($F194='TaxCred&Subs'!$C$12:$C$47),0) ),0),0)))),0)+IF(AND($C194=2,VALUE(RIGHT($AD194,1))>2),(N194-R194)*(IFERROR(INDEX('TaxCred&Subs'!$J$66:$J$99,MATCH(1,($C194&$D194='TaxCred&Subs'!$E$66:$E$99)*($F194='TaxCred&Subs'!$C$66:$C$99),0)),0)),IF(AND($C194=1,VALUE(RIGHT($AD194,1))>2),(N194-R194)*(IFERROR(INDEX('TaxCred&Subs'!$J$66:$J$99,MATCH(1,($C194&$D194='TaxCred&Subs'!$D$66:$D$99)*($F194='TaxCred&Subs'!$C$66:$C$99),0)),0)),IF($C194>2,(N194-R194)*(IFERROR(INDEX('TaxCred&Subs'!$J$66:$J$99,MATCH(1,($C194&$D194='TaxCred&Subs'!$D$66:$D$99)*($F194='TaxCred&Subs'!$C$66:$C$99),0)),0)),0))),0)} -> 0 | Q194: {=ROUND(IF(AND($C194=2,VALUE(RIGHT($AD194,1))>2),(O194-S194)*(IFERROR(INDEX('TaxCred&Subs'!$J$66:$J$99,MATCH(1,($C194&$D194='TaxCred&Subs'!$E$66:$E$99)*($F194='TaxCred&Subs'!$C$66:$C$99),0)),0)),IF(AND($C194=1,VALUE(RIGHT($AD194,1))>2),(O194-S194)*(IFERROR(INDEX('TaxCred&Subs'!$J$66:$J$99,MATCH(1,($C194&$D194='TaxCred&Subs'!$D$66:$D$99)*($F194='TaxCred&Subs'!$C$66:$C$99),0)),0)),IF($C194>2,(O194-S194)*(IFERROR(INDEX('TaxCred&Subs'!$J$66:$J$99,MATCH(1,($C194&$D194='TaxCred&Subs'!$D$66:$D$99)*($F194='TaxCred&Subs'!$C$66:$C$99),0)),0)),0))),0)} -> 0 | R194: {=ROUND(IF(IFERROR(VALUE(RIGHT($AD194,1)),0)>2,IF($C194=8,N194*IFERROR(INDEX('TaxCred&Subs'!$K$139:$S$151,MATCH($C194&$D194&LEFT($AD194,7),'TaxCred&Subs'!$E$139:$E$151,0),MATCH($H194,'TaxCred&Subs'!$K$137:$S$137,0)),0),IF($C194=2,N194*IFERROR(INDEX('TaxCred&Subs'!$K$139:$S$151,MATCH($C194&$D194,'TaxCred&Subs'!$D$139:$D$151,0),MATCH($H194,'TaxCred&Subs'!$K$137:$S$137,0)),0),N194*IFERROR(INDEX('TaxCred&Subs'!$K$139:$S$151,MATCH($C194&$D194,'TaxCred&Subs'!$C$139:$C$151,0),MATCH($H194,'TaxCred&Subs'!$K$137:$S$137,0)),0))),0),0)} -> 0 | S194: {=ROUND(IF(IFERROR(VALUE(RIGHT($AD194,1)),0)>2,IF($C194=8,O194*IFERROR(INDEX('TaxCred&Subs'!$K$139:$S$151,MATCH($C194&$D194&LEFT($AD194,7),'TaxCred&Subs'!$E$139:$E$151,0),MATCH($H194,'TaxCred&Subs'!$K$137:$S$137,0)),0),IF($C194=2,O194*IFERROR(INDEX('TaxCred&Subs'!$K$139:$S$151,MATCH($C194&$D194,'TaxCred&Subs'!$D$139:$D$151,0),MATCH($H194,'TaxCred&Subs'!$K$137:$S$137,0)),0),O194*IFERROR(INDEX('TaxCred&Subs'!$K$139:$S$151,MATCH($C194&$D194,'TaxCred&Subs'!$C$139:$C$151,0),MATCH($H194,'TaxCred&Subs'!$K$137:$S$137,0)),0))),0),0)} -> 0 | T194: =IF($H194=9,IF(R194>0,(N194-P194)*0.15,0),0) -> 0 | U194: =IF($H194=9,IF(S194>0,(O194-Q194)*0.15,0),0) -> 0 | V194: MATURE | W194: 2020 | X194: 1 | Y194: 0 | Z194: -0.0001782623 | AA194: -0.0027424969 | AB194: 0 | AC194: 0 | AD194: LPG_FA2
B195: =B194+1 -> 171 | C195: 1 | D195: 6 | E195: 19 | F195: 2030 | G195: 2050 | H195: 11 | I195: 19 | J195: 0 | K195: 0 | L195: 0 | M195: 0.95 | N195: 4150 | O195: 1220 | P195: {=ROUND(IF($F195<='TaxCred&Subs'!$C$49,(IF($C195=2,IF($M195>=IFERROR(INDEX('TaxCred&Subs'!$L$12:$L$47,MATCH(1,($C195&$D195='TaxCred&Subs'!$E$12:$E$47)*($F195='TaxCred&Subs'!$C$12:$C$47),0) ),9999),IFERROR(INDEX('TaxCred&Subs'!$N$12:$N$47,MATCH(1,($C195&$D195='TaxCred&Subs'!$E$12:$E$47)*($F195='TaxCred&Subs'!$C$12:$C$47),0) ),0),0),(IF($M195>=IFERROR(INDEX('TaxCred&Subs'!$H$12:$H$47,MATCH(1,($C195&$D195='TaxCred&Subs'!$D$12:$D$47)*($F195='TaxCred&Subs'!$C$12:$C$47),0) ),9999),IFERROR(INDEX('TaxCred&Subs'!$N$12:$N$47,MATCH(1,($C195&$D195='TaxCred&Subs'!$D$12:$D$47)*($F195='TaxCred&Subs'!$C$12:$C$47),0) ),0),0)))),0)+IF(AND($C195=2,VALUE(RIGHT($AD195,1))>2),(N195-R195)*(IFERROR(INDEX('TaxCred&Subs'!$J$66:$J$99,MATCH(1,($C195&$D195='TaxCred&Subs'!$E$66:$E$99)*($F195='TaxCred&Subs'!$C$66:$C$99),0)),0)),IF(AND($C195=1,VALUE(RIGHT($AD195,1))>2),(N195-R195)*(IFERROR(INDEX('TaxCred&Subs'!$J$66:$J$99,MATCH(1,($C195&$D195='TaxCred&Subs'!$D$66:$D$99)*($F195='TaxCred&Subs'!$C$66:$C$99),0)),0)),IF($C195>2,(N195-R195)*(IFERROR(INDEX('TaxCred&Subs'!$J$66:$J$99,MATCH(1,($C195&$D195='TaxCred&Subs'!$D$66:$D$99)*($F195='TaxCred&Subs'!$C$66:$C$99),0)),0)),0))),0)} -> 0 | Q195: {=ROUND(IF(AND($C195=2,VALUE(RIGHT($AD195,1))>2),(O195-S195)*(IFERROR(INDEX('TaxCred&Subs'!$J$66:$J$99,MATCH(1,($C195&$D195='TaxCred&Subs'!$E$66:$E$99)*($F195='TaxCred&Subs'!$C$66:$C$99),0)),0)),IF(AND($C195=1,VALUE(RIGHT($AD195,1))>2),(O195-S195)*(IFERROR(INDEX('TaxCred&Subs'!$J$66:$J$99,MATCH(1,($C195&$D195='TaxCred&Subs'!$D$66:$D$99)*($F195='TaxCred&Subs'!$C$66:$C$99),0)),0)),IF($C195>2,(O195-S195)*(IFERROR(INDEX('TaxCred&Subs'!$J$66:$J$99,MATCH(1,($C195&$D195='TaxCred&Subs'!$D$66:$D$99)*($F195='TaxCred&Subs'!$C$66:$C$99),0)),0)),0))),0)} -> 0 | R195: {=ROUND(IF(IFERROR(VALUE(RIGHT($AD195,1)),0)>2,IF($C195=8,N195*IFERROR(INDEX('TaxCred&Subs'!$K$139:$S$151,MATCH($C195&$D195&LEFT($AD195,7),'TaxCred&Subs'!$E$139:$E$151,0),MATCH($H195,'TaxCred&Subs'!$K$137:$S$137,0)),0),IF($C195=2,N195*IFERROR(INDEX('TaxCred&Subs'!$K$139:$S$151,MATCH($C195&$D195,'TaxCred&Subs'!$D$139:$D$151,0),MATCH($H195,'TaxCred&Subs'!$K$137:$S$137,0)),0),N195*IFERROR(INDEX('TaxCred&Subs'!$K$139:$S$151,MATCH($C195&$D195,'TaxCred&Subs'!$C$139:$C$151,0),MATCH($H195,'TaxCred&Subs'!$K$137:$S$137,0)),0))),0),0)} -> 0 | S195: {=ROUND(IF(IFERROR(VALUE(RIGHT($AD195,1)),0)>2,IF($C195=8,O195*IFERROR(INDEX('TaxCred&Subs'!$K$139:$S$151,MATCH($C195&$D195&LEFT($AD195,7),'TaxCred&Subs'!$E$139:$E$151,0),MATCH($H195,'TaxCred&Subs'!$K$137:$S$137,0)),0),IF($C195=2,O195*IFERROR(INDEX('TaxCred&Subs'!$K$139:$S$151,MATCH($C195&$D195,'TaxCred&Subs'!$D$139:$D$151,0),MATCH($H195,'TaxCred&Subs'!$K$137:$S$137,0)),0),O195*IFERROR(INDEX('TaxCred&Subs'!$K$139:$S$151,MATCH($C195&$D195,'TaxCred&Subs'!$C$139:$C$151,0),MATCH($H195,'TaxCred&Subs'!$K$137:$S$137,0)),0))),0),0)} -> 0 | T195: =IF($H195=9,IF(R195>0,(N195-P195)*0.15,0),0) -> 0 | U195: =IF($H195=9,IF(S195>0,(O195-Q195)*0.15,0),0) -> 0 | V195: MATURE | W195: 2020 | X195: 1 | Y195: 0 | Z195: -0.0001782623 | AA195: -0.0027424969 | AB195: 0 | AC195: 0 | AD195: LPG_FA2
B196: =B195+1 -> 172 | C196: 1 | D196: 6 | E196: 20 | F196: 2020 | G196: 2021 | H196: 1 | I196: 20 | J196: 0 | K196: 0 | L196: 0 | M196: 0.95 | N196: 4150 | O196: 1220 | P196: {=ROUND(IF($F196<='TaxCred&Subs'!$C$49,(IF($C196=2,IF($M196>=IFERROR(INDEX('TaxCred&Subs'!$L$12:$L$47,MATCH(1,($C196&$D196='TaxCred&Subs'!$E$12:$E$47)*($F196='TaxCred&Subs'!$C$12:$C$47),0) ),9999),IFERROR(INDEX('TaxCred&Subs'!$N$12:$N$47,MATCH(1,($C196&$D196='TaxCred&Subs'!$E$12:$E$47)*($F196='TaxCred&Subs'!$C$12:$C$47),0) ),0),0),(IF($M196>=IFERROR(INDEX('TaxCred&Subs'!$H$12:$H$47,MATCH(1,($C196&$D196='TaxCred&Subs'!$D$12:$D$47)*($F196='TaxCred&Subs'!$C$12:$C$47),0) ),9999),IFERROR(INDEX('TaxCred&Subs'!$N$12:$N$47,MATCH(1,($C196&$D196='TaxCred&Subs'!$D$12:$D$47)*($F196='TaxCred&Subs'!$C$12:$C$47),0) ),0),0)))),0)+IF(AND($C196=2,VALUE(RIGHT($AD196,1))>2),(N196-R196)*(IFERROR(INDEX('TaxCred&Subs'!$J$66:$J$99,MATCH(1,($C196&$D196='TaxCred&Subs'!$E$66:$E$99)*($F196='TaxCred&Subs'!$C$66:$C$99),0)),0)),IF(AND($C196=1,VALUE(RIGHT($AD196,1))>2),(N196-R196)*(IFERROR(INDEX('TaxCred&Subs'!$J$66:$J$99,MATCH(1,($C196&$D196='TaxCred&Subs'!$D$66:$D$99)*($F196='TaxCred&Subs'!$C$66:$C$99),0)),0)),IF($C196>2,(N196-R196)*(IFERROR(INDEX('TaxCred&Subs'!$J$66:$J$99,MATCH(1,($C196&$D196='TaxCred&Subs'!$D$66:$D$99)*($F196='TaxCred&Subs'!$C$66:$C$99),0)),0)),0))),0)} -> 150 | Q196: {=ROUND(IF(AND($C196=2,VALUE(RIGHT($AD196,1))>2),(O196-S196)*(IFERROR(INDEX('TaxCred&Subs'!$J$66:$J$99,MATCH(1,($C196&$D196='TaxCred&Subs'!$E$66:$E$99)*($F196='TaxCred&Subs'!$C$66:$C$99),0)),0)),IF(AND($C196=1,VALUE(RIGHT($AD196,1))>2),(O196-S196)*(IFERROR(INDEX('TaxCred&Subs'!$J$66:$J$99,MATCH(1,($C196&$D196='TaxCred&Subs'!$D$66:$D$99)*($F196='TaxCred&Subs'!$C$66:$C$99),0)),0)),IF($C196>2,(O196-S196)*(IFERROR(INDEX('TaxCred&Subs'!$J$66:$J$99,MATCH(1,($C196&$D196='TaxCred&Subs'!$D$66:$D$99)*($F196='TaxCred&Subs'!$C$66:$C$99),0)),0)),0))),0)} -> 0 | R196: {=ROUND(IF(IFERROR(VALUE(RIGHT($AD196,1)),0)>2,IF($C196=8,N196*IFERROR(INDEX('TaxCred&Subs'!$K$139:$S$151,MATCH($C196&$D196&LEFT($AD196,7),'TaxCred&Subs'!$E$139:$E$151,0),MATCH($H196,'TaxCred&Subs'!$K$137:$S$137,0)),0),IF($C196=2,N196*IFERROR(INDEX('TaxCred&Subs'!$K$139:$S$151,MATCH($C196&$D196,'TaxCred&Subs'!$D$139:$D$151,0),MATCH($H196,'TaxCred&Subs'!$K$137:$S$137,0)),0),N196*IFERROR(INDEX('TaxCred&Subs'!$K$139:$S$151,MATCH($C196&$D196,'TaxCred&Subs'!$C$139:$C$151,0),MATCH($H196,'TaxCred&Subs'!$K$137:$S$137,0)),0))),0),0)} -> 0 | S196: {=ROUND(IF(IFERROR(VALUE(RIGHT($AD196,1)),0)>2,IF($C196=8,O196*IFERROR(INDEX('TaxCred&Subs'!$K$139:$S$151,MATCH($C196&$D196&LEFT($AD196,7),'TaxCred&Subs'!$E$139:$E$151,0),MATCH($H196,'TaxCred&Subs'!$K$137:$S$137,0)),0),IF($C196=2,O196*IFERROR(INDEX('TaxCred&Subs'!$K$139:$S$151,MATCH($C196&$D196,'TaxCred&Subs'!$D$139:$D$151,0),MATCH($H196,'TaxCred&Subs'!$K$137:$S$137,0)),0),O196*IFERROR(INDEX('TaxCred&Subs'!$K$139:$S$151,MATCH($C196&$D196,'TaxCred&Subs'!$C$139:$C$151,0),MATCH($H196,'TaxCred&Subs'!$K$137:$S$137,0)),0))),0),0)} -> 0 | T196: =IF($H196=9,IF(R196>0,(N196-P196)*0.15,0),0) -> 0 | U196: =IF($H196=9,IF(S196>0,(O196-Q196)*0.15,0),0) -> 0 | V196: MATURE | W196: 2020 | X196: 1 | Y196: 0 | Z196: -0.00020672359 | AA196: -0.003180363 | AB196: 0 | AC196: 0 | AD196: LPG_FA3
B197: =B196+1 -> 173 | C197: 1 | D197: 6 | E197: 20 | F197: 2020 | G197: 2021 | H197: 2 | I197: 20 | J197: 0 | K197: 0 | L197: 0 | M197: 0.95 | N197: 4150 | O197: 1220 | P197: {=ROUND(IF($F197<='TaxCred&Subs'!$C$49,(IF($C197=2,IF($M197>=IFERROR(INDEX('TaxCred&Subs'!$L$12:$L$47,MATCH(1,($C197&$D197='TaxCred&Subs'!$E$12:$E$47)*($F197='TaxCred&Subs'!$C$12:$C$47),0) ),9999),IFERROR(INDEX('TaxCred&Subs'!$N$12:$N$47,MATCH(1,($C197&$D197='TaxCred&Subs'!$E$12:$E$47)*($F197='TaxCred&Subs'!$C$12:$C$47),0) ),0),0),(IF($M197>=IFERROR(INDEX('TaxCred&Subs'!$H$12:$H$47,MATCH(1,($C197&$D197='TaxCred&Subs'!$D$12:$D$47)*($F197='TaxCred&Subs'!$C$12:$C$47),0) ),9999),IFERROR(INDEX('TaxCred&Subs'!$N$12:$N$47,MATCH(1,($C197&$D197='TaxCred&Subs'!$D$12:$D$47)*($F197='TaxCred&Subs'!$C$12:$C$47),0) ),0),0)))),0)+IF(AND($C197=2,VALUE(RIGHT($AD197,1))>2),(N197-R197)*(IFERROR(INDEX('TaxCred&Subs'!$J$66:$J$99,MATCH(1,($C197&$D197='TaxCred&Subs'!$E$66:$E$99)*($F197='TaxCred&Subs'!$C$66:$C$99),0)),0)),IF(AND($C197=1,VALUE(RIGHT($AD197,1))>2),(N197-R197)*(IFERROR(INDEX('TaxCred&Subs'!$J$66:$J$99,MATCH(1,($C197&$D197='TaxCred&Subs'!$D$66:$D$99)*($F197='TaxCred&Subs'!$C$66:$C$99),0)),0)),IF($C197>2,(N197-R197)*(IFERROR(INDEX('TaxCred&Subs'!$J$66:$J$99,MATCH(1,($C197&$D197='TaxCred&Subs'!$D$66:$D$99)*($F197='TaxCred&Subs'!$C$66:$C$99),0)),0)),0))),0)} -> 150 | Q197: {=ROUND(IF(AND($C197=2,VALUE(RIGHT($AD197,1))>2),(O197-S197)*(IFERROR(INDEX('TaxCred&Subs'!$J$66:$J$99,MATCH(1,($C197&$D197='TaxCred&Subs'!$E$66:$E$99)*($F197='TaxCred&Subs'!$C$66:$C$99),0)),0)),IF(AND($C197=1,VALUE(RIGHT($AD197,1))>2),(O197-S197)*(IFERROR(INDEX('TaxCred&Subs'!$J$66:$J$99,MATCH(1,($C197&$D197='TaxCred&Subs'!$D$66:$D$99)*($F197='TaxCred&Subs'!$C$66:$C$99),0)),0)),IF($C197>2,(O197-S197)*(IFERROR(INDEX('TaxCred&Subs'!$J$66:$J$99,MATCH(1,($C197&$D197='TaxCred&Subs'!$D$66:$D$99)*($F197='TaxCred&Subs'!$C$66:$C$99),0)),0)),0))),0)} -> 0 | R197: {=ROUND(IF(IFERROR(VALUE(RIGHT($AD197,1)),0)>2,IF($C197=8,N197*IFERROR(INDEX('TaxCred&Subs'!$K$139:$S$151,MATCH($C197&$D197&LEFT($AD197,7),'TaxCred&Subs'!$E$139:$E$151,0),MATCH($H197,'TaxCred&Subs'!$K$137:$S$137,0)),0),IF($C197=2,N197*IFERROR(INDEX('TaxCred&Subs'!$K$139:$S$151,MATCH($C197&$D197,'TaxCred&Subs'!$D$139:$D$151,0),MATCH($H197,'TaxCred&Subs'!$K$137:$S$137,0)),0),N197*IFERROR(INDEX('TaxCred&Subs'!$K$139:$S$151,MATCH($C197&$D197,'TaxCred&Subs'!$C$139:$C$151,0),MATCH($H197,'TaxCred&Subs'!$K$137:$S$137,0)),0))),0),0)} -> 0 | S197: {=ROUND(IF(IFERROR(VALUE(RIGHT($AD197,1)),0)>2,IF($C197=8,O197*IFERROR(INDEX('TaxCred&Subs'!$K$139:$S$151,MATCH($C197&$D197&LEFT($AD197,7),'TaxCred&Subs'!$E$139:$E$151,0),MATCH($H197,'TaxCred&Subs'!$K$137:$S$137,0)),0),IF($C197=2,O197*IFERROR(INDEX('TaxCred&Subs'!$K$139:$S$151,MATCH($C197&$D197,'TaxCred&Subs'!$D$139:$D$151,0),MATCH($H197,'TaxCred&Subs'!$K$137:$S$137,0)),0),O197*IFERROR(INDEX('TaxCred&Subs'!$K$139:$S$151,MATCH($C197&$D197,'TaxCred&Subs'!$C$139:$C$151,0),MATCH($H197,'TaxCred&Subs'!$K$137:$S$137,0)),0))),0),0)} -> 0 | T197: =IF($H197=9,IF(R197>0,(N197-P197)*0.15,0),0) -> 0 | U197: =IF($H197=9,IF(S197>0,(O197-Q197)*0.15,0),0) -> 0 | V197: MATURE | W197: 2020 | X197: 1 | Y197: 0 | Z197: -0.00020672359 | AA197: -0.003180363 | AB197: 0 | AC197: 0 | AD197: LPG_FA3
B198: =B197+1 -> 174 | C198: 1 | D198: 6 | E198: 20 | F198: 2020 | G198: 2021 | H198: 3 | I198: 20 | J198: 0 | K198: 0 | L198: 0 | M198: 0.95 | N198: 4150 | O198: 1220 | P198: {=ROUND(IF($F198<='TaxCred&Subs'!$C$49,(IF($C198=2,IF($M198>=IFERROR(INDEX('TaxCred&Subs'!$L$12:$L$47,MATCH(1,($C198&$D198='TaxCred&Subs'!$E$12:$E$47)*($F198='TaxCred&Subs'!$C$12:$C$47),0) ),9999),IFERROR(INDEX('TaxCred&Subs'!$N$12:$N$47,MATCH(1,($C198&$D198='TaxCred&Subs'!$E$12:$E$47)*($F198='TaxCred&Subs'!$C$12:$C$47),0) ),0),0),(IF($M198>=IFERROR(INDEX('TaxCred&Subs'!$H$12:$H$47,MATCH(1,($C198&$D198='TaxCred&Subs'!$D$12:$D$47)*($F198='TaxCred&Subs'!$C$12:$C$47),0) ),9999),IFERROR(INDEX('TaxCred&Subs'!$N$12:$N$47,MATCH(1,($C198&$D198='TaxCred&Subs'!$D$12:$D$47)*($F198='TaxCred&Subs'!$C$12:$C$47),0) ),0),0)))),0)+IF(AND($C198=2,VALUE(RIGHT($AD198,1))>2),(N198-R198)*(IFERROR(INDEX('TaxCred&Subs'!$J$66:$J$99,MATCH(1,($C198&$D198='TaxCred&Subs'!$E$66:$E$99)*($F198='TaxCred&Subs'!$C$66:$C$99),0)),0)),IF(AND($C198=1,VALUE(RIGHT($AD198,1))>2),(N198-R198)*(IFERROR(INDEX('TaxCred&Subs'!$J$66:$J$99,MATCH(1,($C198&$D198='TaxCred&Subs'!$D$66:$D$99)*($F198='TaxCred&Subs'!$C$66:$C$99),0)),0)),IF($C198>2,(N198-R198)*(IFERROR(INDEX('TaxCred&Subs'!$J$66:$J$99,MATCH(1,($C198&$D198='TaxCred&Subs'!$D$66:$D$99)*($F198='TaxCred&Subs'!$C$66:$C$99),0)),0)),0))),0)} -> 150 | Q198: {=ROUND(IF(AND($C198=2,VALUE(RIGHT($AD198,1))>2),(O198-S198)*(IFERROR(INDEX('TaxCred&Subs'!$J$66:$J$99,MATCH(1,($C198&$D198='TaxCred&Subs'!$E$66:$E$99)*($F198='TaxCred&Subs'!$C$66:$C$99),0)),0)),IF(AND($C198=1,VALUE(RIGHT($AD198,1))>2),(O198-S198)*(IFERROR(INDEX('TaxCred&Subs'!$J$66:$J$99,MATCH(1,($C198&$D198='TaxCred&Subs'!$D$66:$D$99)*($F198='TaxCred&Subs'!$C$66:$C$99),0)),0)),IF($C198>2,(O198-S198)*(IFERROR(INDEX('TaxCred&Subs'!$J$66:$J$99,MATCH(1,($C198&$D198='TaxCred&Subs'!$D$66:$D$99)*($F198='TaxCred&Subs'!$C$66:$C$99),0)),0)),0))),0)} -> 0 | R198: {=ROUND(IF(IFERROR(VALUE(RIGHT($AD198,1)),0)>2,IF($C198=8,N198*IFERROR(INDEX('TaxCred&Subs'!$K$139:$S$151,MATCH($C198&$D198&LEFT($AD198,7),'TaxCred&Subs'!$E$139:$E$151,0),MATCH($H198,'TaxCred&Subs'!$K$137:$S$137,0)),0),IF($C198=2,N198*IFERROR(INDEX('TaxCred&Subs'!$K$139:$S$151,MATCH($C198&$D198,'TaxCred&Subs'!$D$139:$D$151,0),MATCH($H198,'TaxCred&Subs'!$K$137:$S$137,0)),0),N198*IFERROR(INDEX('TaxCred&Subs'!$K$139:$S$151,MATCH($C198&$D198,'TaxCred&Subs'!$C$139:$C$151,0),MATCH($H198,'TaxCred&Subs'!$K$137:$S$137,0)),0))),0),0)} -> 0 | S198: {=ROUND(IF(IFERROR(VALUE(RIGHT($AD198,1)),0)>2,IF($C198=8,O198*IFERROR(INDEX('TaxCred&Subs'!$K$139:$S$151,MATCH($C198&$D198&LEFT($AD198,7),'TaxCred&Subs'!$E$139:$E$151,0),MATCH($H198,'TaxCred&Subs'!$K$137:$S$137,0)),0),IF($C198=2,O198*IFERROR(INDEX('TaxCred&Subs'!$K$139:$S$151,MATCH($C198&$D198,'TaxCred&Subs'!$D$139:$D$151,0),MATCH($H198,'TaxCred&Subs'!$K$137:$S$137,0)),0),O198*IFERROR(INDEX('TaxCred&Subs'!$K$139:$S$151,MATCH($C198&$D198,'TaxCred&Subs'!$C$139:$C$151,0),MATCH($H198,'TaxCred&Subs'!$K$137:$S$137,0)),0))),0),0)} -> 0 | T198: =IF($H198=9,IF(R198>0,(N198-P198)*0.15,0),0) -> 0 | U198: =IF($H198=9,IF(S198>0,(O198-Q198)*0.15,0),0) -> 0 | V198: MATURE | W198: 2020 | X198: 1 | Y198: 0 | Z198: -0.00020672359 | AA198: -0.003180363 | AB198: 0 | AC198: 0 | AD198: LPG_FA3
B199: =B198+1 -> 175 | C199: 1 | D199: 6 | E199: 20 | F199: 2020 | G199: 2021 | H199: 4 | I199: 20 | J199: 0 | K199: 0 | L199: 0 | M199: 0.95 | N199: 4150 | O199: 1220 | P199: {=ROUND(IF($F199<='TaxCred&Subs'!$C$49,(IF($C199=2,IF($M199>=IFERROR(INDEX('TaxCred&Subs'!$L$12:$L$47,MATCH(1,($C199&$D199='TaxCred&Subs'!$E$12:$E$47)*($F199='TaxCred&Subs'!$C$12:$C$47),0) ),9999),IFERROR(INDEX('TaxCred&Subs'!$N$12:$N$47,MATCH(1,($C199&$D199='TaxCred&Subs'!$E$12:$E$47)*($F199='TaxCred&Subs'!$C$12:$C$47),0) ),0),0),(IF($M199>=IFERROR(INDEX('TaxCred&Subs'!$H$12:$H$47,MATCH(1,($C199&$D199='TaxCred&Subs'!$D$12:$D$47)*($F199='TaxCred&Subs'!$C$12:$C$47),0) ),9999),IFERROR(INDEX('TaxCred&Subs'!$N$12:$N$47,MATCH(1,($C199&$D199='TaxCred&Subs'!$D$12:$D$47)*($F199='TaxCred&Subs'!$C$12:$C$47),0) ),0),0)))),0)+IF(AND($C199=2,VALUE(RIGHT($AD199,1))>2),(N199-R199)*(IFERROR(INDEX('TaxCred&Subs'!$J$66:$J$99,MATCH(1,($C199&$D199='TaxCred&Subs'!$E$66:$E$99)*($F199='TaxCred&Subs'!$C$66:$C$99),0)),0)),IF(AND($C199=1,VALUE(RIGHT($AD199,1))>2),(N199-R199)*(IFERROR(INDEX('TaxCred&Subs'!$J$66:$J$99,MATCH(1,($C199&$D199='TaxCred&Subs'!$D$66:$D$99)*($F199='TaxCred&Subs'!$C$66:$C$99),0)),0)),IF($C199>2,(N199-R199)*(IFERROR(INDEX('TaxCred&Subs'!$J$66:$J$99,MATCH(1,($C199&$D199='TaxCred&Subs'!$D$66:$D$99)*($F199='TaxCred&Subs'!$C$66:$C$99),0)),0)),0))),0)} -> 150 | Q199: {=ROUND(IF(AND($C199=2,VALUE(RIGHT($AD199,1))>2),(O199-S199)*(IFERROR(INDEX('TaxCred&Subs'!$J$66:$J$99,MATCH(1,($C199&$D199='TaxCred&Subs'!$E$66:$E$99)*($F199='TaxCred&Subs'!$C$66:$C$99),0)),0)),IF(AND($C199=1,VALUE(RIGHT($AD199,1))>2),(O199-S199)*(IFERROR(INDEX('TaxCred&Subs'!$J$66:$J$99,MATCH(1,($C199&$D199='TaxCred&Subs'!$D$66:$D$99)*($F199='TaxCred&Subs'!$C$66:$C$99),0)),0)),IF($C199>2,(O199-S199)*(IFERROR(INDEX('TaxCred&Subs'!$J$66:$J$99,MATCH(1,($C199&$D199='TaxCred&Subs'!$D$66:$D$99)*($F199='TaxCred&Subs'!$C$66:$C$99),0)),0)),0))),0)} -> 0 | R199: {=ROUND(IF(IFERROR(VALUE(RIGHT($AD199,1)),0)>2,IF($C199=8,N199*IFERROR(INDEX('TaxCred&Subs'!$K$139:$S$151,MATCH($C199&$D199&LEFT($AD199,7),'TaxCred&Subs'!$E$139:$E$151,0),MATCH($H199,'TaxCred&Subs'!$K$137:$S$137,0)),0),IF($C199=2,N199*IFERROR(INDEX('TaxCred&Subs'!$K$139:$S$151,MATCH($C199&$D199,'TaxCred&Subs'!$D$139:$D$151,0),MATCH($H199,'TaxCred&Subs'!$K$137:$S$137,0)),0),N199*IFERROR(INDEX('TaxCred&Subs'!$K$139:$S$151,MATCH($C199&$D199,'TaxCred&Subs'!$C$139:$C$151,0),MATCH($H199,'TaxCred&Subs'!$K$137:$S$137,0)),0))),0),0)} -> 0 | S199: {=ROUND(IF(IFERROR(VALUE(RIGHT($AD199,1)),0)>2,IF($C199=8,O199*IFERROR(INDEX('TaxCred&Subs'!$K$139:$S$151,MATCH($C199&$D199&LEFT($AD199,7),'TaxCred&Subs'!$E$139:$E$151,0),MATCH($H199,'TaxCred&Subs'!$K$137:$S$137,0)),0),IF($C199=2,O199*IFERROR(INDEX('TaxCred&Subs'!$K$139:$S$151,MATCH($C199&$D199,'TaxCred&Subs'!$D$139:$D$151,0),MATCH($H199,'TaxCred&Subs'!$K$137:$S$137,0)),0),O199*IFERROR(INDEX('TaxCred&Subs'!$K$139:$S$151,MATCH($C199&$D199,'TaxCred&Subs'!$C$139:$C$151,0),MATCH($H199,'TaxCred&Subs'!$K$137:$S$137,0)),0))),0),0)} -> 0 | T199: =IF($H199=9,IF(R199>0,(N199-P199)*0.15,0),0) -> 0 | U199: =IF($H199=9,IF(S199>0,(O199-Q199)*0.15,0),0) -> 0 | V199: MATURE | W199: 2020 | X199: 1 | Y199: 0 | Z199: -0.00020672359 | AA199: -0.003180363 | AB199: 0 | AC199: 0 | AD199: LPG_FA3
B200: =B199+1 -> 176 | C200: 1 | D200: 6 | E200: 20 | F200: 2020 | G200: 2021 | H200: 5 | I200: 20 | J200: 0 | K200: 0 | L200: 0 | M200: 0.9 | N200: 4130 | O200: 1200 | P200: {=ROUND(IF($F200<='TaxCred&Subs'!$C$49,(IF($C200=2,IF($M200>=IFERROR(INDEX('TaxCred&Subs'!$L$12:$L$47,MATCH(1,($C200&$D200='TaxCred&Subs'!$E$12:$E$47)*($F200='TaxCred&Subs'!$C$12:$C$47),0) ),9999),IFERROR(INDEX('TaxCred&Subs'!$N$12:$N$47,MATCH(1,($C200&$D200='TaxCred&Subs'!$E$12:$E$47)*($F200='TaxCred&Subs'!$C$12:$C$47),0) ),0),0),(IF($M200>=IFERROR(INDEX('TaxCred&Subs'!$H$12:$H$47,MATCH(1,($C200&$D200='TaxCred&Subs'!$D$12:$D$47)*($F200='TaxCred&Subs'!$C$12:$C$47),0) ),9999),IFERROR(INDEX('TaxCred&Subs'!$N$12:$N$47,MATCH(1,($C200&$D200='TaxCred&Subs'!$D$12:$D$47)*($F200='TaxCred&Subs'!$C$12:$C$47),0) ),0),0)))),0)+IF(AND($C200=2,VALUE(RIGHT($AD200,1))>2),(N200-R200)*(IFERROR(INDEX('TaxCred&Subs'!$J$66:$J$99,MATCH(1,($C200&$D200='TaxCred&Subs'!$E$66:$E$99)*($F200='TaxCred&Subs'!$C$66:$C$99),0)),0)),IF(AND($C200=1,VALUE(RIGHT($AD200,1))>2),(N200-R200)*(IFERROR(INDEX('TaxCred&Subs'!$J$66:$J$99,MATCH(1,($C200&$D200='TaxCred&Subs'!$D$66:$D$99)*($F200='TaxCred&Subs'!$C$66:$C$99),0)),0)),IF($C200>2,(N200-R200)*(IFERROR(INDEX('TaxCred&Subs'!$J$66:$J$99,MATCH(1,($C200&$D200='TaxCred&Subs'!$D$66:$D$99)*($F200='TaxCred&Subs'!$C$66:$C$99),0)),0)),0))),0)} -> 0 | Q200: {=ROUND(IF(AND($C200=2,VALUE(RIGHT($AD200,1))>2),(O200-S200)*(IFERROR(INDEX('TaxCred&Subs'!$J$66:$J$99,MATCH(1,($C200&$D200='TaxCred&Subs'!$E$66:$E$99)*($F200='TaxCred&Subs'!$C$66:$C$99),0)),0)),IF(AND($C200=1,VALUE(RIGHT($AD200,1))>2),(O200-S200)*(IFERROR(INDEX('TaxCred&Subs'!$J$66:$J$99,MATCH(1,($C200&$D200='TaxCred&Subs'!$D$66:$D$99)*($F200='TaxCred&Subs'!$C$66:$C$99),0)),0)),IF($C200>2,(O200-S200)*(IFERROR(INDEX('TaxCred&Subs'!$J$66:$J$99,MATCH(1,($C200&$D200='TaxCred&Subs'!$D$66:$D$99)*($F200='TaxCred&Subs'!$C$66:$C$99),0)),0)),0))),0)} -> 0 | R200: {=ROUND(IF(IFERROR(VALUE(RIGHT($AD200,1)),0)>2,IF($C200=8,N200*IFERROR(INDEX('TaxCred&Subs'!$K$139:$S$151,MATCH($C200&$D200&LEFT($AD200,7),'TaxCred&Subs'!$E$139:$E$151,0),MATCH($H200,'TaxCred&Subs'!$K$137:$S$137,0)),0),IF($C200=2,N200*IFERROR(INDEX('TaxCred&Subs'!$K$139:$S$151,MATCH($C200&$D200,'TaxCred&Subs'!$D$139:$D$151,0),MATCH($H200,'TaxCred&Subs'!$K$137:$S$137,0)),0),N200*IFERROR(INDEX('TaxCred&Subs'!$K$139:$S$151,MATCH($C200&$D200,'TaxCred&Subs'!$C$139:$C$151,0),MATCH($H200,'TaxCred&Subs'!$K$137:$S$137,0)),0))),0),0)} -> 0 | S200: {=ROUND(IF(IFERROR(VALUE(RIGHT($AD200,1)),0)>2,IF($C200=8,O200*IFERROR(INDEX('TaxCred&Subs'!$K$139:$S$151,MATCH($C200&$D200&LEFT($AD200,7),'TaxCred&Subs'!$E$139:$E$151,0),MATCH($H200,'TaxCred&Subs'!$K$137:$S$137,0)),0),IF($C200=2,O200*IFERROR(INDEX('TaxCred&Subs'!$K$139:$S$151,MATCH($C200&$D200,'TaxCred&Subs'!$D$139:$D$151,0),MATCH($H200,'TaxCred&Subs'!$K$137:$S$137,0)),0),O200*IFERROR(INDEX('TaxCred&Subs'!$K$139:$S$151,MATCH($C200&$D200,'TaxCred&Subs'!$C$139:$C$151,0),MATCH($H200,'TaxCred&Subs'!$K$137:$S$137,0)),0))),0),0)} -> 0 | T200: =IF($H200=9,IF(R200>0,(N200-P200)*0.15,0),0) -> 0 | U200: =IF($H200=9,IF(S200>0,(O200-Q200)*0.15,0),0) -> 0 | V200: MATURE | W200: 2020 | X200: 1 | Y200: 0 | Z200: -0.00020672359 | AA200: -0.003180363 | AB200: 0 | AC200: 0 | AD200: LPG_FA3
B201: =B200+1 -> 177 | C201: 1 | D201: 6 | E201: 20 | F201: 2020 | G201: 2021 | H201: 6 | I201: 20 | J201: 0 | K201: 0 | L201: 0 | M201: 0.9 | N201: 4130 | O201: 1200 | P201: {=ROUND(IF($F201<='TaxCred&Subs'!$C$49,(IF($C201=2,IF($M201>=IFERROR(INDEX('TaxCred&Subs'!$L$12:$L$47,MATCH(1,($C201&$D201='TaxCred&Subs'!$E$12:$E$47)*($F201='TaxCred&Subs'!$C$12:$C$47),0) ),9999),IFERROR(INDEX('TaxCred&Subs'!$N$12:$N$47,MATCH(1,($C201&$D201='TaxCred&Subs'!$E$12:$E$47)*($F201='TaxCred&Subs'!$C$12:$C$47),0) ),0),0),(IF($M201>=IFERROR(INDEX('TaxCred&Subs'!$H$12:$H$47,MATCH(1,($C201&$D201='TaxCred&Subs'!$D$12:$D$47)*($F201='TaxCred&Subs'!$C$12:$C$47),0) ),9999),IFERROR(INDEX('TaxCred&Subs'!$N$12:$N$47,MATCH(1,($C201&$D201='TaxCred&Subs'!$D$12:$D$47)*($F201='TaxCred&Subs'!$C$12:$C$47),0) ),0),0)))),0)+IF(AND($C201=2,VALUE(RIGHT($AD201,1))>2),(N201-R201)*(IFERROR(INDEX('TaxCred&Subs'!$J$66:$J$99,MATCH(1,($C201&$D201='TaxCred&Subs'!$E$66:$E$99)*($F201='TaxCred&Subs'!$C$66:$C$99),0)),0)),IF(AND($C201=1,VALUE(RIGHT($AD201,1))>2),(N201-R201)*(IFERROR(INDEX('TaxCred&Subs'!$J$66:$J$99,MATCH(1,($C201&$D201='TaxCred&Subs'!$D$66:$D$99)*($F201='TaxCred&Subs'!$C$66:$C$99),0)),0)),IF($C201>2,(N201-R201)*(IFERROR(INDEX('TaxCred&Subs'!$J$66:$J$99,MATCH(1,($C201&$D201='TaxCred&Subs'!$D$66:$D$99)*($F201='TaxCred&Subs'!$C$66:$C$99),0)),0)),0))),0)} -> 0 | Q201: {=ROUND(IF(AND($C201=2,VALUE(RIGHT($AD201,1))>2),(O201-S201)*(IFERROR(INDEX('TaxCred&Subs'!$J$66:$J$99,MATCH(1,($C201&$D201='TaxCred&Subs'!$E$66:$E$99)*($F201='TaxCred&Subs'!$C$66:$C$99),0)),0)),IF(AND($C201=1,VALUE(RIGHT($AD201,1))>2),(O201-S201)*(IFERROR(INDEX('TaxCred&Subs'!$J$66:$J$99,MATCH(1,($C201&$D201='TaxCred&Subs'!$D$66:$D$99)*($F201='TaxCred&Subs'!$C$66:$C$99),0)),0)),IF($C201>2,(O201-S201)*(IFERROR(INDEX('TaxCred&Subs'!$J$66:$J$99,MATCH(1,($C201&$D201='TaxCred&Subs'!$D$66:$D$99)*($F201='TaxCred&Subs'!$C$66:$C$99),0)),0)),0))),0)} -> 0 | R201: {=ROUND(IF(IFERROR(VALUE(RIGHT($AD201,1)),0)>2,IF($C201=8,N201*IFERROR(INDEX('TaxCred&Subs'!$K$139:$S$151,MATCH($C201&$D201&LEFT($AD201,7),'TaxCred&Subs'!$E$139:$E$151,0),MATCH($H201,'TaxCred&Subs'!$K$137:$S$137,0)),0),IF($C201=2,N201*IFERROR(INDEX('TaxCred&Subs'!$K$139:$S$151,MATCH($C201&$D201,'TaxCred&Subs'!$D$139:$D$151,0),MATCH($H201,'TaxCred&Subs'!$K$137:$S$137,0)),0),N201*IFERROR(INDEX('TaxCred&Subs'!$K$139:$S$151,MATCH($C201&$D201,'TaxCred&Subs'!$C$139:$C$151,0),MATCH($H201,'TaxCred&Subs'!$K$137:$S$137,0)),0))),0),0)} -> 0 | S201: {=ROUND(IF(IFERROR(VALUE(RIGHT($AD201,1)),0)>2,IF($C201=8,O201*IFERROR(INDEX('TaxCred&Subs'!$K$139:$S$151,MATCH($C201&$D201&LEFT($AD201,7),'TaxCred&Subs'!$E$139:$E$151,0),MATCH($H201,'TaxCred&Subs'!$K$137:$S$137,0)),0),IF($C201=2,O201*IFERROR(INDEX('TaxCred&Subs'!$K$139:$S$151,MATCH($C201&$D201,'TaxCred&Subs'!$D$139:$D$151,0),MATCH($H201,'TaxCred&Subs'!$K$137:$S$137,0)),0),O201*IFERROR(INDEX('TaxCred&Subs'!$K$139:$S$151,MATCH($C201&$D201,'TaxCred&Subs'!$C$139:$C$151,0),MATCH($H201,'TaxCred&Subs'!$K$137:$S$137,0)),0))),0),0)} -> 0 | T201: =IF($H201=9,IF(R201>0,(N201-P201)*0.15,0),0) -> 0 | U201: =IF($H201=9,IF(S201>0,(O201-Q201)*0.15,0),0) -> 0 | V201: MATURE | W201: 2020 | X201: 1 | Y201: 0 | Z201: -0.00020672359 | AA201: -0.003180363 | AB201: 0 | AC201: 0 | AD201: LPG_FA3
B202: =B201+1 -> 178 | C202: 1 | D202: 6 | E202: 20 | F202: 2020 | G202: 2021 | H202: 7 | I202: 20 | J202: 0 | K202: 0 | L202: 0 | M202: 0.9 | N202: 4130 | O202: 1200 | P202: {=ROUND(IF($F202<='TaxCred&Subs'!$C$49,(IF($C202=2,IF($M202>=IFERROR(INDEX('TaxCred&Subs'!$L$12:$L$47,MATCH(1,($C202&$D202='TaxCred&Subs'!$E$12:$E$47)*($F202='TaxCred&Subs'!$C$12:$C$47),0) ),9999),IFERROR(INDEX('TaxCred&Subs'!$N$12:$N$47,MATCH(1,($C202&$D202='TaxCred&Subs'!$E$12:$E$47)*($F202='TaxCred&Subs'!$C$12:$C$47),0) ),0),0),(IF($M202>=IFERROR(INDEX('TaxCred&Subs'!$H$12:$H$47,MATCH(1,($C202&$D202='TaxCred&Subs'!$D$12:$D$47)*($F202='TaxCred&Subs'!$C$12:$C$47),0) ),9999),IFERROR(INDEX('TaxCred&Subs'!$N$12:$N$47,MATCH(1,($C202&$D202='TaxCred&Subs'!$D$12:$D$47)*($F202='TaxCred&Subs'!$C$12:$C$47),0) ),0),0)))),0)+IF(AND($C202=2,VALUE(RIGHT($AD202,1))>2),(N202-R202)*(IFERROR(INDEX('TaxCred&Subs'!$J$66:$J$99,MATCH(1,($C202&$D202='TaxCred&Subs'!$E$66:$E$99)*($F202='TaxCred&Subs'!$C$66:$C$99),0)),0)),IF(AND($C202=1,VALUE(RIGHT($AD202,1))>2),(N202-R202)*(IFERROR(INDEX('TaxCred&Subs'!$J$66:$J$99,MATCH(1,($C202&$D202='TaxCred&Subs'!$D$66:$D$99)*($F202='TaxCred&Subs'!$C$66:$C$99),0)),0)),IF($C202>2,(N202-R202)*(IFERROR(INDEX('TaxCred&Subs'!$J$66:$J$99,MATCH(1,($C202&$D202='TaxCred&Subs'!$D$66:$D$99)*($F202='TaxCred&Subs'!$C$66:$C$99),0)),0)),0))),0)} -> 0 | Q202: {=ROUND(IF(AND($C202=2,VALUE(RIGHT($AD202,1))>2),(O202-S202)*(IFERROR(INDEX('TaxCred&Subs'!$J$66:$J$99,MATCH(1,($C202&$D202='TaxCred&Subs'!$E$66:$E$99)*($F202='TaxCred&Subs'!$C$66:$C$99),0)),0)),IF(AND($C202=1,VALUE(RIGHT($AD202,1))>2),(O202-S202)*(IFERROR(INDEX('TaxCred&Subs'!$J$66:$J$99,MATCH(1,($C202&$D202='TaxCred&Subs'!$D$66:$D$99)*($F202='TaxCred&Subs'!$C$66:$C$99),0)),0)),IF($C202>2,(O202-S202)*(IFERROR(INDEX('TaxCred&Subs'!$J$66:$J$99,MATCH(1,($C202&$D202='TaxCred&Subs'!$D$66:$D$99)*($F202='TaxCred&Subs'!$C$66:$C$99),0)),0)),0))),0)} -> 0 | R202: {=ROUND(IF(IFERROR(VALUE(RIGHT($AD202,1)),0)>2,IF($C202=8,N202*IFERROR(INDEX('TaxCred&Subs'!$K$139:$S$151,MATCH($C202&$D202&LEFT($AD202,7),'TaxCred&Subs'!$E$139:$E$151,0),MATCH($H202,'TaxCred&Subs'!$K$137:$S$137,0)),0),IF($C202=2,N202*IFERROR(INDEX('TaxCred&Subs'!$K$139:$S$151,MATCH($C202&$D202,'TaxCred&Subs'!$D$139:$D$151,0),MATCH($H202,'TaxCred&Subs'!$K$137:$S$137,0)),0),N202*IFERROR(INDEX('TaxCred&Subs'!$K$139:$S$151,MATCH($C202&$D202,'TaxCred&Subs'!$C$139:$C$151,0),MATCH($H202,'TaxCred&Subs'!$K$137:$S$137,0)),0))),0),0)} -> 0 | S202: {=ROUND(IF(IFERROR(VALUE(RIGHT($AD202,1)),0)>2,IF($C202=8,O202*IFERROR(INDEX('TaxCred&Subs'!$K$139:$S$151,MATCH($C202&$D202&LEFT($AD202,7),'TaxCred&Subs'!$E$139:$E$151,0),MATCH($H202,'TaxCred&Subs'!$K$137:$S$137,0)),0),IF($C202=2,O202*IFERROR(INDEX('TaxCred&Subs'!$K$139:$S$151,MATCH($C202&$D202,'TaxCred&Subs'!$D$139:$D$151,0),MATCH($H202,'TaxCred&Subs'!$K$137:$S$137,0)),0),O202*IFERROR(INDEX('TaxCred&Subs'!$K$139:$S$151,MATCH($C202&$D202,'TaxCred&Subs'!$C$139:$C$151,0),MATCH($H202,'TaxCred&Subs'!$K$137:$S$137,0)),0))),0),0)} -> 0 | T202: =IF($H202=9,IF(R202>0,(N202-P202)*0.15,0),0) -> 0 | U202: =IF($H202=9,IF(S202>0,(O202-Q202)*0.15,0),0) -> 0 | V202: MATURE | W202: 2020 | X202: 1 | Y202: 0 | Z202: -0.00020672359 | AA202: -0.003180363 | AB202: 0 | AC202: 0 | AD202: LPG_FA3
B203: =B202+1 -> 179 | C203: 1 | D203: 6 | E203: 20 | F203: 2020 | G203: 2021 | H203: 8 | I203: 20 | J203: 0 | K203: 0 | L203: 0 | M203: 0.9 | N203: 4130 | O203: 1200 | P203: {=ROUND(IF($F203<='TaxCred&Subs'!$C$49,(IF($C203=2,IF($M203>=IFERROR(INDEX('TaxCred&Subs'!$L$12:$L$47,MATCH(1,($C203&$D203='TaxCred&Subs'!$E$12:$E$47)*($F203='TaxCred&Subs'!$C$12:$C$47),0) ),9999),IFERROR(INDEX('TaxCred&Subs'!$N$12:$N$47,MATCH(1,($C203&$D203='TaxCred&Subs'!$E$12:$E$47)*($F203='TaxCred&Subs'!$C$12:$C$47),0) ),0),0),(IF($M203>=IFERROR(INDEX('TaxCred&Subs'!$H$12:$H$47,MATCH(1,($C203&$D203='TaxCred&Subs'!$D$12:$D$47)*($F203='TaxCred&Subs'!$C$12:$C$47),0) ),9999),IFERROR(INDEX('TaxCred&Subs'!$N$12:$N$47,MATCH(1,($C203&$D203='TaxCred&Subs'!$D$12:$D$47)*($F203='TaxCred&Subs'!$C$12:$C$47),0) ),0),0)))),0)+IF(AND($C203=2,VALUE(RIGHT($AD203,1))>2),(N203-R203)*(IFERROR(INDEX('TaxCred&Subs'!$J$66:$J$99,MATCH(1,($C203&$D203='TaxCred&Subs'!$E$66:$E$99)*($F203='TaxCred&Subs'!$C$66:$C$99),0)),0)),IF(AND($C203=1,VALUE(RIGHT($AD203,1))>2),(N203-R203)*(IFERROR(INDEX('TaxCred&Subs'!$J$66:$J$99,MATCH(1,($C203&$D203='TaxCred&Subs'!$D$66:$D$99)*($F203='TaxCred&Subs'!$C$66:$C$99),0)),0)),IF($C203>2,(N203-R203)*(IFERROR(INDEX('TaxCred&Subs'!$J$66:$J$99,MATCH(1,($C203&$D203='TaxCred&Subs'!$D$66:$D$99)*($F203='TaxCred&Subs'!$C$66:$C$99),0)),0)),0))),0)} -> 0 | Q203: {=ROUND(IF(AND($C203=2,VALUE(RIGHT($AD203,1))>2),(O203-S203)*(IFERROR(INDEX('TaxCred&Subs'!$J$66:$J$99,MATCH(1,($C203&$D203='TaxCred&Subs'!$E$66:$E$99)*($F203='TaxCred&Subs'!$C$66:$C$99),0)),0)),IF(AND($C203=1,VALUE(RIGHT($AD203,1))>2),(O203-S203)*(IFERROR(INDEX('TaxCred&Subs'!$J$66:$J$99,MATCH(1,($C203&$D203='TaxCred&Subs'!$D$66:$D$99)*($F203='TaxCred&Subs'!$C$66:$C$99),0)),0)),IF($C203>2,(O203-S203)*(IFERROR(INDEX('TaxCred&Subs'!$J$66:$J$99,MATCH(1,($C203&$D203='TaxCred&Subs'!$D$66:$D$99)*($F203='TaxCred&Subs'!$C$66:$C$99),0)),0)),0))),0)} -> 0 | R203: {=ROUND(IF(IFERROR(VALUE(RIGHT($AD203,1)),0)>2,IF($C203=8,N203*IFERROR(INDEX('TaxCred&Subs'!$K$139:$S$151,MATCH($C203&$D203&LEFT($AD203,7),'TaxCred&Subs'!$E$139:$E$151,0),MATCH($H203,'TaxCred&Subs'!$K$137:$S$137,0)),0),IF($C203=2,N203*IFERROR(INDEX('TaxCred&Subs'!$K$139:$S$151,MATCH($C203&$D203,'TaxCred&Subs'!$D$139:$D$151,0),MATCH($H203,'TaxCred&Subs'!$K$137:$S$137,0)),0),N203*IFERROR(INDEX('TaxCred&Subs'!$K$139:$S$151,MATCH($C203&$D203,'TaxCred&Subs'!$C$139:$C$151,0),MATCH($H203,'TaxCred&Subs'!$K$137:$S$137,0)),0))),0),0)} -> 0 | S203: {=ROUND(IF(IFERROR(VALUE(RIGHT($AD203,1)),0)>2,IF($C203=8,O203*IFERROR(INDEX('TaxCred&Subs'!$K$139:$S$151,MATCH($C203&$D203&LEFT($AD203,7),'TaxCred&Subs'!$E$139:$E$151,0),MATCH($H203,'TaxCred&Subs'!$K$137:$S$137,0)),0),IF($C203=2,O203*IFERROR(INDEX('TaxCred&Subs'!$K$139:$S$151,MATCH($C203&$D203,'TaxCred&Subs'!$D$139:$D$151,0),MATCH($H203,'TaxCred&Subs'!$K$137:$S$137,0)),0),O203*IFERROR(INDEX('TaxCred&Subs'!$K$139:$S$151,MATCH($C203&$D203,'TaxCred&Subs'!$C$139:$C$151,0),MATCH($H203,'TaxCred&Subs'!$K$137:$S$137,0)),0))),0),0)} -> 0 | T203: =IF($H203=9,IF(R203>0,(N203-P203)*0.15,0),0) -> 0 | U203: =IF($H203=9,IF(S203>0,(O203-Q203)*0.15,0),0) -> 0 | V203: MATURE | W203: 2020 | X203: 1 | Y203: 0 | Z203: -0.00020672359 | AA203: -0.003180363 | AB203: 0 | AC203: 0 | AD203: LPG_FA3
... B213: =B212+1 -> 189 | C213: 1 | D213: 6 | E213: 20 | F213: 2022 | G213: 2028 | H213: 9 | I213: 20 | J213: 0 | K213: 0 | L213: 0 | M213: 0.9 | N213: 4130 | O213: 1200 | P213: {=ROUND(IF($F213<='TaxCred&Subs'!$C$49,(IF($C213=2,IF($M213>=IFERROR(INDEX('TaxCred&Subs'!$L$12:$L$47,MATCH(1,($C213&$D213='TaxCred&Subs'!$E$12:$E$47)*($F213='TaxCred&Subs'!$C$12:$C$47),0) ),9999),IFERROR(INDEX('TaxCred&Subs'!$N$12:$N$47,MATCH(1,($C213&$D213='TaxCred&Subs'!$E$12:$E$47)*($F213='TaxCred&Subs'!$C$12:$C$47),0) ),0),0),(IF($M213>=IFERROR(INDEX('TaxCred&Subs'!$H$12:$H$47,MATCH(1,($C213&$D213='TaxCred&Subs'!$D$12:$D$47)*($F213='TaxCred&Subs'!$C$12:$C$47),0) ),9999),IFERROR(INDEX('TaxCred&Subs'!$N$12:$N$47,MATCH(1,($C213&$D213='TaxCred&Subs'!$D$12:$D$47)*($F213='TaxCred&Subs'!$C$12:$C$47),0) ),0),0)))),0)+IF(AND($C213=2,VALUE(RIGHT($AD213,1))>2),(N213-R213)*(IFERROR(INDEX('TaxCred&Subs'!$J$66:$J$99,MATCH(1,($C213&$D213='TaxCred&Subs'!$E$66:$E$99)*($F213='TaxCred&Subs'!$C$66:$C$99),0)),0)),IF(AND($C213=1,VALUE(RIGHT($AD213,1))>2),(N213-R213)*(IFERROR(INDEX('TaxCred&Subs'!$J$66:$J$99,MATCH(1,($C213&$D213='TaxCred&Subs'!$D$66:$D$99)*($F213='TaxCred&Subs'!$C$66:$C$99),0)),0)),IF($C213>2,(N213-R213)*(IFERROR(INDEX('TaxCred&Subs'!$J$66:$J$99,MATCH(1,($C213&$D213='TaxCred&Subs'!$D$66:$D$99)*($F213='TaxCred&Subs'!$C$66:$C$99),0)),0)),0))),0)} -> 0 | Q213: {=ROUND(IF(AND($C213=2,VALUE(RIGHT($AD213,1))>2),(O213-S213)*(IFERROR(INDEX('TaxCred&Subs'!$J$66:$J$99,MATCH(1,($C213&$D213='TaxCred&Subs'!$E$66:$E$99)*($F213='TaxCred&Subs'!$C$66:$C$99),0)),0)),IF(AND($C213=1,VALUE(RIGHT($AD213,1))>2),(O213-S213)*(IFERROR(INDEX('TaxCred&Subs'!$J$66:$J$99,MATCH(1,($C213&$D213='TaxCred&Subs'!$D$66:$D$99)*($F213='TaxCred&Subs'!$C$66:$C$99),0)),0)),IF($C213>2,(O213-S213)*(IFERROR(INDEX('TaxCred&Subs'!$J$66:$J$99,MATCH(1,($C213&$D213='TaxCred&Subs'!$D$66:$D$99)*($F213='TaxCred&Subs'!$C$66:$C$99),0)),0)),0))),0)} -> 0 | R213: {=ROUND(IF(IFERROR(VALUE(RIGHT($AD213,1)),0)>2,IF($C213=8,N213*IFERROR(INDEX('TaxCred&Subs'!$K$139:$S$151,MATCH($C213&$D213&LEFT($AD213,7),'TaxCred&Subs'!$E$139:$E$151,0),MATCH($H213,'TaxCred&Subs'!$K$137:$S$137,0)),0),IF($C213=2,N213*IFERROR(INDEX('TaxCred&Subs'!$K$139:$S$151,MATCH($C213&$D213,'TaxCred&Subs'!$D$139:$D$151,0),MATCH($H213,'TaxCred&Subs'!$K$137:$S$137,0)),0),N213*IFERROR(INDEX('TaxCred&Subs'!$K$139:$S$151,MATCH($C213&$D213,'TaxCred&Subs'!$C$139:$C$151,0),MATCH($H213,'TaxCred&Subs'!$K$137:$S$137,0)),0))),0),0)} -> 0 | S213: {=ROUND(IF(IFERROR(VALUE(RIGHT($AD213,1)),0)>2,IF($C213=8,O213*IFERROR(INDEX('TaxCred&Subs'!$K$139:$S$151,MATCH($C213&$D213&LEFT($AD213,7),'TaxCred&Subs'!$E$139:$E$151,0),MATCH($H213,'TaxCred&Subs'!$K$137:$S$137,0)),0),IF($C213=2,O213*IFERROR(INDEX('TaxCred&Subs'!$K$139:$S$151,MATCH($C213&$D213,'TaxCred&Subs'!$D$139:$D$151,0),MATCH($H213,'TaxCred&Subs'!$K$137:$S$137,0)),0),O213*IFERROR(INDEX('TaxCred&Subs'!$K$139:$S$151,MATCH($C213&$D213,'TaxCred&Subs'!$C$139:$C$151,0),MATCH($H213,'TaxCred&Subs'!$K$137:$S$137,0)),0))),0),0)} -> 0 | T213: =IF($H213=9,IF(R213>0,(N213-P213)*0.15,0),0) -> 0 | U213: =IF($H213=9,IF(S213>0,(O213-Q213)*0.15,0),0) -> 0 | V213: MATURE | W213: 2020 | X213: 1 | Y213: 0 | Z213: -0.00020672359 | AA213: -0.003180363 | AB213: 0 | AC213: 0 | AD213: LPG_FA3
B214: =B213+1 -> 190 | C214: 1 | D214: 6 | E214: 20 | F214: 2029 | G214: 2050 | H214: 11 | I214: 20 | J214: 0 | K214: 0 | L214: 0 | M214: 0.95 | N214: 4150 | O214: 1220 | P214: {=ROUND(IF($F214<='TaxCred&Subs'!$C$49,(IF($C214=2,IF($M214>=IFERROR(INDEX('TaxCred&Subs'!$L$12:$L$47,MATCH(1,($C214&$D214='TaxCred&Subs'!$E$12:$E$47)*($F214='TaxCred&Subs'!$C$12:$C$47),0) ),9999),IFERROR(INDEX('TaxCred&Subs'!$N$12:$N$47,MATCH(1,($C214&$D214='TaxCred&Subs'!$E$12:$E$47)*($F214='TaxCred&Subs'!$C$12:$C$47),0) ),0),0),(IF($M214>=IFERROR(INDEX('TaxCred&Subs'!$H$12:$H$47,MATCH(1,($C214&$D214='TaxCred&Subs'!$D$12:$D$47)*($F214='TaxCred&Subs'!$C$12:$C$47),0) ),9999),IFERROR(INDEX('TaxCred&Subs'!$N$12:$N$47,MATCH(1,($C214&$D214='TaxCred&Subs'!$D$12:$D$47)*($F214='TaxCred&Subs'!$C$12:$C$47),0) ),0),0)))),0)+IF(AND($C214=2,VALUE(RIGHT($AD214,1))>2),(N214-R214)*(IFERROR(INDEX('TaxCred&Subs'!$J$66:$J$99,MATCH(1,($C214&$D214='TaxCred&Subs'!$E$66:$E$99)*($F214='TaxCred&Subs'!$C$66:$C$99),0)),0)),IF(AND($C214=1,VALUE(RIGHT($AD214,1))>2),(N214-R214)*(IFERROR(INDEX('TaxCred&Subs'!$J$66:$J$99,MATCH(1,($C214&$D214='TaxCred&Subs'!$D$66:$D$99)*($F214='TaxCred&Subs'!$C$66:$C$99),0)),0)),IF($C214>2,(N214-R214)*(IFERROR(INDEX('TaxCred&Subs'!$J$66:$J$99,MATCH(1,($C214&$D214='TaxCred&Subs'!$D$66:$D$99)*($F214='TaxCred&Subs'!$C$66:$C$99),0)),0)),0))),0)} -> 0 | Q214: {=ROUND(IF(AND($C214=2,VALUE(RIGHT($AD214,1))>2),(O214-S214)*(IFERROR(INDEX('TaxCred&Subs'!$J$66:$J$99,MATCH(1,($C214&$D214='TaxCred&Subs'!$E$66:$E$99)*($F214='TaxCred&Subs'!$C$66:$C$99),0)),0)),IF(AND($C214=1,VALUE(RIGHT($AD214,1))>2),(O214-S214)*(IFERROR(INDEX('TaxCred&Subs'!$J$66:$J$99,MATCH(1,($C214&$D214='TaxCred&Subs'!$D$66:$D$99)*($F214='TaxCred&Subs'!$C$66:$C$99),0)),0)),IF($C214>2,(O214-S214)*(IFERROR(INDEX('TaxCred&Subs'!$J$66:$J$99,MATCH(1,($C214&$D214='TaxCred&Subs'!$D$66:$D$99)*($F214='TaxCred&Subs'!$C$66:$C$99),0)),0)),0))),0)} -> 0 | R214: {=ROUND(IF(IFERROR(VALUE(RIGHT($AD214,1)),0)>2,IF($C214=8,N214*IFERROR(INDEX('TaxCred&Subs'!$K$139:$S$151,MATCH($C214&$D214&LEFT($AD214,7),'TaxCred&Subs'!$E$139:$E$151,0),MATCH($H214,'TaxCred&Subs'!$K$137:$S$137,0)),0),IF($C214=2,N214*IFERROR(INDEX('TaxCred&Subs'!$K$139:$S$151,MATCH($C214&$D214,'TaxCred&Subs'!$D$139:$D$151,0),MATCH($H214,'TaxCred&Subs'!$K$137:$S$137,0)),0),N214*IFERROR(INDEX('TaxCred&Subs'!$K$139:$S$151,MATCH($C214&$D214,'TaxCred&Subs'!$C$139:$C$151,0),MATCH($H214,'TaxCred&Subs'!$K$137:$S$137,0)),0))),0),0)} -> 0 | S214: {=ROUND(IF(IFERROR(VALUE(RIGHT($AD214,1)),0)>2,IF($C214=8,O214*IFERROR(INDEX('TaxCred&Subs'!$K$139:$S$151,MATCH($C214&$D214&LEFT($AD214,7),'TaxCred&Subs'!$E$139:$E$151,0),MATCH($H214,'TaxCred&Subs'!$K$137:$S$137,0)),0),IF($C214=2,O214*IFERROR(INDEX('TaxCred&Subs'!$K$139:$S$151,MATCH($C214&$D214,'TaxCred&Subs'!$D$139:$D$151,0),MATCH($H214,'TaxCred&Subs'!$K$137:$S$137,0)),0),O214*IFERROR(INDEX('TaxCred&Subs'!$K$139:$S$151,MATCH($C214&$D214,'TaxCred&Subs'!$C$139:$C$151,0),MATCH($H214,'TaxCred&Subs'!$K$137:$S$137,0)),0))),0),0)} -> 0 | T214: =IF($H214=9,IF(R214>0,(N214-P214)*0.15,0),0) -> 0 | U214: =IF($H214=9,IF(S214>0,(O214-Q214)*0.15,0),0) -> 0 | V214: MATURE | W214: 2020 | X214: 1 | Y214: 0 | Z214: -1 | AA214: -1 | AB214: 0 | AC214: 0 | AD214: LPG_FA3 | AE214: Doesn't meet or is same as 2029 standard
B215: =B214+1 -> 191 | C215: 1 | D215: 6 | E215: 21 | F215: 2020 | G215: 2021 | H215: 11 | I215: 21 | J215: 0 | K215: 0 | L215: 0 | M215: 0.99 | N215: 4320 | O215: 1390 | P215: {=ROUND(IF($F215<='TaxCred&Subs'!$C$49,(IF($C215=2,IF($M215>=IFERROR(INDEX('TaxCred&Subs'!$L$12:$L$47,MATCH(1,($C215&$D215='TaxCred&Subs'!$E$12:$E$47)*($F215='TaxCred&Subs'!$C$12:$C$47),0) ),9999),IFERROR(INDEX('TaxCred&Subs'!$N$12:$N$47,MATCH(1,($C215&$D215='TaxCred&Subs'!$E$12:$E$47)*($F215='TaxCred&Subs'!$C$12:$C$47),0) ),0),0),(IF($M215>=IFERROR(INDEX('TaxCred&Subs'!$H$12:$H$47,MATCH(1,($C215&$D215='TaxCred&Subs'!$D$12:$D$47)*($F215='TaxCred&Subs'!$C$12:$C$47),0) ),9999),IFERROR(INDEX('TaxCred&Subs'!$N$12:$N$47,MATCH(1,($C215&$D215='TaxCred&Subs'!$D$12:$D$47)*($F215='TaxCred&Subs'!$C$12:$C$47),0) ),0),0)))),0)+IF(AND($C215=2,VALUE(RIGHT($AD215,1))>2),(N215-R215)*(IFERROR(INDEX('TaxCred&Subs'!$J$66:$J$99,MATCH(1,($C215&$D215='TaxCred&Subs'!$E$66:$E$99)*($F215='TaxCred&Subs'!$C$66:$C$99),0)),0)),IF(AND($C215=1,VALUE(RIGHT($AD215,1))>2),(N215-R215)*(IFERROR(INDEX('TaxCred&Subs'!$J$66:$J$99,MATCH(1,($C215&$D215='TaxCred&Subs'!$D$66:$D$99)*($F215='TaxCred&Subs'!$C$66:$C$99),0)),0)),IF($C215>2,(N215-R215)*(IFERROR(INDEX('TaxCred&Subs'!$J$66:$J$99,MATCH(1,($C215&$D215='TaxCred&Subs'!$D$66:$D$99)*($F215='TaxCred&Subs'!$C$66:$C$99),0)),0)),0))),0)} -> 150 | Q215: {=ROUND(IF(AND($C215=2,VALUE(RIGHT($AD215,1))>2),(O215-S215)*(IFERROR(INDEX('TaxCred&Subs'!$J$66:$J$99,MATCH(1,($C215&$D215='TaxCred&Subs'!$E$66:$E$99)*($F215='TaxCred&Subs'!$C$66:$C$99),0)),0)),IF(AND($C215=1,VALUE(RIGHT($AD215,1))>2),(O215-S215)*(IFERROR(INDEX('TaxCred&Subs'!$J$66:$J$99,MATCH(1,($C215&$D215='TaxCred&Subs'!$D$66:$D$99)*($F215='TaxCred&Subs'!$C$66:$C$99),0)),0)),IF($C215>2,(O215-S215)*(IFERROR(INDEX('TaxCred&Subs'!$J$66:$J$99,MATCH(1,($C215&$D215='TaxCred&Subs'!$D$66:$D$99)*($F215='TaxCred&Subs'!$C$66:$C$99),0)),0)),0))),0)} -> 0 | R215: {=ROUND(IF(IFERROR(VALUE(RIGHT($AD215,1)),0)>2,IF($C215=8,N215*IFERROR(INDEX('TaxCred&Subs'!$K$139:$S$151,MATCH($C215&$D215&LEFT($AD215,7),'TaxCred&Subs'!$E$139:$E$151,0),MATCH($H215,'TaxCred&Subs'!$K$137:$S$137,0)),0),IF($C215=2,N215*IFERROR(INDEX('TaxCred&Subs'!$K$139:$S$151,MATCH($C215&$D215,'TaxCred&Subs'!$D$139:$D$151,0),MATCH($H215,'TaxCred&Subs'!$K$137:$S$137,0)),0),N215*IFERROR(INDEX('TaxCred&Subs'!$K$139:$S$151,MATCH($C215&$D215,'TaxCred&Subs'!$C$139:$C$151,0),MATCH($H215,'TaxCred&Subs'!$K$137:$S$137,0)),0))),0),0)} -> 0 | S215: {=ROUND(IF(IFERROR(VALUE(RIGHT($AD215,1)),0)>2,IF($C215=8,O215*IFERROR(INDEX('TaxCred&Subs'!$K$139:$S$151,MATCH($C215&$D215&LEFT($AD215,7),'TaxCred&Subs'!$E$139:$E$151,0),MATCH($H215,'TaxCred&Subs'!$K$137:$S$137,0)),0),IF($C215=2,O215*IFERROR(INDEX('TaxCred&Subs'!$K$139:$S$151,MATCH($C215&$D215,'TaxCred&Subs'!$D$139:$D$151,0),MATCH($H215,'TaxCred&Subs'!$K$137:$S$137,0)),0),O215*IFERROR(INDEX('TaxCred&Subs'!$K$139:$S$151,MATCH($C215&$D215,'TaxCred&Subs'!$C$139:$C$151,0),MATCH($H215,'TaxCred&Subs'!$K$137:$S$137,0)),0))),0),0)} -> 0 | T215: =IF($H215=9,IF(R215>0,(N215-P215)*0.15,0),0) -> 0 | U215: =IF($H215=9,IF(S215>0,(O215-Q215)*0.15,0),0) -> 0 | V215: MATURE | W215: 2020 | X215: 1 | Y215: 0 | Z215: -0.00020672359 | AA215: -0.003180363 | AB215: 0 | AC215: 0 | AD215: LPG_FA4
B216: =B215+1 -> 192 | C216: 1 | D216: 6 | E216: 21 | F216: 2022 | G216: 2032 | H216: 11 | I216: 21 | J216: 0 | K216: 0 | L216: 0 | M216: 0.99 | N216: 4320 | O216: 1390 | P216: {=ROUND(IF($F216<='TaxCred&Subs'!$C$49,(IF($C216=2,IF($M216>=IFERROR(INDEX('TaxCred&Subs'!$L$12:$L$47,MATCH(1,($C216&$D216='TaxCred&Subs'!$E$12:$E$47)*($F216='TaxCred&Subs'!$C$12:$C$47),0) ),9999),IFERROR(INDEX('TaxCred&Subs'!$N$12:$N$47,MATCH(1,($C216&$D216='TaxCred&Subs'!$E$12:$E$47)*($F216='TaxCred&Subs'!$C$12:$C$47),0) ),0),0),(IF($M216>=IFERROR(INDEX('TaxCred&Subs'!$H$12:$H$47,MATCH(1,($C216&$D216='TaxCred&Subs'!$D$12:$D$47)*($F216='TaxCred&Subs'!$C$12:$C$47),0) ),9999),IFERROR(INDEX('TaxCred&Subs'!$N$12:$N$47,MATCH(1,($C216&$D216='TaxCred&Subs'!$D$12:$D$47)*($F216='TaxCred&Subs'!$C$12:$C$47),0) ),0),0)))),0)+IF(AND($C216=2,VALUE(RIGHT($AD216,1))>2),(N216-R216)*(IFERROR(INDEX('TaxCred&Subs'!$J$66:$J$99,MATCH(1,($C216&$D216='TaxCred&Subs'!$E$66:$E$99)*($F216='TaxCred&Subs'!$C$66:$C$99),0)),0)),IF(AND($C216=1,VALUE(RIGHT($AD216,1))>2),(N216-R216)*(IFERROR(INDEX('TaxCred&Subs'!$J$66:$J$99,MATCH(1,($C216&$D216='TaxCred&Subs'!$D$66:$D$99)*($F216='TaxCred&Subs'!$C$66:$C$99),0)),0)),IF($C216>2,(N216-R216)*(IFERROR(INDEX('TaxCred&Subs'!$J$66:$J$99,MATCH(1,($C216&$D216='TaxCred&Subs'!$D$66:$D$99)*($F216='TaxCred&Subs'!$C$66:$C$99),0)),0)),0))),0)} -> 600 | Q216: {=ROUND(IF(AND($C216=2,VALUE(RIGHT($AD216,1))>2),(O216-S216)*(IFERROR(INDEX('TaxCred&Subs'!$J$66:$J$99,MATCH(1,($C216&$D216='TaxCred&Subs'!$E$66:$E$99)*($F216='TaxCred&Subs'!$C$66:$C$99),0)),0)),IF(AND($C216=1,VALUE(RIGHT($AD216,1))>2),(O216-S216)*(IFERROR(INDEX('TaxCred&Subs'!$J$66:$J$99,MATCH(1,($C216&$D216='TaxCred&Subs'!$D$66:$D$99)*($F216='TaxCred&Subs'!$C$66:$C$99),0)),0)),IF($C216>2,(O216-S216)*(IFERROR(INDEX('TaxCred&Subs'!$J$66:$J$99,MATCH(1,($C216&$D216='TaxCred&Subs'!$D$66:$D$99)*($F216='TaxCred&Subs'!$C$66:$C$99),0)),0)),0))),0)} -> 0 | R216: {=ROUND(IF(IFERROR(VALUE(RIGHT($AD216,1)),0)>2,IF($C216=8,N216*IFERROR(INDEX('TaxCred&Subs'!$K$139:$S$151,MATCH($C216&$D216&LEFT($AD216,7),'TaxCred&Subs'!$E$139:$E$151,0),MATCH($H216,'TaxCred&Subs'!$K$137:$S$137,0)),0),IF($C216=2,N216*IFERROR(INDEX('TaxCred&Subs'!$K$139:$S$151,MATCH($C216&$D216,'TaxCred&Subs'!$D$139:$D$151,0),MATCH($H216,'TaxCred&Subs'!$K$137:$S$137,0)),0),N216*IFERROR(INDEX('TaxCred&Subs'!$K$139:$S$151,MATCH($C216&$D216,'TaxCred&Subs'!$C$139:$C$151,0),MATCH($H216,'TaxCred&Subs'!$K$137:$S$137,0)),0))),0),0)} -> 0 | S216: {=ROUND(IF(IFERROR(VALUE(RIGHT($AD216,1)),0)>2,IF($C216=8,O216*IFERROR(INDEX('TaxCred&Subs'!$K$139:$S$151,MATCH($C216&$D216&LEFT($AD216,7),'TaxCred&Subs'!$E$139:$E$151,0),MATCH($H216,'TaxCred&Subs'!$K$137:$S$137,0)),0),IF($C216=2,O216*IFERROR(INDEX('TaxCred&Subs'!$K$139:$S$151,MATCH($C216&$D216,'TaxCred&Subs'!$D$139:$D$151,0),MATCH($H216,'TaxCred&Subs'!$K$137:$S$137,0)),0),O216*IFERROR(INDEX('TaxCred&Subs'!$K$139:$S$151,MATCH($C216&$D216,'TaxCred&Subs'!$C$139:$C$151,0),MATCH($H216,'TaxCred&Subs'!$K$137:$S$137,0)),0))),0),0)} -> 0 | T216: =IF($H216=9,IF(R216>0,(N216-P216)*0.15,0),0) -> 0 | U216: =IF($H216=9,IF(S216>0,(O216-Q216)*0.15,0),0) -> 0 | V216: MATURE | W216: 2020 | X216: 1 | Y216: 0 | Z216: -0.00020672359 | AA216: -0.003180363 | AB216: 0 | AC216: 0 | AD216: LPG_FA4
B217: =B216+1 -> 193 | C217: 1 | D217: 6 | E217: 21 | F217: 2033 | G217: 2050 | H217: 11 | I217: 21 | J217: 0 | K217: 0 | L217: 0 | M217: 0.99 | N217: 4320 | O217: 1390 | P217: {=ROUND(IF($F217<='TaxCred&Subs'!$C$49,(IF($C217=2,IF($M217>=IFERROR(INDEX('TaxCred&Subs'!$L$12:$L$47,MATCH(1,($C217&$D217='TaxCred&Subs'!$E$12:$E$47)*($F217='TaxCred&Subs'!$C$12:$C$47),0) ),9999),IFERROR(INDEX('TaxCred&Subs'!$N$12:$N$47,MATCH(1,($C217&$D217='TaxCred&Subs'!$E$12:$E$47)*($F217='TaxCred&Subs'!$C$12:$C$47),0) ),0),0),(IF($M217>=IFERROR(INDEX('TaxCred&Subs'!$H$12:$H$47,MATCH(1,($C217&$D217='TaxCred&Subs'!$D$12:$D$47)*($F217='TaxCred&Subs'!$C$12:$C$47),0) ),9999),IFERROR(INDEX('TaxCred&Subs'!$N$12:$N$47,MATCH(1,($C217&$D217='TaxCred&Subs'!$D$12:$D$47)*($F217='TaxCred&Subs'!$C$12:$C$47),0) ),0),0)))),0)+IF(AND($C217=2,VALUE(RIGHT($AD217,1))>2),(N217-R217)*(IFERROR(INDEX('TaxCred&Subs'!$J$66:$J$99,MATCH(1,($C217&$D217='TaxCred&Subs'!$E$66:$E$99)*($F217='TaxCred&Subs'!$C$66:$C$99),0)),0)),IF(AND($C217=1,VALUE(RIGHT($AD217,1))>2),(N217-R217)*(IFERROR(INDEX('TaxCred&Subs'!$J$66:$J$99,MATCH(1,($C217&$D217='TaxCred&Subs'!$D$66:$D$99)*($F217='TaxCred&Subs'!$C$66:$C$99),0)),0)),IF($C217>2,(N217-R217)*(IFERROR(INDEX('TaxCred&Subs'!$J$66:$J$99,MATCH(1,($C217&$D217='TaxCred&Subs'!$D$66:$D$99)*($F217='TaxCred&Subs'!$C$66:$C$99),0)),0)),0))),0)} -> 0 | Q217: {=ROUND(IF(AND($C217=2,VALUE(RIGHT($AD217,1))>2),(O217-S217)*(IFERROR(INDEX('TaxCred&Subs'!$J$66:$J$99,MATCH(1,($C217&$D217='TaxCred&Subs'!$E$66:$E$99)*($F217='TaxCred&Subs'!$C$66:$C$99),0)),0)),IF(AND($C217=1,VALUE(RIGHT($AD217,1))>2),(O217-S217)*(IFERROR(INDEX('TaxCred&Subs'!$J$66:$J$99,MATCH(1,($C217&$D217='TaxCred&Subs'!$D$66:$D$99)*($F217='TaxCred&Subs'!$C$66:$C$99),0)),0)),IF($C217>2,(O217-S217)*(IFERROR(INDEX('TaxCred&Subs'!$J$66:$J$99,MATCH(1,($C217&$D217='TaxCred&Subs'!$D$66:$D$99)*($F217='TaxCred&Subs'!$C$66:$C$99),0)),0)),0))),0)} -> 0 | R217: {=ROUND(IF(IFERROR(VALUE(RIGHT($AD217,1)),0)>2,IF($C217=8,N217*IFERROR(INDEX('TaxCred&Subs'!$K$139:$S$151,MATCH($C217&$D217&LEFT($AD217,7),'TaxCred&Subs'!$E$139:$E$151,0),MATCH($H217,'TaxCred&Subs'!$K$137:$S$137,0)),0),IF($C217=2,N217*IFERROR(INDEX('TaxCred&Subs'!$K$139:$S$151,MATCH($C217&$D217,'TaxCred&Subs'!$D$139:$D$151,0),MATCH($H217,'TaxCred&Subs'!$K$137:$S$137,0)),0),N217*IFERROR(INDEX('TaxCred&Subs'!$K$139:$S$151,MATCH($C217&$D217,'TaxCred&Subs'!$C$139:$C$151,0),MATCH($H217,'TaxCred&Subs'!$K$137:$S$137,0)),0))),0),0)} -> 0 | S217: {=ROUND(IF(IFERROR(VALUE(RIGHT($AD217,1)),0)>2,IF($C217=8,O217*IFERROR(INDEX('TaxCred&Subs'!$K$139:$S$151,MATCH($C217&$D217&LEFT($AD217,7),'TaxCred&Subs'!$E$139:$E$151,0),MATCH($H217,'TaxCred&Subs'!$K$137:$S$137,0)),0),IF($C217=2,O217*IFERROR(INDEX('TaxCred&Subs'!$K$139:$S$151,MATCH($C217&$D217,'TaxCred&Subs'!$D$139:$D$151,0),MATCH($H217,'TaxCred&Subs'!$K$137:$S$137,0)),0),O217*IFERROR(INDEX('TaxCred&Subs'!$K$139:$S$151,MATCH($C217&$D217,'TaxCred&Subs'!$C$139:$C$151,0),MATCH($H217,'TaxCred&Subs'!$K$137:$S$137,0)),0))),0),0)} -> 0 | T217: =IF($H217=9,IF(R217>0,(N217-P217)*0.15,0),0) -> 0 | U217: =IF($H217=9,IF(S217>0,(O217-Q217)*0.15,0),0) -> 0 | V217: MATURE | W217: 2020 | X217: 1 | Y217: 0 | Z217: -0.00020672359 | AA217: -0.003180363 | AB217: 0 | AC217: 0 | AD217: LPG_FA4
B218: =B217+1 -> 194 | C218: 1 | D218: 7 | E218: 22 | F218: 2020 | G218: 2050 | H218: 11 | I218: 22 | J218: 0 | K218: 0 | L218: 0 | M218: 0.83 | N218: 4885 | O218: 3035 | P218: {=ROUND(IF($F218<='TaxCred&Subs'!$C$49,(IF($C218=2,IF($M218>=IFERROR(INDEX('TaxCred&Subs'!$L$12:$L$47,MATCH(1,($C218&$D218='TaxCred&Subs'!$E$12:$E$47)*($F218='TaxCred&Subs'!$C$12:$C$47),0) ),9999),IFERROR(INDEX('TaxCred&Subs'!$N$12:$N$47,MATCH(1,($C218&$D218='TaxCred&Subs'!$E$12:$E$47)*($F218='TaxCred&Subs'!$C$12:$C$47),0) ),0),0),(IF($M218>=IFERROR(INDEX('TaxCred&Subs'!$H$12:$H$47,MATCH(1,($C218&$D218='TaxCred&Subs'!$D$12:$D$47)*($F218='TaxCred&Subs'!$C$12:$C$47),0) ),9999),IFERROR(INDEX('TaxCred&Subs'!$N$12:$N$47,MATCH(1,($C218&$D218='TaxCred&Subs'!$D$12:$D$47)*($F218='TaxCred&Subs'!$C$12:$C$47),0) ),0),0)))),0)+IF(AND($C218=2,VALUE(RIGHT($AD218,1))>2),(N218-R218)*(IFERROR(INDEX('TaxCred&Subs'!$J$66:$J$99,MATCH(1,($C218&$D218='TaxCred&Subs'!$E$66:$E$99)*($F218='TaxCred&Subs'!$C$66:$C$99),0)),0)),IF(AND($C218=1,VALUE(RIGHT($AD218,1))>2),(N218-R218)*(IFERROR(INDEX('TaxCred&Subs'!$J$66:$J$99,MATCH(1,($C218&$D218='TaxCred&Subs'!$D$66:$D$99)*($F218='TaxCred&Subs'!$C$66:$C$99),0)),0)),IF($C218>2,(N218-R218)*(IFERROR(INDEX('TaxCred&Subs'!$J$66:$J$99,MATCH(1,($C218&$D218='TaxCred&Subs'!$D$66:$D$99)*($F218='TaxCred&Subs'!$C$66:$C$99),0)),0)),0))),0)} -> 0 | Q218: {=ROUND(IF(AND($C218=2,VALUE(RIGHT($AD218,1))>2),(O218-S218)*(IFERROR(INDEX('TaxCred&Subs'!$J$66:$J$99,MATCH(1,($C218&$D218='TaxCred&Subs'!$E$66:$E$99)*($F218='TaxCred&Subs'!$C$66:$C$99),0)),0)),IF(AND($C218=1,VALUE(RIGHT($AD218,1))>2),(O218-S218)*(IFERROR(INDEX('TaxCred&Subs'!$J$66:$J$99,MATCH(1,($C218&$D218='TaxCred&Subs'!$D$66:$D$99)*($F218='TaxCred&Subs'!$C$66:$C$99),0)),0)),IF($C218>2,(O218-S218)*(IFERROR(INDEX('TaxCred&Subs'!$J$66:$J$99,MATCH(1,($C218&$D218='TaxCred&Subs'!$D$66:$D$99)*($F218='TaxCred&Subs'!$C$66:$C$99),0)),0)),0))),0)} -> 0 | R218: {=ROUND(IF(IFERROR(VALUE(RIGHT($AD218,1)),0)>2,IF($C218=8,N218*IFERROR(INDEX('TaxCred&Subs'!$K$139:$S$151,MATCH($C218&$D218&LEFT($AD218,7),'TaxCred&Subs'!$E$139:$E$151,0),MATCH($H218,'TaxCred&Subs'!$K$137:$S$137,0)),0),IF($C218=2,N218*IFERROR(INDEX('TaxCred&Subs'!$K$139:$S$151,MATCH($C218&$D218,'TaxCred&Subs'!$D$139:$D$151,0),MATCH($H218,'TaxCred&Subs'!$K$137:$S$137,0)),0),N218*IFERROR(INDEX('TaxCred&Subs'!$K$139:$S$151,MATCH($C218&$D218,'TaxCred&Subs'!$C$139:$C$151,0),MATCH($H218,'TaxCred&Subs'!$K$137:$S$137,0)),0))),0),0)} -> 0 | S218: {=ROUND(IF(IFERROR(VALUE(RIGHT($AD218,1)),0)>2,IF($C218=8,O218*IFERROR(INDEX('TaxCred&Subs'!$K$139:$S$151,MATCH($C218&$D218&LEFT($AD218,7),'TaxCred&Subs'!$E$139:$E$151,0),MATCH($H218,'TaxCred&Subs'!$K$137:$S$137,0)),0),IF($C218=2,O218*IFERROR(INDEX('TaxCred&Subs'!$K$139:$S$151,MATCH($C218&$D218,'TaxCred&Subs'!$D$139:$D$151,0),MATCH($H218,'TaxCred&Subs'!$K$137:$S$137,0)),0),O218*IFERROR(INDEX('TaxCred&Subs'!$K$139:$S$151,MATCH($C218&$D218,'TaxCred&Subs'!$C$139:$C$151,0),MATCH($H218,'TaxCred&Subs'!$K$137:$S$137,0)),0))),0),0)} -> 0 | T218: =IF($H218=9,IF(R218>0,(N218-P218)*0.15,0),0) -> 0 | U218: =IF($H218=9,IF(S218>0,(O218-Q218)*0.15,0),0) -> 0 | V218: MATURE | W218: 2020 | X218: 1 | Y218: 0 | Z218: -0.00017036065 | AA218: -0.002620933 | AB218: 0 | AC218: 0 | AD218: DIST_FA1
B219: =B218+1 -> 195 | C219: 1 | D219: 7 | E219: 23 | F219: 2020 | G219: 2050 | H219: 11 | I219: 23 | J219: 0 | K219: 0 | L219: 0 | M219: 0.85487 | N219: 5150 | O219: 3070 | P219: {=ROUND(IF($F219<='TaxCred&Subs'!$C$49,(IF($C219=2,IF($M219>=IFERROR(INDEX('TaxCred&Subs'!$L$12:$L$47,MATCH(1,($C219&$D219='TaxCred&Subs'!$E$12:$E$47)*($F219='TaxCred&Subs'!$C$12:$C$47),0) ),9999),IFERROR(INDEX('TaxCred&Subs'!$N$12:$N$47,MATCH(1,($C219&$D219='TaxCred&Subs'!$E$12:$E$47)*($F219='TaxCred&Subs'!$C$12:$C$47),0) ),0),0),(IF($M219>=IFERROR(INDEX('TaxCred&Subs'!$H$12:$H$47,MATCH(1,($C219&$D219='TaxCred&Subs'!$D$12:$D$47)*($F219='TaxCred&Subs'!$C$12:$C$47),0) ),9999),IFERROR(INDEX('TaxCred&Subs'!$N$12:$N$47,MATCH(1,($C219&$D219='TaxCred&Subs'!$D$12:$D$47)*($F219='TaxCred&Subs'!$C$12:$C$47),0) ),0),0)))),0)+IF(AND($C219=2,VALUE(RIGHT($AD219,1))>2),(N219-R219)*(IFERROR(INDEX('TaxCred&Subs'!$J$66:$J$99,MATCH(1,($C219&$D219='TaxCred&Subs'!$E$66:$E$99)*($F219='TaxCred&Subs'!$C$66:$C$99),0)),0)),IF(AND($C219=1,VALUE(RIGHT($AD219,1))>2),(N219-R219)*(IFERROR(INDEX('TaxCred&Subs'!$J$66:$J$99,MATCH(1,($C219&$D219='TaxCred&Subs'!$D$66:$D$99)*($F219='TaxCred&Subs'!$C$66:$C$99),0)),0)),IF($C219>2,(N219-R219)*(IFERROR(INDEX('TaxCred&Subs'!$J$66:$J$99,MATCH(1,($C219&$D219='TaxCred&Subs'!$D$66:$D$99)*($F219='TaxCred&Subs'!$C$66:$C$99),0)),0)),0))),0)} -> 150 | Q219: {=ROUND(IF(AND($C219=2,VALUE(RIGHT($AD219,1))>2),(O219-S219)*(IFERROR(INDEX('TaxCred&Subs'!$J$66:$J$99,MATCH(1,($C219&$D219='TaxCred&Subs'!$E$66:$E$99)*($F219='TaxCred&Subs'!$C$66:$C$99),0)),0)),IF(AND($C219=1,VALUE(RIGHT($AD219,1))>2),(O219-S219)*(IFERROR(INDEX('TaxCred&Subs'!$J$66:$J$99,MATCH(1,($C219&$D219='TaxCred&Subs'!$D$66:$D$99)*($F219='TaxCred&Subs'!$C$66:$C$99),0)),0)),IF($C219>2,(O219-S219)*(IFERROR(INDEX('TaxCred&Subs'!$J$66:$J$99,MATCH(1,($C219&$D219='TaxCred&Subs'!$D$66:$D$99)*($F219='TaxCred&Subs'!$C$66:$C$99),0)),0)),0))),0)} -> 0 | R219: {=ROUND(IF(IFERROR(VALUE(RIGHT($AD219,1)),0)>2,IF($C219=8,N219*IFERROR(INDEX('TaxCred&Subs'!$K$139:$S$151,MATCH($C219&$D219&LEFT($AD219,7),'TaxCred&Subs'!$E$139:$E$151,0),MATCH($H219,'TaxCred&Subs'!$K$137:$S$137,0)),0),IF($C219=2,N219*IFERROR(INDEX('TaxCred&Subs'!$K$139:$S$151,MATCH($C219&$D219,'TaxCred&Subs'!$D$139:$D$151,0),MATCH($H219,'TaxCred&Subs'!$K$137:$S$137,0)),0),N219*IFERROR(INDEX('TaxCred&Subs'!$K$139:$S$151,MATCH($C219&$D219,'TaxCred&Subs'!$C$139:$C$151,0),MATCH($H219,'TaxCred&Subs'!$K$137:$S$137,0)),0))),0),0)} -> 0 | S219: {=ROUND(IF(IFERROR(VALUE(RIGHT($AD219,1)),0)>2,IF($C219=8,O219*IFERROR(INDEX('TaxCred&Subs'!$K$139:$S$151,MATCH($C219&$D219&LEFT($AD219,7),'TaxCred&Subs'!$E$139:$E$151,0),MATCH($H219,'TaxCred&Subs'!$K$137:$S$137,0)),0),IF($C219=2,O219*IFERROR(INDEX('TaxCred&Subs'!$K$139:$S$151,MATCH($C219&$D219,'TaxCred&Subs'!$D$139:$D$151,0),MATCH($H219,'TaxCred&Subs'!$K$137:$S$137,0)),0),O219*IFERROR(INDEX('TaxCred&Subs'!$K$139:$S$151,MATCH($C219&$D219,'TaxCred&Subs'!$C$139:$C$151,0),MATCH($H219,'TaxCred&Subs'!$K$137:$S$137,0)),0))),0),0)} -> 0 | T219: =IF($H219=9,IF(R219>0,(N219-P219)*0.15,0),0) -> 0 | U219: =IF($H219=9,IF(S219>0,(O219-Q219)*0.15,0),0) -> 0 | V219: MATURE | W219: 2020 | X219: 1 | Y219: 0 | Z219: -0.00017036065 | AA219: -0.002620933 | AB219: 0 | AC219: 0 | AD219: DIST_FA2
B220: =B219+1 -> 196 | C220: 1 | D220: 7 | E220: 24 | F220: 2020 | G220: 2022 | H220: 11 | I220: 24 | J220: 0 | K220: 0 | L220: 0 | M220: 0.85 | N220: 5150 | O220: 3070 | P220: {=ROUND(IF($F220<='TaxCred&Subs'!$C$49,(IF($C220=2,IF($M220>=IFERROR(INDEX('TaxCred&Subs'!$L$12:$L$47,MATCH(1,($C220&$D220='TaxCred&Subs'!$E$12:$E$47)*($F220='TaxCred&Subs'!$C$12:$C$47),0) ),9999),IFERROR(INDEX('TaxCred&Subs'!$N$12:$N$47,MATCH(1,($C220&$D220='TaxCred&Subs'!$E$12:$E$47)*($F220='TaxCred&Subs'!$C$12:$C$47),0) ),0),0),(IF($M220>=IFERROR(INDEX('TaxCred&Subs'!$H$12:$H$47,MATCH(1,($C220&$D220='TaxCred&Subs'!$D$12:$D$47)*($F220='TaxCred&Subs'!$C$12:$C$47),0) ),9999),IFERROR(INDEX('TaxCred&Subs'!$N$12:$N$47,MATCH(1,($C220&$D220='TaxCred&Subs'!$D$12:$D$47)*($F220='TaxCred&Subs'!$C$12:$C$47),0) ),0),0)))),0)+IF(AND($C220=2,VALUE(RIGHT($AD220,1))>2),(N220-R220)*(IFERROR(INDEX('TaxCred&Subs'!$J$66:$J$99,MATCH(1,($C220&$D220='TaxCred&Subs'!$E$66:$E$99)*($F220='TaxCred&Subs'!$C$66:$C$99),0)),0)),IF(AND($C220=1,VALUE(RIGHT($AD220,1))>2),(N220-R220)*(IFERROR(INDEX('TaxCred&Subs'!$J$66:$J$99,MATCH(1,($C220&$D220='TaxCred&Subs'!$D$66:$D$99)*($F220='TaxCred&Subs'!$C$66:$C$99),0)),0)),IF($C220>2,(N220-R220)*(IFERROR(INDEX('TaxCred&Subs'!$J$66:$J$99,MATCH(1,($C220&$D220='TaxCred&Subs'!$D$66:$D$99)*($F220='TaxCred&Subs'!$C$66:$C$99),0)),0)),0))),0)} -> 150 | Q220: {=ROUND(IF(AND($C220=2,VALUE(RIGHT($AD220,1))>2),(O220-S220)*(IFERROR(INDEX('TaxCred&Subs'!$J$66:$J$99,MATCH(1,($C220&$D220='TaxCred&Subs'!$E$66:$E$99)*($F220='TaxCred&Subs'!$C$66:$C$99),0)),0)),IF(AND($C220=1,VALUE(RIGHT($AD220,1))>2),(O220-S220)*(IFERROR(INDEX('TaxCred&Subs'!$J$66:$J$99,MATCH(1,($C220&$D220='TaxCred&Subs'!$D$66:$D$99)*($F220='TaxCred&Subs'!$C$66:$C$99),0)),0)),IF($C220>2,(O220-S220)*(IFERROR(INDEX('TaxCred&Subs'!$J$66:$J$99,MATCH(1,($C220&$D220='TaxCred&Subs'!$D$66:$D$99)*($F220='TaxCred&Subs'!$C$66:$C$99),0)),0)),0))),0)} -> 0 | R220: {=ROUND(IF(IFERROR(VALUE(RIGHT($AD220,1)),0)>2,IF($C220=8,N220*IFERROR(INDEX('TaxCred&Subs'!$K$139:$S$151,MATCH($C220&$D220&LEFT($AD220,7),'TaxCred&Subs'!$E$139:$E$151,0),MATCH($H220,'TaxCred&Subs'!$K$137:$S$137,0)),0),IF($C220=2,N220*IFERROR(INDEX('TaxCred&Subs'!$K$139:$S$151,MATCH($C220&$D220,'TaxCred&Subs'!$D$139:$D$151,0),MATCH($H220,'TaxCred&Subs'!$K$137:$S$137,0)),0),N220*IFERROR(INDEX('TaxCred&Subs'!$K$139:$S$151,MATCH($C220&$D220,'TaxCred&Subs'!$C$139:$C$151,0),MATCH($H220,'TaxCred&Subs'!$K$137:$S$137,0)),0))),0),0)} -> 0 | S220: {=ROUND(IF(IFERROR(VALUE(RIGHT($AD220,1)),0)>2,IF($C220=8,O220*IFERROR(INDEX('TaxCred&Subs'!$K$139:$S$151,MATCH($C220&$D220&LEFT($AD220,7),'TaxCred&Subs'!$E$139:$E$151,0),MATCH($H220,'TaxCred&Subs'!$K$137:$S$137,0)),0),IF($C220=2,O220*IFERROR(INDEX('TaxCred&Subs'!$K$139:$S$151,MATCH($C220&$D220,'TaxCred&Subs'!$D$139:$D$151,0),MATCH($H220,'TaxCred&Subs'!$K$137:$S$137,0)),0),O220*IFERROR(INDEX('TaxCred&Subs'!$K$139:$S$151,MATCH($C220&$D220,'TaxCred&Subs'!$C$139:$C$151,0),MATCH($H220,'TaxCred&Subs'!$K$137:$S$137,0)),0))),0),0)} -> 0 | T220: =IF($H220=9,IF(R220>0,(N220-P220)*0.15,0),0) -> 0 | U220: =IF($H220=9,IF(S220>0,(O220-Q220)*0.15,0),0) -> 0 | V220: MATURE | W220: 2020 | X220: 1 | Y220: 0 | Z220: -0.00021648258 | AA220: -0.0033305012 | AB220: 0 | AC220: 0 | AD220: DIST_FA3
B221: =B220+1 -> 197 | C221: 1 | D221: 7 | E221: 24 | F221: 2023 | G221: 2026 | H221: 11 | I221: 24 | J221: 0 | K221: 0 | L221: 0 | M221: 0.85 | N221: 5150 | O221: 3070 | P221: {=ROUND(IF($F221<='TaxCred&Subs'!$C$49,(IF($C221=2,IF($M221>=IFERROR(INDEX('TaxCred&Subs'!$L$12:$L$47,MATCH(1,($C221&$D221='TaxCred&Subs'!$E$12:$E$47)*($F221='TaxCred&Subs'!$C$12:$C$47),0) ),9999),IFERROR(INDEX('TaxCred&Subs'!$N$12:$N$47,MATCH(1,($C221&$D221='TaxCred&Subs'!$E$12:$E$47)*($F221='TaxCred&Subs'!$C$12:$C$47),0) ),0),0),(IF($M221>=IFERROR(INDEX('TaxCred&Subs'!$H$12:$H$47,MATCH(1,($C221&$D221='TaxCred&Subs'!$D$12:$D$47)*($F221='TaxCred&Subs'!$C$12:$C$47),0) ),9999),IFERROR(INDEX('TaxCred&Subs'!$N$12:$N$47,MATCH(1,($C221&$D221='TaxCred&Subs'!$D$12:$D$47)*($F221='TaxCred&Subs'!$C$12:$C$47),0) ),0),0)))),0)+IF(AND($C221=2,VALUE(RIGHT($AD221,1))>2),(N221-R221)*(IFERROR(INDEX('TaxCred&Subs'!$J$66:$J$99,MATCH(1,($C221&$D221='TaxCred&Subs'!$E$66:$E$99)*($F221='TaxCred&Subs'!$C$66:$C$99),0)),0)),IF(AND($C221=1,VALUE(RIGHT($AD221,1))>2),(N221-R221)*(IFERROR(INDEX('TaxCred&Subs'!$J$66:$J$99,MATCH(1,($C221&$D221='TaxCred&Subs'!$D$66:$D$99)*($F221='TaxCred&Subs'!$C$66:$C$99),0)),0)),IF($C221>2,(N221-R221)*(IFERROR(INDEX('TaxCred&Subs'!$J$66:$J$99,MATCH(1,($C221&$D221='TaxCred&Subs'!$D$66:$D$99)*($F221='TaxCred&Subs'!$C$66:$C$99),0)),0)),0))),0)} -> 600 | Q221: {=ROUND(IF(AND($C221=2,VALUE(RIGHT($AD221,1))>2),(O221-S221)*(IFERROR(INDEX('TaxCred&Subs'!$J$66:$J$99,MATCH(1,($C221&$D221='TaxCred&Subs'!$E$66:$E$99)*($F221='TaxCred&Subs'!$C$66:$C$99),0)),0)),IF(AND($C221=1,VALUE(RIGHT($AD221,1))>2),(O221-S221)*(IFERROR(INDEX('TaxCred&Subs'!$J$66:$J$99,MATCH(1,($C221&$D221='TaxCred&Subs'!$D$66:$D$99)*($F221='TaxCred&Subs'!$C$66:$C$99),0)),0)),IF($C221>2,(O221-S221)*(IFERROR(INDEX('TaxCred&Subs'!$J$66:$J$99,MATCH(1,($C221&$D221='TaxCred&Subs'!$D$66:$D$99)*($F221='TaxCred&Subs'!$C$66:$C$99),0)),0)),0))),0)} -> 0 | R221: {=ROUND(IF(IFERROR(VALUE(RIGHT($AD221,1)),0)>2,IF($C221=8,N221*IFERROR(INDEX('TaxCred&Subs'!$K$139:$S$151,MATCH($C221&$D221&LEFT($AD221,7),'TaxCred&Subs'!$E$139:$E$151,0),MATCH($H221,'TaxCred&Subs'!$K$137:$S$137,0)),0),IF($C221=2,N221*IFERROR(INDEX('TaxCred&Subs'!$K$139:$S$151,MATCH($C221&$D221,'TaxCred&Subs'!$D$139:$D$151,0),MATCH($H221,'TaxCred&Subs'!$K$137:$S$137,0)),0),N221*IFERROR(INDEX('TaxCred&Subs'!$K$139:$S$151,MATCH($C221&$D221,'TaxCred&Subs'!$C$139:$C$151,0),MATCH($H221,'TaxCred&Subs'!$K$137:$S$137,0)),0))),0),0)} -> 0 | S221: {=ROUND(IF(IFERROR(VALUE(RIGHT($AD221,1)),0)>2,IF($C221=8,O221*IFERROR(INDEX('TaxCred&Subs'!$K$139:$S$151,MATCH($C221&$D221&LEFT($AD221,7),'TaxCred&Subs'!$E$139:$E$151,0),MATCH($H221,'TaxCred&Subs'!$K$137:$S$137,0)),0),IF($C221=2,O221*IFERROR(INDEX('TaxCred&Subs'!$K$139:$S$151,MATCH($C221&$D221,'TaxCred&Subs'!$D$139:$D$151,0),MATCH($H221,'TaxCred&Subs'!$K$137:$S$137,0)),0),O221*IFERROR(INDEX('TaxCred&Subs'!$K$139:$S$151,MATCH($C221&$D221,'TaxCred&Subs'!$C$139:$C$151,0),MATCH($H221,'TaxCred&Subs'!$K$137:$S$137,0)),0))),0),0)} -> 0 | T221: =IF($H221=9,IF(R221>0,(N221-P221)*0.15,0),0) -> 0 | U221: =IF($H221=9,IF(S221>0,(O221-Q221)*0.15,0),0) -> 0 | V221: MATURE | W221: 2020 | X221: 1 | Y221: 0 | Z221: -0.00021648258 | AA221: -0.0033305012 | AB221: 0 | AC221: 0 | AD221: DIST_FA3
